2-2/Bilgisayar Organizasyonu/ödevler/2024/ödev 3/sinem/22011647_riscv.v
module adder(
    input [31:0] a, b,
    output [31:0] y
);
    assign y = a + b;
endmodule

module alu (
    input [31:0] a,
    input [31:0] b,
    input [2:0] sel,
    output reg [31:0] y,
    output zero
);
    always @* begin
        case (sel)
            3'b000: y = a + b;  // add, addi
            3'b001: y = a - b;  // sub
            3'b010: y = (a < b) ? 32'b1 : 32'b0;  // slt, slti
            3'b011: y = a | b;  // or, ori
            3'b100: y = a & b;  // and, andi
            default: y = 32'b0;
        endcase
    end

    assign zero = (y == 32'b0);
endmodule

module aludec(
    input opb5,
    input [2:0] funct3,
    input funct7b5,
    input [1:0] ALUOp,
    output reg [2:0] ALUControl
);
    wire RtypeSub;
    assign RtypeSub = funct7b5 & opb5; // TRUE for R–type subtract

    always @* begin
        case(ALUOp)
            2'b00: ALUControl = 3'b000; // addition
            2'b01: ALUControl = 3'b001; // subtraction
            default: case(funct3) // R–type or I–type ALU
                3'b000: ALUControl = (RtypeSub) ? 3'b001 : 3'b000; // sub or add, addi
                3'b010: ALUControl = 3'b010; // slt, slti
                3'b110: ALUControl = 3'b011; // or, ori
                3'b111: ALUControl = 3'b100; // and, andi
                default: ALUControl = 3'bxxx; // ???
            endcase
        endcase
    end
endmodule

module controller(
    input [6:0] op,
    input [2:0] funct3,
    input funct7b5,
    input Zero,
    output [1:0] ResultSrc,
    output MemWrite,
    output PCSrc, ALUSrc,
    output RegWrite, Jump,
    output [1:0] ImmSrc,
    output [2:0] ALUControl
);
    wire [1:0] ALUOp;
    wire Branch;

    maindec md(
        .op(op), .ResultSrc(ResultSrc), .MemWrite(MemWrite), .Branch(Branch),
        .ALUSrc(ALUSrc), .RegWrite(RegWrite), .Jump(Jump), .ImmSrc(ImmSrc), .ALUOp(ALUOp)
    );

    aludec ad(
        .opb5(op[5]), .funct3(funct3), .funct7b5(funct7b5), .ALUOp(ALUOp), .ALUControl(ALUControl)
    );

    assign PCSrc = Branch & Zero | Jump;
endmodule

module datapath(
    input clk, reset,
    input [1:0] ResultSrc,
    input PCSrc, ALUSrc,
    input RegWrite,
    input [1:0] ImmSrc,
    input [2:0] ALUControl,
    output Zero,
    output [31:0] PC,
    input [31:0] Instr,
    output [31:0] ALUResult, WriteData,
    input [31:0] ReadData
);
    wire [31:0] PCNext, PCPlus4, PCTarget;
    wire [31:0] ImmExt;
    wire [31:0] SrcA, SrcB;
    wire [31:0] Result;

    // next PC logic
    flopr #(32) pcreg(.clk(clk), .reset(reset), .d(PCNext), .q(PC));
    adder pcadd4(.a(PC), .b(32'd4), .y(PCPlus4));
    adder pcaddbranch(.a(PC), .b(ImmExt), .y(PCTarget));
    mux2 #(32) pcmux(.d0(PCPlus4), .d1(PCTarget), .s(PCSrc), .y(PCNext));

    // register file logic
    regfile rf(
        .clk(clk), .we3(RegWrite), 
        .a1(Instr[19:15]), .a2(Instr[24:20]), .a3(Instr[11:7]), 
        .wd3(Result), 
        .rd1(SrcA), .rd2(WriteData)
    );

    extend ext(.instr(Instr[31:7]), .immsrc(ImmSrc), .immext(ImmExt));

    // ALU logic
    mux2 #(32) srcbmux(.d0(WriteData), .d1(ImmExt), .s(ALUSrc), .y(SrcB));
    alu alu(.a(SrcA), .b(SrcB), .sel(ALUControl), .y(ALUResult), .zero(Zero));
    mux3 #(32) resultmux(.d0(ALUResult), .d1(ReadData), .d2(PCPlus4), .s(ResultSrc), .y(Result));
endmodule

module dmem(
    input clk, we,
    input [31:0] a, wd,
    output [31:0] rd
);
    reg [31:0] RAM[63:0];

    initial begin

         //initializing the ARR Array

        RAM[0] = 3;
        RAM[1] = 7;
        RAM[2] = 2;
        RAM[3] = 6;
        RAM[4] = 5;
        RAM[5] = 4;
        RAM[6] = 1;
        RAM[7] = 1000;
        RAM[8] = 999;
        RAM[9] = 25;
        RAM[10] = 90;
        RAM[11] = 100;
        RAM[12] = 30;
        RAM[13] = 20;
        RAM[14] = 10;
        RAM[15] = 200;
        RAM[16] = 3300;
        RAM[17] = 250;
        RAM[18] = 12;
        RAM[19] = 75;

    
         //initializing the COUNT Array

        RAM[20] = 17;
        RAM[21] = 13;
        RAM[22] = 18;
        RAM[23] = 14;
        RAM[24] = 15;
        RAM[25] = 16;
        RAM[26] = 19;
        RAM[27] = 1;
        RAM[28] = 2;
        RAM[29] = 9;
        RAM[30] = 6;
        RAM[31] = 5;
        RAM[32] = 8;
        RAM[33] = 10;
        RAM[34] = 12;
        RAM[35] = 4;
        RAM[36] = 0;
        RAM[37] = 3;
        RAM[38] = 11;
        RAM[39] = 7;

        //initializing the RESULT Array

        RAM[40] = 0;
        RAM[41] = 0;
        RAM[42] = 0;
        RAM[43] = 0;
        RAM[44] = 0;
        RAM[45] = 0;
        RAM[46] = 0;
        RAM[47] = 0;
        RAM[48] = 0;
        RAM[49] = 0;
        RAM[50] = 0;
        RAM[51] = 0;
        RAM[52] = 0;
        RAM[53] = 0;
        RAM[54] = 0;
        RAM[55] = 0;
        RAM[56] = 0;
        RAM[57] = 0;
        RAM[58] = 0;
        RAM[59] = 0;

    end


    assign rd = RAM[a[31:2]]; // word aligned

    always @(posedge clk) begin
        if (we) begin
            RAM[a[31:2]] <= wd;
        end
    end
endmodule


module extend(
    input [31:7] instr,
    input [1:0] immsrc,
    output [31:0] immext
);
    reg [31:0] immext;
    always @* begin
        case(immsrc)
            // I−type
            2'b00: immext = {{20{instr[31]}}, instr[31:20]};
            // S−type (stores)
            2'b01: immext = {{20{instr[31]}}, instr[31:25], instr[11:7]};
            // B−type (branches)
            2'b10: immext = {{20{instr[31]}}, instr[7], instr[30:25], instr[11:8], 1'b0};
            // J−type (jal)
            2'b11: immext = {{12{instr[31]}}, instr[19:12], instr[20], instr[30:21], 1'b0};
            default: immext = 32'bx; // undefined
        endcase
    end
endmodule

module flopenr #(
    parameter WIDTH = 8
)(
    input clk, reset, en,
    input [WIDTH-1:0] d,
    output [WIDTH-1:0] q
);
    reg [WIDTH-1:0] q;
    always @(posedge clk or posedge reset) begin
        if (reset) q <= 0;
        else if (en) q <= d;
    end
endmodule

module flopr #(
    parameter WIDTH = 8
)(
    input clk, reset,
    input [WIDTH-1:0] d,
    output [WIDTH-1:0] q
);
    reg [WIDTH-1:0] q;
    always @(posedge clk or posedge reset) begin
        if (reset) q <= 0;
        else q <= d;
    end
endmodule

module imem(
    input [31:0] a,
    output [31:0] rd
);
    reg [31:0] RAM[63:0];

    initial begin
        $readmemh("22011647_hexcodes.txt", RAM);
    end

    assign rd = RAM[a[31:2]];
endmodule

module maindec(
    input [6:0] op,
    output reg [1:0] ResultSrc,
    output reg MemWrite,
    output reg Branch, ALUSrc,
    output reg RegWrite, Jump,
    output reg [1:0] ImmSrc,
    output reg [1:0] ALUOp
);
    always @* begin
        case(op)
            7'b0000011: {RegWrite, ImmSrc, ALUSrc, MemWrite, ResultSrc, Branch, ALUOp, Jump} = 11'b1_00_1_0_01_0_00_0; // lw 
            7'b0100011: {RegWrite, ImmSrc, ALUSrc, MemWrite, ResultSrc, Branch, ALUOp, Jump} = 11'b0_01_1_1_00_0_00_0; // sw
            7'b0110011: {RegWrite, ImmSrc, ALUSrc, MemWrite, ResultSrc, Branch, ALUOp, Jump} = 11'b1_xx_0_0_00_0_10_0; // R–type
            7'b1100011: {RegWrite, ImmSrc, ALUSrc, MemWrite, ResultSrc, Branch, ALUOp, Jump} = 11'b0_10_0_0_00_1_01_0; // beq
            7'b0010011: {RegWrite, ImmSrc, ALUSrc, MemWrite, ResultSrc, Branch, ALUOp, Jump} = 11'b1_00_1_0_00_0_10_0; // I–type ALU
            7'b1101111: {RegWrite, ImmSrc, ALUSrc, MemWrite, ResultSrc, Branch, ALUOp, Jump} = 11'b1_11_0_0_10_0_00_1; // jal
            default: {RegWrite, ImmSrc, ALUSrc, MemWrite, ResultSrc, Branch, ALUOp, Jump} = 11'bx_xx_x_x_xx_x_xx_x; // ???
        endcase
    end
endmodule

module mux2 #(
    parameter WIDTH = 8
)(
    input [WIDTH-1:0] d0, d1,
    input s,
    output [WIDTH-1:0] y
);
    assign y = s ? d1 : d0;
endmodule

module mux3 #(
    parameter WIDTH = 8
)(
    input [WIDTH-1:0] d0, d1, d2,
    input [1:0] s,
    output [WIDTH-1:0] y
);
    reg [WIDTH-1:0] y;
    always @* begin
        case(s)
            2'b00: y = d0;
            2'b01: y = d1;
            2'b10: y = d2;
            default: y = {WIDTH{1'bx}};
        endcase
    end
endmodule

module regfile(
    input clk,
    input we3,
    input [4:0] a1, a2, a3,
    input [31:0] wd3,
    output [31:0] rd1, rd2
);
    reg [31:0] rf[31:0];
    initial rf[0] = 0;

    always @(posedge clk) begin
        if (we3) begin
            rf[a3] <= wd3;
        end
    end

    assign rd1 = (a1 != 0) ? rf[a1] : 32'b0;
    assign rd2 = (a2 != 0) ? rf[a2] : 32'b0;
endmodule

module riscvsingle(
    input clk, reset,
    output [31:0] PC,
    input [31:0] Instr,
    output MemWrite,
    output [31:0] ALUResult, WriteData,
    input [31:0] ReadData
);
    wire ALUSrc, RegWrite, Jump, Zero;
    wire [1:0] ResultSrc, ImmSrc;
    wire [2:0] ALUControl;

    controller c(
        .op(Instr[6:0]), .funct3(Instr[14:12]), .funct7b5(Instr[30]), .Zero(Zero),
        .ResultSrc(ResultSrc), .MemWrite(MemWrite), .PCSrc(PCSrc),
        .ALUSrc(ALUSrc), .RegWrite(RegWrite), .Jump(Jump),
        .ImmSrc(ImmSrc), .ALUControl(ALUControl)
    );

    datapath dp(
        .clk(clk), .reset(reset), .ResultSrc(ResultSrc), .PCSrc(PCSrc),
        .ALUSrc(ALUSrc), .RegWrite(RegWrite),
        .ImmSrc(ImmSrc), .ALUControl(ALUControl),
        .Zero(Zero), .PC(PC), .Instr(Instr),
        .ALUResult(ALUResult), .WriteData(WriteData), .ReadData(ReadData)
    );
endmodule

module top(
    input clk, reset,
    output [31:0] WriteData, DataAdr,
    output MemWrite
);
    wire [31:0] PC, Instr, ReadData;

    riscvsingle rvsingle(
        .clk(clk), .reset(reset), .PC(PC), .Instr(Instr), .MemWrite(MemWrite),
        .ALUResult(DataAdr), .WriteData(WriteData), .ReadData(ReadData)
    );

    imem imem(
        .a(PC), .rd(Instr)
    );

    dmem dmem(
        .clk(clk), .we(MemWrite), .a(DataAdr), .wd(WriteData), .rd(ReadData)
    );
endmodule

2-2/Bilgisayar Organizasyonu/ödevler/2024/ödev 3/sinem/22011647_tb.v
`include "22011647_riscv.v"
module testbench();
    reg clk;
    reg reset;
    wire [31:0] WriteData, DataAdr;
    wire MemWrite;
    integer i;


    top uut (
        .clk(clk), 
        .reset(reset), 
        .WriteData(WriteData), 
        .DataAdr(DataAdr), 
        .MemWrite(MemWrite)
    );

    initial begin
        reset <= 1;
        #22; 
        reset <= 0;
    end

    always begin
        clk <= 1; 
        #1; 
        clk <= 0; 
        #1;
    end

    always @(negedge clk) begin

        /*if($time<636) begin
            $display("At time %d: DataAdr = %0d, WriteData = %0d, MemWrite = %0b", $time, DataAdr, WriteData, MemWrite);
            $display("r5: %d  r6: %d  r7: %d  , x3: %d, X2: %d , X8: %d,  x9: %d", uut.rvsingle.dp.rf.rf[5],uut.rvsingle.dp.rf.rf[6],uut.rvsingle.dp.rf.rf[7],uut.rvsingle.dp.rf.rf[3],uut.rvsingle.dp.rf.rf[2],uut.rvsingle.dp.rf.rf[8], uut.rvsingle.dp.rf.rf[9]);      
        end*/

        
        if($time>636) begin
            $display("At time %d: r3: %d", $time,uut.rvsingle.dp.rf.rf[3]);
        end

        if($time > 790) begin
            for(i=40; i<60;i=i+1)begin
                $display("RESULT[%d]: %d",i-40, uut.dmem.RAM[i]);
            end    
            $finish;
        end
    end

    initial begin
        $dumpfile("22011647.vcd"); 
        $dumpvars(0, testbench);
    end
endmodule

2-2/Bilgisayar Organizasyonu/ödevler/2024/ödev 3/sinem/22011647.vcd
$date
	Mon May 20 02:12:55 2024
$end
$version
	Icarus Verilog
$end
$timescale
	1s
$end
$scope module testbench $end
$var wire 32 ! WriteData [31:0] $end
$var wire 1 " MemWrite $end
$var wire 32 # DataAdr [31:0] $end
$var reg 1 $ clk $end
$var reg 1 % reset $end
$var integer 32 & i [31:0] $end
$scope module uut $end
$var wire 1 $ clk $end
$var wire 1 % reset $end
$var wire 32 ' WriteData [31:0] $end
$var wire 32 ( ReadData [31:0] $end
$var wire 32 ) PC [31:0] $end
$var wire 1 " MemWrite $end
$var wire 32 * Instr [31:0] $end
$var wire 32 + DataAdr [31:0] $end
$scope module dmem $end
$var wire 1 $ clk $end
$var wire 32 , rd [31:0] $end
$var wire 1 " we $end
$var wire 32 - wd [31:0] $end
$var wire 32 . a [31:0] $end
$upscope $end
$scope module imem $end
$var wire 32 / rd [31:0] $end
$var wire 32 0 a [31:0] $end
$upscope $end
$scope module rvsingle $end
$var wire 32 1 Instr [31:0] $end
$var wire 32 2 ReadData [31:0] $end
$var wire 1 $ clk $end
$var wire 1 % reset $end
$var wire 1 3 Zero $end
$var wire 32 4 WriteData [31:0] $end
$var wire 2 5 ResultSrc [1:0] $end
$var wire 1 6 RegWrite $end
$var wire 1 7 PCSrc $end
$var wire 32 8 PC [31:0] $end
$var wire 1 " MemWrite $end
$var wire 1 9 Jump $end
$var wire 2 : ImmSrc [1:0] $end
$var wire 1 ; ALUSrc $end
$var wire 32 < ALUResult [31:0] $end
$var wire 3 = ALUControl [2:0] $end
$scope module c $end
$var wire 1 7 PCSrc $end
$var wire 3 > funct3 [2:0] $end
$var wire 1 ? funct7b5 $end
$var wire 7 @ op [6:0] $end
$var wire 1 3 Zero $end
$var wire 2 A ResultSrc [1:0] $end
$var wire 1 6 RegWrite $end
$var wire 1 " MemWrite $end
$var wire 1 9 Jump $end
$var wire 2 B ImmSrc [1:0] $end
$var wire 1 C Branch $end
$var wire 1 ; ALUSrc $end
$var wire 2 D ALUOp [1:0] $end
$var wire 3 E ALUControl [2:0] $end
$scope module ad $end
$var wire 1 F RtypeSub $end
$var wire 3 G funct3 [2:0] $end
$var wire 1 ? funct7b5 $end
$var wire 1 H opb5 $end
$var wire 2 I ALUOp [1:0] $end
$var reg 3 J ALUControl [2:0] $end
$upscope $end
$scope module md $end
$var wire 7 K op [6:0] $end
$var reg 2 L ALUOp [1:0] $end
$var reg 1 ; ALUSrc $end
$var reg 1 C Branch $end
$var reg 2 M ImmSrc [1:0] $end
$var reg 1 9 Jump $end
$var reg 1 " MemWrite $end
$var reg 1 6 RegWrite $end
$var reg 2 N ResultSrc [1:0] $end
$upscope $end
$upscope $end
$scope module dp $end
$var wire 3 O ALUControl [2:0] $end
$var wire 1 ; ALUSrc $end
$var wire 2 P ImmSrc [1:0] $end
$var wire 32 Q Instr [31:0] $end
$var wire 1 7 PCSrc $end
$var wire 32 R ReadData [31:0] $end
$var wire 1 6 RegWrite $end
$var wire 2 S ResultSrc [1:0] $end
$var wire 1 $ clk $end
$var wire 1 % reset $end
$var wire 1 3 Zero $end
$var wire 32 T WriteData [31:0] $end
$var wire 32 U SrcB [31:0] $end
$var wire 32 V SrcA [31:0] $end
$var wire 32 W Result [31:0] $end
$var wire 32 X PCTarget [31:0] $end
$var wire 32 Y PCPlus4 [31:0] $end
$var wire 32 Z PCNext [31:0] $end
$var wire 32 [ PC [31:0] $end
$var wire 32 \ ImmExt [31:0] $end
$var wire 32 ] ALUResult [31:0] $end
$scope module alu $end
$var wire 3 ^ sel [2:0] $end
$var wire 1 3 zero $end
$var wire 32 _ b [31:0] $end
$var wire 32 ` a [31:0] $end
$var reg 32 a y [31:0] $end
$upscope $end
$scope module ext $end
$var wire 2 b immsrc [1:0] $end
$var wire 25 c instr [31:7] $end
$var reg 32 d immext [31:0] $end
$upscope $end
$scope module pcadd4 $end
$var wire 32 e b [31:0] $end
$var wire 32 f y [31:0] $end
$var wire 32 g a [31:0] $end
$upscope $end
$scope module pcaddbranch $end
$var wire 32 h b [31:0] $end
$var wire 32 i y [31:0] $end
$var wire 32 j a [31:0] $end
$upscope $end
$scope module pcmux $end
$var wire 32 k d0 [31:0] $end
$var wire 32 l d1 [31:0] $end
$var wire 1 7 s $end
$var wire 32 m y [31:0] $end
$var parameter 32 n WIDTH $end
$upscope $end
$scope module pcreg $end
$var wire 1 $ clk $end
$var wire 32 o d [31:0] $end
$var wire 1 % reset $end
$var parameter 32 p WIDTH $end
$var reg 32 q q [31:0] $end
$upscope $end
$scope module resultmux $end
$var wire 32 r d0 [31:0] $end
$var wire 32 s d1 [31:0] $end
$var wire 32 t d2 [31:0] $end
$var wire 2 u s [1:0] $end
$var parameter 32 v WIDTH $end
$var reg 32 w y [31:0] $end
$upscope $end
$scope module rf $end
$var wire 5 x a1 [4:0] $end
$var wire 5 y a2 [4:0] $end
$var wire 5 z a3 [4:0] $end
$var wire 1 $ clk $end
$var wire 32 { wd3 [31:0] $end
$var wire 1 6 we3 $end
$var wire 32 | rd2 [31:0] $end
$var wire 32 } rd1 [31:0] $end
$upscope $end
$scope module srcbmux $end
$var wire 32 ~ d0 [31:0] $end
$var wire 32 !" d1 [31:0] $end
$var wire 1 ; s $end
$var wire 32 "" y [31:0] $end
$var parameter 32 #" WIDTH $end
$upscope $end
$upscope $end
$upscope $end
$upscope $end
$upscope $end
$enddefinitions $end
$comment Show the parameter values. $end
$dumpall
b100000 #"
b100000 v
b100000 p
b100000 n
$end
#0
$dumpvars
b101000 ""
b101000 !"
bx ~
b0 }
bx |
b101000 {
b110 z
b1000 y
b0 x
b101000 w
b0 u
b100 t
b1011010 s
b101000 r
b0 q
b100 o
b100 m
b101000 l
b100 k
b0 j
b101000 i
b101000 h
b0 g
b100 f
b100 e
b101000 d
b1010000000000000110 c
b0 b
b101000 a
b0 `
b101000 _
b0 ^
b101000 ]
b101000 \
b0 [
b100 Z
b100 Y
b101000 X
b101000 W
b0 V
b101000 U
bx T
b0 S
b1011010 R
b10100000000000001100010011 Q
b0 P
b0 O
b0 N
b0 M
b10 L
b10011 K
b0 J
b10 I
0H
b0 G
0F
b0 E
b10 D
0C
b0 B
b0 A
b10011 @
0?
b0 >
b0 =
b101000 <
1;
b0 :
09
b0 8
07
16
b0 5
bx 4
03
b1011010 2
b10100000000000001100010011 1
b0 0
b10100000000000001100010011 /
b101000 .
bx -
b1011010 ,
b101000 +
b10100000000000001100010011 *
b0 )
b1011010 (
bx '
bx &
1%
1$
b101000 #
0"
bx !
$end
#1
0$
#2
1$
#3
0$
#4
1$
#5
0$
#6
1$
#7
0$
#8
1$
#9
0$
#10
1$
#11
0$
#12
1$
#13
0$
#14
1$
#15
0$
#16
1$
#17
0$
#18
1$
#19
0$
#20
1$
#21
0$
#22
b100 (
b100 ,
b100 2
b100 R
b100 s
b10100 W
b10100 w
b10100 {
b10100 #
b10100 +
b10100 .
b10100 <
b10100 ]
b10100 a
b10100 r
b10100 U
b10100 _
b10100 ""
b10100 \
b10100 d
b10100 h
b10100 !"
b10100 y
b101 z
b101000000000000101 c
b1000 Z
b1000 m
b1000 o
b1010000000000001010010011 *
b1010000000000001010010011 /
b1010000000000001010010011 1
b1010000000000001010010011 Q
b11000 X
b11000 i
b11000 l
b1000 Y
b1000 f
b1000 k
b1000 t
b100 )
b100 0
b100 8
b100 [
b100 g
b100 j
b100 q
1$
0%
#23
0$
#24
b100 z
b101000000000000100 c
b1100 Z
b1100 m
b1100 o
b1010000000000001000010011 *
b1010000000000001000010011 /
b1010000000000001000010011 1
b1010000000000001000010011 Q
b11100 X
b11100 i
b11100 l
b1100 Y
b1100 f
b1100 k
b1100 t
b1000 )
b1000 0
b1000 8
b1000 [
b1000 g
b1000 j
b1000 q
1$
#25
0$
#26
b100 (
b100 ,
b100 2
b100 R
b100 s
b10100 W
b10100 w
b10100 {
b1 =
b1 E
b1 J
b1 O
b1 ^
b10100 #
b10100 +
b10100 .
b10100 <
b10100 ]
b10100 a
b10100 r
1H
06
b10 :
b10 B
b10 M
b10 P
b10 b
0;
1C
b1 D
b1 I
b1 L
b101000 V
b101000 `
b101000 }
b10100 !
b10100 '
b10100 -
b10100 4
b10100 T
b10100 |
b10100 ~
b111100 \
b111100 d
b111100 h
b111100 !"
b1100011 @
b1100011 K
b110 x
b101 y
b11100 z
b1001010011000011100 c
b10000 Z
b10000 m
b10000 o
b10010100110000111001100011 *
b10010100110000111001100011 /
b10010100110000111001100011 1
b10010100110000111001100011 Q
b1001000 X
b1001000 i
b1001000 l
b10000 Y
b10000 f
b10000 k
b10000 t
b1100 )
b1100 0
b1100 8
b1100 [
b1100 g
b1100 j
b1100 q
1$
#27
0$
#28
b11 (
b11 ,
b11 2
b11 R
b11 s
b0 W
b0 w
b0 {
13
b0 #
b0 +
b0 .
b0 <
b0 ]
b0 a
b0 r
16
bx :
bx B
bx M
bx P
bx b
0C
b10 D
b10 I
b10 L
1F
b10100 V
b10100 `
b10100 }
bx \
bx d
bx h
bx !"
b110011 @
b110011 K
1?
b101 x
b100 y
b10 z
b100000001000010100000010 c
b10100 Z
b10100 m
b10100 o
b1000000010000101000000100110011 *
b1000000010000101000000100110011 /
b1000000010000101000000100110011 1
b1000000010000101000000100110011 Q
bx X
bx i
bx l
b10100 Y
b10100 f
b10100 k
b10100 t
b10000 )
b10000 0
b10000 8
b10000 [
b10000 g
b10000 j
b10000 q
1$
#29
0$
#30
b0 (
b0 ,
b0 2
b0 R
b0 s
b10100000 W
b10100000 w
b10100000 {
b10110100 X
b10110100 i
b10110100 l
b10100000 \
b10100000 d
b10100000 h
b10100000 !"
b0 =
b0 E
b0 J
b0 O
b0 ^
03
b10100000 #
b10100000 +
b10100000 .
b10100000 <
b10100000 ]
b10100000 a
b10100000 r
b10100000 U
b10100000 _
b10100000 ""
0H
b0 :
b0 B
b0 M
b0 P
b0 b
1;
0F
b0 V
b0 `
b0 }
b0 !
b0 '
b0 -
b0 4
b0 T
b0 |
b0 ~
b10011 @
b10011 K
0?
b0 x
b0 y
b1001 z
b101000000000000001001 c
b11000 Z
b11000 m
b11000 o
b1010000000000000010010010011 *
b1010000000000000010010010011 /
b1010000000000000010010010011 1
b1010000000000000010010010011 Q
b11000 Y
b11000 f
b11000 k
b11000 t
b10100 )
b10100 0
b10100 8
b10100 [
b10100 g
b10100 j
b10100 q
1$
#31
0$
#32
b11 (
b11 ,
b11 2
b11 R
b11 s
b0 W
b0 w
b0 {
13
b0 #
b0 +
b0 .
b0 <
b0 ]
b0 a
b0 r
b0 U
b0 _
b0 ""
1H
bx :
bx B
bx M
bx P
bx b
0;
bx \
bx d
bx h
bx !"
b110011 @
b110011 K
b10 x
b10 y
b10 z
b100001000000010 c
b11100 Z
b11100 m
b11100 o
b1000010000000100110011 *
b1000010000000100110011 /
b1000010000000100110011 1
b1000010000000100110011 Q
bx X
bx i
bx l
b11100 Y
b11100 f
b11100 k
b11100 t
b11000 )
b11000 0
b11000 8
b11000 [
b11000 g
b11000 j
b11000 q
1$
#33
0$
#34
b100000 Z
b100000 m
b100000 o
b100000 Y
b100000 f
b100000 k
b100000 t
b11100 )
b11100 0
b11100 8
b11100 [
b11100 g
b11100 j
b11100 q
1$
#35
0$
#36
b1011010 (
b1011010 ,
b1011010 2
b1011010 R
b1011010 s
b101000 W
b101000 w
b101000 {
03
b101000 #
b101000 +
b101000 .
b101000 <
b101000 ]
b101000 a
b101000 r
b10100 U
b10100 _
b10100 ""
b10100 V
b10100 `
b10100 }
b10100 !
b10100 '
b10100 -
b10100 4
b10100 T
b10100 |
b10100 ~
b101 x
b101 y
b11 z
b1010010100000011 c
b100100 Z
b100100 m
b100100 o
b10100101000000110110011 *
b10100101000000110110011 /
b10100101000000110110011 1
b10100101000000110110011 Q
b100100 Y
b100100 f
b100100 k
b100100 t
b100000 )
b100000 0
b100000 8
b100000 [
b100000 g
b100000 j
b100000 q
1$
#37
0$
#38
b10001 (
b10001 ,
b10001 2
b10001 R
b10001 s
b1010000 W
b1010000 w
b1010000 {
b1010000 #
b1010000 +
b1010000 .
b1010000 <
b1010000 ]
b1010000 a
b1010000 r
b101000 U
b101000 _
b101000 ""
b101000 V
b101000 `
b101000 }
b101000 !
b101000 '
b101000 -
b101000 4
b101000 T
b101000 |
b101000 ~
b11 x
b11 y
b110001100000011 c
b101000 Z
b101000 m
b101000 o
b1100011000000110110011 *
b1100011000000110110011 /
b1100011000000110110011 1
b1100011000000110110011 Q
b101000 Y
b101000 f
b101000 k
b101000 t
b100100 )
b100100 0
b100100 8
b100100 [
b100100 g
b100100 j
b100100 q
1$
#39
0$
#40
b101000 X
b101000 i
b101000 l
b0 \
b0 d
b0 h
b0 !"
13
b11 (
b11 ,
b11 2
b11 R
b11 s
b11 W
b11 w
b11 {
0H
b0 :
b0 B
b0 M
b0 P
b0 b
1;
b1 5
b1 A
b1 N
b1 S
b1 u
b0 D
b0 I
b0 L
b0 =
b0 E
b0 J
b0 O
b0 ^
b0 #
b0 +
b0 .
b0 <
b0 ]
b0 a
b0 r
b0 U
b0 _
b0 ""
b11 @
b11 K
b10 >
b10 G
b10 x
b0 y
b1000 z
b1001001000 c
b0 V
b0 `
b0 }
b0 !
b0 '
b0 -
b0 4
b0 T
b0 |
b0 ~
b101100 Z
b101100 m
b101100 o
b10010010000000011 *
b10010010000000011 /
b10010010000000011 1
b10010010000000011 Q
b101100 Y
b101100 f
b101100 k
b101100 t
b101000 )
b101000 0
b101000 8
b101000 [
b101000 g
b101000 j
b101000 q
1$
#41
0$
#42
b10001 W
b10001 w
b10001 {
b10001 (
b10001 ,
b10001 2
b10001 R
b10001 s
03
b1010000 #
b1010000 +
b1010000 .
b1010000 <
b1010000 ]
b1010000 a
b1010000 r
b1010000 V
b1010000 `
b1010000 }
b11 x
b111 z
b1101000111 c
b110000 Z
b110000 m
b110000 o
b11010001110000011 *
b11010001110000011 /
b11010001110000011 1
b11010001110000011 Q
b101100 X
b101100 i
b101100 l
b110000 Y
b110000 f
b110000 k
b110000 t
b101100 )
b101100 0
b101100 8
b101100 [
b101100 g
b101100 j
b101100 q
1$
#43
0$
#44
b1111100111 (
b1111100111 ,
b1111100111 2
b1111100111 R
b1111100111 s
b100010 W
b100010 w
b100010 {
b100010 #
b100010 +
b100010 .
b100010 <
b100010 ]
b100010 a
b100010 r
b10001 U
b10001 _
b10001 ""
1H
bx :
bx B
bx M
bx P
bx b
0;
b0 5
b0 A
b0 N
b0 S
b0 u
b10 D
b10 I
b10 L
b10001 V
b10001 `
b10001 }
b10001 !
b10001 '
b10001 -
b10001 4
b10001 T
b10001 |
b10001 ~
bx \
bx d
bx h
bx !"
b110011 @
b110011 K
b0 >
b0 G
b111 x
b111 y
b1110011100000111 c
b110100 Z
b110100 m
b110100 o
b11100111000001110110011 *
b11100111000001110110011 /
b11100111000001110110011 1
b11100111000001110110011 Q
bx X
bx i
bx l
b110100 Y
b110100 f
b110100 k
b110100 t
b110000 )
b110000 0
b110000 8
b110000 [
b110000 g
b110000 j
b110000 q
1$
#45
0$
#46
b11111010 (
b11111010 ,
b11111010 2
b11111010 R
b11111010 s
b1000100 W
b1000100 w
b1000100 {
b1000100 #
b1000100 +
b1000100 .
b1000100 <
b1000100 ]
b1000100 a
b1000100 r
b100010 U
b100010 _
b100010 ""
b100010 V
b100010 `
b100010 }
b100010 !
b100010 '
b100010 -
b100010 4
b100010 T
b100010 |
b100010 ~
b111000 Z
b111000 m
b111000 o
b111000 Y
b111000 f
b111000 k
b111000 t
b110100 )
b110100 0
b110100 8
b110100 [
b110100 g
b110100 j
b110100 q
1$
#47
0$
#48
b0 (
b0 ,
b0 2
b0 R
b0 s
b11100100 W
b11100100 w
b11100100 {
b11100100 #
b11100100 +
b11100100 .
b11100100 <
b11100100 ]
b11100100 a
b11100100 r
b1000100 U
b1000100 _
b1000100 ""
b1001 x
b1001 z
b1110100100001001 c
b10100000 V
b10100000 `
b10100000 }
b1000100 !
b1000100 '
b1000100 -
b1000100 4
b1000100 T
b1000100 |
b1000100 ~
b111100 Z
b111100 m
b111100 o
b11101001000010010110011 *
b11101001000010010110011 /
b11101001000010010110011 1
b11101001000010010110011 Q
b111100 Y
b111100 f
b111100 k
b111100 t
b111000 )
b111000 0
b111000 8
b111000 [
b111000 g
b111000 j
b111000 q
1$
#49
0$
#50
b111100 X
b111100 i
b111100 l
b0 \
b0 d
b0 h
b0 !"
03
b0 U
b0 _
b0 ""
b0 (
b0 ,
b0 2
b0 R
b0 s
b11100100 W
b11100100 w
b11100100 {
06
b1 :
b1 B
b1 M
b1 P
b1 b
1;
1"
b0 D
b0 I
b0 L
b0 =
b0 E
b0 J
b0 O
b0 ^
b11 !
b11 '
b11 -
b11 4
b11 T
b11 |
b11 ~
b11100100 #
b11100100 +
b11100100 .
b11100100 <
b11100100 ]
b11100100 a
b11100100 r
b100011 @
b100011 K
b10 >
b10 G
b1000 y
b0 z
b10000100101000000 c
b11100100 V
b11100100 `
b11100100 }
b1000000 Z
b1000000 m
b1000000 o
b100001001010000000100011 *
b100001001010000000100011 /
b100001001010000000100011 1
b100001001010000000100011 Q
b1000000 Y
b1000000 f
b1000000 k
b1000000 t
b111100 )
b111100 0
b111100 8
b111100 [
b111100 g
b111100 j
b111100 q
1$
#51
0$
