2-2/Bilgisayar Organizasyonu/ödevler/2025/yelizcengiz/computer_organization/risc_v_bit_counter_32/dmem.v
// File: dmem.v
module dmem(
    input         clk,
    input         we,
    input  [31:0] a,
    input  [31:0] wd,
    output [31:0] rd
);

  // 64 words of 32-bit data memory
  reg [31:0] RAM [0:63];

 initial begin
    RAM[0]  = 32'h00000000;
    RAM[1]  = 32'h00000001;
    RAM[2]  = 32'h00000200;
    RAM[3]  = 32'h00400000;
    RAM[4]  = 32'h80000000;
    RAM[5]  = 32'h51C06460;
    RAM[6]  = 32'hDEC287D9;
    RAM[7]  = 32'h6C896594;
    RAM[8]  = 32'h99999999;
    RAM[9]  = 32'hFFFFFFFF;
    RAM[10] = 32'h7FFFFFFF;
    RAM[11] = 32'hFFFFFFFE;
    RAM[12] = 32'hC7B52169;
    RAM[13] = 32'h8CEFF731;
    RAM[14] = 32'hA550921E;
    RAM[15] = 32'h0DB01F33;
    RAM[16] = 32'h24BB7B48;
    RAM[17] = 32'h98513914;
    RAM[18] = 32'hCD76ED30;
    RAM[19] = 32'hC0000003;
  end
  // asynchronous read (word-aligned)
  assign rd = RAM[a[31:2]];

  // synchronous write
  always @(posedge clk) begin
    if (we)
      RAM[a[31:2]] <= wd;
  end

endmodule

2-2/Bilgisayar Organizasyonu/ödevler/2025/yelizcengiz/computer_organization/risc_v_bit_counter_32/top.v
// File: top.v
module top(
    input        clk,
    input        reset,
    output reg [31:0] WriteData,
    output reg [31:0] DataAdr,
    output reg MemWrite
);
    reg [5:0] idx;
    reg [31:0] temp;
    wire [31:0] rd;
    reg [1:0] state;

    dmem mem(
        .clk(clk),
        .we(MemWrite),
        .a(DataAdr),
        .wd(WriteData),
        .rd(rd)
    );

    function [31:0] popcount;
        input [31:0] x;
        integer i;
        begin
            popcount = 0;
            for (i = 0; i < 32; i = i + 1)
                popcount = popcount + x[i];
        end
    endfunction

    always @(posedge clk) begin
        if (reset) begin
            idx <= 0;
            state <= 0;
            MemWrite <= 0;
        end else begin
            case (state)
                0: begin
                    DataAdr <= idx << 2;
                    MemWrite <= 0;
                    state <= 1;
                end
                1: begin
                    temp <= rd;
                    DataAdr <= (idx + 20) << 2;
                    WriteData <= popcount(rd);
                    MemWrite <= 1;
                    state <= 2;
                end
                2: begin
                    MemWrite <= 0;
                    idx <= idx + 1;
                    if (idx == 19)
                        state <= 3;
                    else
                        state <= 0;
                end
                3: begin
                    MemWrite <= 0;
                end
            endcase
        end
    end
endmodule

2-2/Bilgisayar Organizasyonu/ödevler/2025/yelizcengiz/computer_organization/risc_v_bit_counter_32/testbench.v
`timescale 1ns/1ps

module testbench;
    reg         clk;
    reg         reset;
    wire [31:0] WriteData;
    wire [31:0] DataAdr;
    wire        MemWrite;

    // Instantiate top
    top dut(
        .clk(clk),
        .reset(reset),
        .WriteData(WriteData),
        .DataAdr(DataAdr),
        .MemWrite(MemWrite)
    );

    // Dump waveforms for GTKWave
    initial begin
        $dumpfile("waveform.vcd");
        $dumpvars(0, testbench);
    end

    // Clock generation
    initial clk = 0;
    always #5 clk = ~clk;

    // Reset pulse
    initial begin
        reset = 1;
        #20 reset = 0;
    end

    integer i;
    initial begin
        #800;
        $display("COUNT dizisi (dmem[20] - dmem[39]):");
        for (i = 20; i < 40; i = i + 1) begin
            $display("COUNT[%0d] = %0d", i-20, dut.mem.RAM[i]);
        end
        $finish;
    end
endmodule

2-2/Bilgisayar Organizasyonu/ödevler/2025/yelizcengiz/computer_organization/risc_v_bit_counter_32/waveform.vcd
$date
	Tue May 27 21:16:36 2025
$end
$version
	Icarus Verilog
$end
$timescale
	1ps
$end
$scope module testbench $end
$var wire 32 ! WriteData [31:0] $end
$var wire 1 " MemWrite $end
$var wire 32 # DataAdr [31:0] $end
$var reg 1 $ clk $end
$var reg 1 % reset $end
$var integer 32 & i [31:0] $end
$scope module dut $end
$var wire 1 $ clk $end
$var wire 1 % reset $end
$var wire 32 ' rd [31:0] $end
$var reg 32 ( DataAdr [31:0] $end
$var reg 1 " MemWrite $end
$var reg 32 ) WriteData [31:0] $end
$var reg 6 * idx [5:0] $end
$var reg 2 + state [1:0] $end
$var reg 32 , temp [31:0] $end
$scope function popcount $end
$var reg 32 - x [31:0] $end
$var integer 32 . i [31:0] $end
$upscope $end
$scope module mem $end
$var wire 32 / a [31:0] $end
$var wire 1 $ clk $end
$var wire 32 0 rd [31:0] $end
$var wire 32 1 wd [31:0] $end
$var wire 1 " we $end
$upscope $end
$upscope $end
$upscope $end
$enddefinitions $end
$comment Show the parameter values. $end
$dumpall
$end
#0
$dumpvars
bx 1
bx 0
bx /
bx .
bx -
bx ,
bx +
bx *
bx )
bx (
bx '
bx &
1%
0$
bx #
x"
bx !
$end
#5000
0"
b0 +
b0 *
1$
#10000
0$
#15000
1$
#20000
0$
0%
#25000
b0 '
b0 0
b1 +
b0 #
b0 (
b0 /
1$
#30000
0$
#35000
bx '
bx 0
b10 +
1"
b0 !
b0 )
b0 1
b1010000 #
b1010000 (
b1010000 /
b0 ,
b100000 .
b0 -
1$
#40000
0$
#45000
b0 '
b0 0
b0 +
b1 *
0"
1$
#50000
0$
#55000
b1 '
b1 0
b1 +
b100 #
b100 (
b100 /
1$
#60000
0$
#65000
bx '
bx 0
b10 +
1"
b1 !
b1 )
b1 1
b1010100 #
b1010100 (
b1010100 /
b1 ,
b100000 .
b1 -
1$
#70000
0$
#75000
b0 +
b10 *
0"
b1 '
b1 0
1$
#80000
0$
#85000
b1000000000 '
b1000000000 0
b1 +
b1000 #
b1000 (
b1000 /
1$
#90000
0$
#95000
bx '
bx 0
b10 +
1"
b1011000 #
b1011000 (
b1011000 /
b1000000000 ,
b100000 .
b1000000000 -
1$
#100000
0$
#105000
b1 '
b1 0
b0 +
b11 *
0"
1$
#110000
0$
#115000
b10000000000000000000000 '
b10000000000000000000000 0
b1 +
b1100 #
b1100 (
b1100 /
1$
#120000
0$
#125000
bx '
bx 0
b10 +
1"
b1011100 #
b1011100 (
b1011100 /
b10000000000000000000000 ,
b100000 .
b10000000000000000000000 -
1$
#130000
0$
#135000
b0 +
b100 *
0"
b1 '
b1 0
1$
#140000
0$
#145000
b10000000000000000000000000000000 '
b10000000000000000000000000000000 0
b1 +
b10000 #
b10000 (
b10000 /
1$
#150000
0$
#155000
bx '
bx 0
b10 +
1"
b1100000 #
b1100000 (
b1100000 /
b10000000000000000000000000000000 ,
b100000 .
b10000000000000000000000000000000 -
1$
#160000
0$
#165000
b1 '
b1 0
b0 +
b101 *
0"
1$
#170000
0$
#175000
b1010001110000000110010001100000 '
b1010001110000000110010001100000 0
b1 +
b10100 #
b10100 (
b10100 /
1$
#180000
0$
#185000
bx '
bx 0
b10 +
1"
b1010 !
b1010 )
b1010 1
b1100100 #
b1100100 (
b1100100 /
b1010001110000000110010001100000 ,
b100000 .
b1010001110000000110010001100000 -
1$
#190000
0$
#195000
b0 +
b110 *
0"
b1010 '
b1010 0
1$
#200000
0$
#205000
b11011110110000101000011111011001 '
b11011110110000101000011111011001 0
b1 +
b11000 #
b11000 (
b11000 /
1$
#210000
0$
#215000
bx '
bx 0
b10 +
1"
b10010 !
b10010 )
b10010 1
b1101000 #
b1101000 (
b1101000 /
b11011110110000101000011111011001 ,
b100000 .
b11011110110000101000011111011001 -
1$
#220000
0$
#225000
b10010 '
b10010 0
b0 +
b111 *
0"
1$
#230000
0$
#235000
b1101100100010010110010110010100 '
b1101100100010010110010110010100 0
b1 +
b11100 #
b11100 (
b11100 /
1$
#240000
0$
#245000
bx '
bx 0
b10 +
1"
b1110 !
b1110 )
b1110 1
b1101100 #
b1101100 (
b1101100 /
b1101100100010010110010110010100 ,
b100000 .
b1101100100010010110010110010100 -
1$
#250000
0$
#255000
b0 +
b1000 *
0"
b1110 '
b1110 0
1$
#260000
0$
#265000
b10011001100110011001100110011001 '
b10011001100110011001100110011001 0
b1 +
b100000 #
b100000 (
b100000 /
1$
#270000
0$
#275000
bx '
bx 0
b10 +
1"
b10000 !
b10000 )
b10000 1
b1110000 #
b1110000 (
b1110000 /
b10011001100110011001100110011001 ,
b100000 .
b10011001100110011001100110011001 -
1$
#280000
0$
#285000
b10000 '
b10000 0
b0 +
b1001 *
0"
1$
#290000
0$
#295000
b11111111111111111111111111111111 '
b11111111111111111111111111111111 0
b1 +
b100100 #
b100100 (
b100100 /
1$
#300000
0$
#305000
bx '
bx 0
b10 +
1"
b100000 !
b100000 )
b100000 1
b1110100 #
b1110100 (
b1110100 /
b11111111111111111111111111111111 ,
b100000 .
b11111111111111111111111111111111 -
1$
#310000
0$
#315000
b0 +
b1010 *
0"
b100000 '
b100000 0
1$
#320000
0$
#325000
b1111111111111111111111111111111 '
b1111111111111111111111111111111 0
b1 +
b101000 #
b101000 (
b101000 /
1$
#330000
0$
#335000
bx '
bx 0
b10 +
1"
b11111 !
b11111 )
b11111 1
b1111000 #
b1111000 (
b1111000 /
b1111111111111111111111111111111 ,
b100000 .
b1111111111111111111111111111111 -
1$
#340000
0$
#345000
b11111 '
b11111 0
b0 +
b1011 *
0"
1$
#350000
0$
#355000
b11111111111111111111111111111110 '
b11111111111111111111111111111110 0
b1 +
b101100 #
b101100 (
b101100 /
1$
#360000
0$
#365000
bx '
bx 0
b10 +
1"
b1111100 #
b1111100 (
b1111100 /
b11111111111111111111111111111110 ,
b100000 .
b11111111111111111111111111111110 -
1$
#370000
0$
#375000
b0 +
b1100 *
0"
b11111 '
b11111 0
1$
#380000
0$
#385000
b11000111101101010010000101101001 '
b11000111101101010010000101101001 0
b1 +
b110000 #
b110000 (
b110000 /
1$
#390000
0$
#395000
bx '
bx 0
b10 +
1"
b10000 !
b10000 )
b10000 1
b10000000 #
b10000000 (
b10000000 /
b11000111101101010010000101101001 ,
b100000 .
b11000111101101010010000101101001 -
1$
#400000
0$
#405000
b10000 '
b10000 0
b0 +
b1101 *
0"
1$
#410000
0$
#415000
b10001100111011111111011100110001 '
b10001100111011111111011100110001 0
b1 +
b110100 #
b110100 (
b110100 /
1$
#420000
0$
#425000
bx '
bx 0
b10 +
1"
b10100 !
b10100 )
b10100 1
b10000100 #
b10000100 (
b10000100 /
b10001100111011111111011100110001 ,
b100000 .
b10001100111011111111011100110001 -
1$
#430000
0$
#435000
b0 +
b1110 *
0"
b10100 '
b10100 0
1$
#440000
0$
#445000
b10100101010100001001001000011110 '
b10100101010100001001001000011110 0
b1 +
b111000 #
b111000 (
b111000 /
1$
#450000
0$
#455000
bx '
bx 0
b10 +
1"
b1101 !
b1101 )
b1101 1
b10001000 #
b10001000 (
b10001000 /
b10100101010100001001001000011110 ,
b100000 .
b10100101010100001001001000011110 -
1$
#460000
0$
#465000
b1101 '
b1101 0
b0 +
b1111 *
0"
1$
#470000
0$
#475000
b1101101100000001111100110011 '
b1101101100000001111100110011 0
b1 +
b111100 #
b111100 (
b111100 /
1$
#480000
0$
#485000
bx '
bx 0
b10 +
1"
b1111 !
b1111 )
b1111 1
b10001100 #
b10001100 (
b10001100 /
b1101101100000001111100110011 ,
b100000 .
b1101101100000001111100110011 -
1$
#490000
0$
#495000
b0 +
b10000 *
0"
b1111 '
b1111 0
1$
#500000
0$
#505000
b100100101110110111101101001000 '
b100100101110110111101101001000 0
b1 +
b1000000 #
b1000000 (
b1000000 /
1$
#510000
0$
#515000
bx '
bx 0
b10 +
1"
b10000 !
b10000 )
b10000 1
b10010000 #
b10010000 (
b10010000 /
b100100101110110111101101001000 ,
b100000 .
b100100101110110111101101001000 -
1$
#520000
0$
#525000
b10000 '
b10000 0
b0 +
b10001 *
0"
1$
#530000
0$
#535000
b10011000010100010011100100010100 '
b10011000010100010011100100010100 0
b1 +
b1000100 #
b1000100 (
b1000100 /
1$
#540000
0$
#545000
bx '
bx 0
b10 +
1"
b1100 !
b1100 )
b1100 1
b10010100 #
b10010100 (
b10010100 /
b10011000010100010011100100010100 ,
b100000 .
b10011000010100010011100100010100 -
1$
#550000
0$
#555000
b0 +
b10010 *
0"
b1100 '
b1100 0
1$
#560000
0$
#565000
b11001101011101101110110100110000 '
b11001101011101101110110100110000 0
b1 +
b1001000 #
b1001000 (
b1001000 /
1$
#570000
0$
#575000
bx '
bx 0
b10 +
1"
b10010 !
b10010 )
b10010 1
b10011000 #
b10011000 (
b10011000 /
b11001101011101101110110100110000 ,
b100000 .
b11001101011101101110110100110000 -
1$
#580000
0$
#585000
b10010 '
b10010 0
b0 +
b10011 *
0"
1$
#590000
0$
#595000
b11000000000000000000000000000011 '
b11000000000000000000000000000011 0
b1 +
b1001100 #
b1001100 (
b1001100 /
1$
#600000
0$
#605000
bx '
bx 0
b10 +
1"
b100 !
b100 )
b100 1
b10011100 #
b10011100 (
b10011100 /
b11000000000000000000000000000011 ,
b100000 .
b11000000000000000000000000000011 -
1$
#610000
0$
#615000
b11 +
b10100 *
0"
b100 '
b100 0
1$
#620000
0$
#625000
1$
#630000
0$
#635000
1$
#640000
0$
#645000
1$
#650000
0$
#655000
1$
#660000
0$
#665000
1$
#670000
0$
#675000
1$
#680000
0$
#685000
1$
#690000
0$
#695000
1$
#700000
0$
#705000
1$
#710000
0$
#715000
1$
#720000
0$
#725000
1$
#730000
0$
#735000
1$
#740000
0$
#745000
1$
#750000
0$
#755000
1$
#760000
0$
#765000
1$
#770000
0$
#775000
1$
#780000
0$
#785000
1$
#790000
0$
#795000
1$
#800000
0$
b101000 &
