2-2/Bilgisayar Organizasyonu/ödevler/2024/tarık_taşkın/bilgisayar_organizasyonu/ödev_3/kodlar/21011022.v
module singleCycleProcessorWithSra(clk, rst);
    input clk, rst;

    wire PCSrc, regWrite, zero, memWrite, ALUSrc;
    wire [1:0] immSrc, resultSrc;
    wire [2:0] ALUControl;
    wire [31:0] PCNext, PCPlus4, PCTarget;
    wire [31:0] RD1, RD2, immExt, PC, instruction, result;
    wire [31:0] srcB, ALUResult, readData;
    
    PC pc(PC, PCNext, clk, rst);
    adder PCAdder(PCPlus4, PC, 32'd4);
    mux nextPC(PCNext, PCPlus4, PCTarget, PCSrc);
    adder jumpAdder(PCTarget, PC, immExt);

    instructionMemory instrMem(instruction, PC, rst);
    regFile regF(RD1, RD2, instruction[19:15], instruction[24:20], instruction[11:7], result, regWrite, clk, rst);
    signExtender signExt(immExt, instruction, immSrc);   
    mux muxRegtoALU(srcB, RD2, immExt, ALUSrc);
    ALU alu(ALUResult, zero, RD1, srcB, ALUControl);
    controlUnit control(PCSrc, resultSrc, memWrite, ALUControl, ALUSrc, immSrc, regWrite, instruction[6:0], instruction[14:12], instruction[31:25], zero);
    dataMemory dataMem(readData, ALUResult, RD2, memWrite, clk, rst);
    mux4 muxDatatoReg1(result, ALUResult, readData, PCPlus4, {32{1'bx}}, resultSrc);
endmodule

module ALU(result, zero, A, B, ALUControl);
    input [31:0] A, B;
    input [2:0] ALUControl;

    output [31:0] result;
    output zero;
    
    wire [31:0] sum, sra;
    wire msb;
    
    assign sum = ALUControl[0] ? (A + (~B + 1)) : (A + B);
    assign sra = $signed(A) >>> B; // sağa kaydırma işlemi A'nın MSB'i dikkate alınarak gerçekleştirilir.
    
    assign result = (ALUControl == 3'b000) ? sum :
                    (ALUControl == 3'b001) ? sum :
                    (ALUControl == 3'b010) ? A & B :
                    (ALUControl == 3'b011) ? A | B :
                    (ALUControl == 3'b100) ? sra : // sra işlemi 100 seçim bitiyle sonuç olarak çıkar.
                    (ALUControl == 3'b101) ? {{31{1'b0}}, sum[31]} :
                    {32{1'bx}};

    assign zero = (result == 32'b0);
endmodule

module adder(result, A, B);
    input [31:0] A, B;
    output [31:0] result;

    assign result = A + B;
endmodule

module PC(PC, PCNext, clk, rst);
    input [31:0] PCNext;
    input clk, rst;
    output reg [31:0] PC;

    always@(posedge clk)
        if(~rst) PC <= PCNext;
        else PC <= {32{1'b0}};
endmodule

module signExtender(immExt, instruction, immSrc);
    input [31:0] instruction;
    input [1:0] immSrc;
    output [31:0] immExt;

    assign immExt = (immSrc == 2'b00) ? {{20{instruction[31]}}, instruction[31:20]} : // I-Type
                    (immSrc == 2'b01) ? {{20{instruction[31]}}, instruction[31:25], instruction[11:7]} : // S-Type
                    (immSrc == 2'b10) ? {{19{instruction[31]}}, instruction[31], instruction[7], instruction[30:25], instruction[11:8], 1'b0} : // B-Type
                    {{12{instruction[31]}}, instruction[19:12], instruction[20], instruction[30:21], 1'b0} ; // J-Type
endmodule

module mux(result, A, B, select);
    input [31:0] A, B;
    input select;    
    output [31:0] result;

    assign result = select ? B : A;
endmodule

module mux4(result, A, B, C, D, select);
    input [31:0] A, B, C, D;
    input [1:0] select;    
    output [31:0] result;

    assign result = (select == 2'b00) ? A :
                    (select == 2'b01) ? B :
                    (select == 2'b10) ? C : D;
endmodule

module regFile(RD1, RD2, A1, A2, A3, WD3, WE3, clk, rst);
    input [4:0] A1, A2, A3;
    input clk, rst, WE3;
    input [31:0] WD3;
    output [31:0] RD1, RD2;

    reg [31:0] register[31:0];

    integer i;
    initial begin
        for (i=0; i<32; i=i+1) begin
            register[i] = 0;
        end
    end

    always@(posedge clk)
        if(WE3) register[A3] <= WD3;
    
    //aşağıda bi terslik var
    assign RD1 = (~rst) ? register[A1] : {32{1'b0}};
    assign RD2 = (~rst) ? register[A2] : {32{1'b0}};    
endmodule

module instructionMemory(RD, A, rst);
    input [31:0] A;
    input rst;
    output [31:0] RD;

    reg [31:0] memory[31:0];

    initial
        begin
            $readmemh("instructionMemory.dat", memory);
            /*
                addi   x1, x1, 40        //arr
                addi   x2, x2, 60        //count
                addi   x3, x3, 80        //result

                addi   x4, x4, 0         //Döngü Değişkeni (i=0)
                addi   x5, x5, 20        //Döngü Kontrolü (N=20)
                loop1: beq x4, x5, done1 //i>=20 olması durumunda döngü sonlanır
                lw     x6, 0(x2)         //count[i]
                lw     x7, 0(x1)         //arr[i]
                add    x3, x3, x6        //result'ı tutan register result + count[i]'yi gösterir (result[count[i]])
                sw     x7, 0(x3)         //result[count[i]] = arr[i]

                sub    x3, x3, x6        //result'u gösteren register eski yerine getirilir
                addi   x4, x4, 1         //i = i + 1
                addi   x1, x1, 1         //arr'nin bir sonraki elemanına geçilir
                addi   x2, x2, 1         //count'unn bir sonraki elemanına geçilir
                beq    x4, x4, loop1     //loop'a geri dönmek için sonucu her zaman 1 olan beq kullanılır
                done1:

                addi   x4, x0, 0         //Döngü Değişkeni (i=0)
                loop2: beq x4, x5, done2 //i>=20 olması durumunda döngü sonlanır
                lw     x6, 0(x3)         //result[i]
                addi   x4, x4, 1         //i = i + 1
                addi   x3, x3, 1         //result'un bir sonraki elemanına geçilir
                beq    x4, x4, loop2     //loop'a geri dönmek için sonucu her zaman 1 olan beq kullanılır
                done2:
                addi   x0, x0, 1         //Döngü sonlanması için eklenmiştir.
            */
        end

    assign RD = (rst) ? {32{1'b0}} : memory[A/4]; //sadece 4'ün katlarındaki verileri okumaması için

endmodule

module dataMemory(RD, A, WD, WE, clk, rst);
    input [31:0] A, WD;
    input WE, clk, rst;
    output [31:0] RD;

    reg [31:0] memory[256:0];

    initial begin          /* HEX */
        memory[40] = 3;    /* 003 */  memory[60] = 17;
        memory[41] = 7;    /* 007 */  memory[61] = 13;
        memory[42] = 2;    /* 002 */  memory[62] = 18;
        memory[43] = 6;    /* 006 */  memory[63] = 14;
        memory[44] = 5;    /* 005 */  memory[64] = 15;
        memory[45] = 4;    /* 004 */  memory[65] = 16;
        memory[46] = 1;    /* 001 */  memory[66] = 19;
        memory[47] = 1000; /* 3E8 */  memory[67] = 1;
        memory[48] = 999;  /* 3E7 */  memory[68] = 2;
        memory[49] = 25;   /* 019 */  memory[69] = 9;
        memory[50] = 90;   /* 05A */  memory[70] = 6;
        memory[51] = 100;  /* 064 */  memory[71] = 5;
        memory[52] = 30;   /* 01E */  memory[72] = 8;
        memory[53] = 20;   /* 014 */  memory[73] = 10;
        memory[54] = 10;   /* 00A */  memory[74] = 12;
        memory[55] = 200;  /* 0C8 */  memory[75] = 4;
        memory[56] = 3300; /* CE4 */  memory[76] = 0;
        memory[57] = 250;  /* 0FA */  memory[77] = 3;
        memory[58] = 12;   /* 00C */  memory[78] = 11;
        memory[59] = 75;   /* 04B */  memory[79] = 7;        
    end

    always@(posedge clk)
        if(WE) memory[A] <= WD;

    assign RD = (rst) ? {32{1'b0}} : memory[A];
endmodule

module ALUDecoder(ALUControl, funct3, funct7, op, ALUOp);
    input [2:0] funct3;
    input [6:0] funct7, op;
    input [1:0] ALUOp;
    output [2:0] ALUControl;

    assign ALUControl = (ALUOp == 2'b00) ? 3'b000 : // lw, sw (add)
                        (ALUOp == 2'b01) ? 3'b001 : // beq (sub)
                        ((ALUOp == 2'b10) & (funct3 == 3'b000) & ({op[5], funct7[5]} == 2'b11)) ? 3'b001 : // sub
                        ((ALUOp == 2'b10) & (funct3 == 3'b000) & ({op[5], funct7[5]} != 2'b11)) ? 3'b000 : // add
                        ((ALUOp == 2'b10) & (funct3 == 3'b010)) ? 3'b101 : // slt
                        ((ALUOp == 2'b10) & (funct3 == 3'b101) & ({op[5], funct7[5]} == 2'b11)) ? 3'b100 : //sra
                        ((ALUOp == 2'b10) & (funct3 == 3'b110)) ? 3'b011 : // or
                        ((ALUOp == 2'b10) & (funct3 == 3'b111)) ? 3'b010 : // and
                                                                  3'bxxx ;
endmodule

module mainDecoder(regWrite, immSrc, ALUSrc, memWrite, resultSrc, branch, ALUOp, jump, op);
    input [6:0] op;
    output regWrite, ALUSrc, memWrite, branch, jump;
    output [1:0] ALUOp, immSrc, resultSrc;

    assign regWrite = (op == 7'b0000011 | op == 7'b0110011 | op == 7'b0010011 | op == 7'b1101111) ? 1'b1 : 1'b0;
    assign immSrc = (op == 7'b0000011 | op == 7'b0010011) ? 2'b00 :
                    (op == 7'b0100011) ? 2'b01 :
                    (op == 7'b1100011) ? 2'b10 :
                    (op == 7'b1101111) ? 2'b11 : 
                    2'bxx;
    assign ALUSrc = (op == 7'b0000011 | op == 7'b0100011 | op == 7'b0010011) ? 1'b1 :
                    (op == 7'b0110011 | op == 7'b1100011) ? 1'b0 :
                    1'bx;
    assign memWrite = (op == 7'b0100011) ? 1'b1 : 1'b0;
    assign resultSrc = (op == 7'b0110011 | op == 7'b0010011) ? 2'b00 :
                       (op == 7'b0000011) ? 2'b01 : 
                       (op == 7'b1101111) ? 2'b10 :
                       2'bxx;
    assign branch = (op == 7'b1100011) ? 1'b1 : 1'b0;
    assign ALUOp = (op == 7'b0000011 | op == 7'b0100011) ? 2'b00 :
                   (op == 7'b1100011) ? 2'b01 : 
                   (op == 7'b0110011 | op == 7'b0010011) ? 2'b10 :
                   2'bxx;
    assign jump = (op == 7'b1101111) ? 1'b1 : 1'b0;
endmodule

module controlUnit(PCSrc, resultSrc, memWrite, ALUControl, ALUSrc, immSrc, regWrite, op, funct3, funct7, zero);
    input [6:0] op, funct7;
    input [2:0] funct3;
    input zero;

    output PCSrc, memWrite, ALUSrc, regWrite;
    output [1:0] resultSrc, immSrc;
    output [2:0] ALUControl;

    wire [1:0] ALUOp;
    wire branch, jump;

    mainDecoder mainDecoder(regWrite, immSrc, ALUSrc, memWrite, resultSrc, branch, ALUOp, jump, op);
    ALUDecoder ALUDecoder(ALUControl, funct3, funct7, op, ALUOp);

    assign PCSrc = (zero & branch) | jump;
endmodule

2-2/Bilgisayar Organizasyonu/ödevler/2024/tarık_taşkın/bilgisayar_organizasyonu/ödev_3/kodlar/21011022_tb.v
`include "21011022.v"

module SCPwithSra_tb();
    reg clk = 1'b1;
    reg rst = 1'b1;

    singleCycleProcessorWithSra scp(clk, rst);

    initial begin
        $dumpfile("21011022.vcd");
        $dumpvars(0, SCPwithSra_tb);
    end

    always begin
        clk = ~clk; #5;
    end

    initial begin
        rst <= 1'b0; #3145;
        rst <= 1'b1; #5;
        $finish;
    end
endmodule

//iverilog -o 21011022_tb.vvp 21011022_tb.v
//vvp 21011022_tb.vvp

2-2/Bilgisayar Organizasyonu/ödevler/2024/tarık_taşkın/bilgisayar_organizasyonu/ödev_3/kodlar/21011022.vcd
$date
	Sat May 11 19:14:17 2024
$end
$version
	Icarus Verilog
$end
$timescale
	1s
$end
$scope module SCPwithSra_tb $end
$var reg 1 ! clk $end
$var reg 1 " rst $end
$scope module scp $end
$var wire 1 ! clk $end
$var wire 1 " rst $end
$var wire 1 # zero $end
$var wire 32 $ srcB [31:0] $end
$var wire 2 % resultSrc [1:0] $end
$var wire 32 & result [31:0] $end
$var wire 1 ' regWrite $end
$var wire 32 ( readData [31:0] $end
$var wire 1 ) memWrite $end
$var wire 32 * instruction [31:0] $end
$var wire 2 + immSrc [1:0] $end
$var wire 32 , immExt [31:0] $end
$var wire 32 - RD2 [31:0] $end
$var wire 32 . RD1 [31:0] $end
$var wire 32 / PCTarget [31:0] $end
$var wire 1 0 PCSrc $end
$var wire 32 1 PCPlus4 [31:0] $end
$var wire 32 2 PCNext [31:0] $end
$var wire 32 3 PC [31:0] $end
$var wire 1 4 ALUSrc $end
$var wire 32 5 ALUResult [31:0] $end
$var wire 3 6 ALUControl [2:0] $end
$scope module PCAdder $end
$var wire 32 7 B [31:0] $end
$var wire 32 8 result [31:0] $end
$var wire 32 9 A [31:0] $end
$upscope $end
$scope module alu $end
$var wire 1 # zero $end
$var wire 32 : sum [31:0] $end
$var wire 32 ; sra [31:0] $end
$var wire 32 < result [31:0] $end
$var wire 32 = B [31:0] $end
$var wire 3 > ALUControl [2:0] $end
$var wire 32 ? A [31:0] $end
$upscope $end
$scope module control $end
$var wire 1 0 PCSrc $end
$var wire 3 @ funct3 [2:0] $end
$var wire 7 A funct7 [6:0] $end
$var wire 7 B op [6:0] $end
$var wire 1 # zero $end
$var wire 2 C resultSrc [1:0] $end
$var wire 1 ' regWrite $end
$var wire 1 ) memWrite $end
$var wire 1 D jump $end
$var wire 2 E immSrc [1:0] $end
$var wire 1 F branch $end
$var wire 1 4 ALUSrc $end
$var wire 2 G ALUOp [1:0] $end
$var wire 3 H ALUControl [2:0] $end
$scope module ALUDecoder $end
$var wire 3 I funct3 [2:0] $end
$var wire 7 J funct7 [6:0] $end
$var wire 7 K op [6:0] $end
$var wire 2 L ALUOp [1:0] $end
$var wire 3 M ALUControl [2:0] $end
$upscope $end
$scope module mainDecoder $end
$var wire 7 N op [6:0] $end
$var wire 2 O resultSrc [1:0] $end
$var wire 1 ' regWrite $end
$var wire 1 ) memWrite $end
$var wire 1 D jump $end
$var wire 2 P immSrc [1:0] $end
$var wire 1 F branch $end
$var wire 1 4 ALUSrc $end
$var wire 2 Q ALUOp [1:0] $end
$upscope $end
$upscope $end
$scope module dataMem $end
$var wire 32 R A [31:0] $end
$var wire 1 ) WE $end
$var wire 1 ! clk $end
$var wire 1 " rst $end
$var wire 32 S WD [31:0] $end
$var wire 32 T RD [31:0] $end
$upscope $end
$scope module instrMem $end
$var wire 1 " rst $end
$var wire 32 U RD [31:0] $end
$var wire 32 V A [31:0] $end
$upscope $end
$scope module jumpAdder $end
$var wire 32 W result [31:0] $end
$var wire 32 X B [31:0] $end
$var wire 32 Y A [31:0] $end
$upscope $end
$scope module muxDatatoReg1 $end
$var wire 32 Z A [31:0] $end
$var wire 32 [ B [31:0] $end
$var wire 32 \ C [31:0] $end
$var wire 32 ] D [31:0] $end
$var wire 2 ^ select [1:0] $end
$var wire 32 _ result [31:0] $end
$upscope $end
$scope module muxRegtoALU $end
$var wire 1 4 select $end
$var wire 32 ` result [31:0] $end
$var wire 32 a B [31:0] $end
$var wire 32 b A [31:0] $end
$upscope $end
$scope module nextPC $end
$var wire 32 c A [31:0] $end
$var wire 32 d B [31:0] $end
$var wire 1 0 select $end
$var wire 32 e result [31:0] $end
$upscope $end
$scope module pc $end
$var wire 32 f PCNext [31:0] $end
$var wire 1 ! clk $end
$var wire 1 " rst $end
$var reg 32 g PC [31:0] $end
$upscope $end
$scope module regF $end
$var wire 5 h A1 [4:0] $end
$var wire 5 i A2 [4:0] $end
$var wire 5 j A3 [4:0] $end
$var wire 32 k WD3 [31:0] $end
$var wire 1 ' WE3 $end
$var wire 1 ! clk $end
$var wire 1 " rst $end
$var wire 32 l RD2 [31:0] $end
$var wire 32 m RD1 [31:0] $end
$var integer 32 n i [31:0] $end
$upscope $end
$scope module signExt $end
$var wire 2 o immSrc [1:0] $end
$var wire 32 p instruction [31:0] $end
$var wire 32 q immExt [31:0] $end
$upscope $end
$upscope $end
$upscope $end
$enddefinitions $end
$comment Show the parameter values. $end
$dumpall
$end
#0
$dumpvars
b101000 q
b10100000001000000010010011 p
b0 o
b100000 n
b0 m
b0 l
b101000 k
b1 j
b1000 i
b1 h
b0 g
b100 f
b100 e
b101000 d
b100 c
b0 b
b101000 a
b101000 `
b101000 _
b0 ^
bx ]
b100 \
b11 [
b101000 Z
b0 Y
b101000 X
b101000 W
b0 V
b10100000001000000010010011 U
b11 T
b0 S
b101000 R
b10 Q
b0 P
b0 O
b10011 N
b0 M
b10 L
b10011 K
b1 J
b0 I
b0 H
b10 G
0F
b0 E
0D
b0 C
b10011 B
b1 A
b0 @
b0 ?
b0 >
b101000 =
b101000 <
b0 ;
b101000 :
b0 9
b100 8
b100 7
b0 6
b101000 5
14
b0 3
b100 2
b100 1
00
b101000 /
b0 .
b0 -
b101000 ,
b0 +
b10100000001000000010010011 *
0)
b11 (
1'
b101000 &
b0 %
b101000 $
0#
0"
0!
$end
#5
b10001 (
b10001 T
b10001 [
b111100 &
b111100 _
b111100 k
b111100 $
b111100 =
b111100 `
b111100 5
b111100 <
b111100 R
b111100 Z
b111100 ,
b111100 X
b111100 a
b111100 q
b111100 :
b10 j
b11100 i
b10 h
b0 .
b0 ?
b0 m
b11110000010000000100010011 *
b11110000010000000100010011 U
b11110000010000000100010011 p
b1000 2
b1000 e
b1000 f
b1000000 /
b1000000 W
b1000000 d
b1000 1
b1000 8
b1000 \
b1000 c
b100 3
b100 9
b100 V
b100 Y
b100 g
1!
#10
0!
#15
b1010000 $
b1010000 =
b1010000 `
bx (
bx T
bx [
b1010000 &
b1010000 _
b1010000 k
b1010000 ,
b1010000 X
b1010000 a
b1010000 q
b1010000 5
b1010000 <
b1010000 R
b1010000 Z
b10 A
b10 J
b11 j
b10000 i
b11 h
b1010000 :
b101000000011000000110010011 *
b101000000011000000110010011 U
b101000000011000000110010011 p
b1100 2
b1100 e
b1100 f
b0 .
b0 ?
b0 m
b1011000 /
b1011000 W
b1011000 d
b1100 1
b1100 8
b1100 \
b1100 c
b1000 3
b1000 9
b1000 V
b1000 Y
b1000 g
1!
#20
0!
#25
1#
b0 &
b0 _
b0 k
b0 $
b0 =
b0 `
b0 5
b0 <
b0 R
b0 Z
b0 ,
b0 X
b0 a
b0 q
b0 :
b0 A
b0 J
b100 j
b0 i
b100 h
b0 .
b0 ?
b0 m
b100000001000010011 *
b100000001000010011 U
b100000001000010011 p
b10000 2
b10000 e
b10000 f
b1100 /
b1100 W
b1100 d
b10000 1
b10000 8
b10000 \
b10000 c
b1100 3
b1100 9
b1100 V
b1100 Y
b1100 g
1!
#30
0!
#35
b10100 &
b10100 _
b10100 k
0#
b10100 5
b10100 <
b10100 R
b10100 Z
b10100 :
b10100 $
b10100 =
b10100 `
b10100 ,
b10100 X
b10100 a
b10100 q
b101 j
b10100 i
b101 h
b1010000101000001010010011 *
b1010000101000001010010011 U
b1010000101000001010010011 p
b10100 2
b10100 e
b10100 f
b100100 /
b100100 W
b100100 d
b10100 1
b10100 8
b10100 \
b10100 c
b10000 3
b10000 9
b10000 V
b10000 Y
b10000 g
1!
#40
0!
#45
00
0#
b1 6
b1 >
b1 H
b1 M
0'
bx (
bx T
bx [
bx &
bx _
bx k
b10 +
b10 E
b10 P
b10 o
04
bx %
bx C
bx O
bx ^
b1 G
b1 L
b1 Q
b11111111111111111111111111101100 5
b11111111111111111111111111101100 <
b11111111111111111111111111101100 R
b11111111111111111111111111101100 Z
b101000 ,
b101000 X
b101000 a
b101000 q
1F
b10100 -
b10100 S
b10100 b
b10100 l
b11111111111111111111111111101100 :
b1 A
b1 J
b1100011 B
b1100011 K
b1100011 N
b1000 j
b101 i
b100 h
b0 .
b0 ?
b0 m
b10010100100000010001100011 *
b10010100100000010001100011 U
b10010100100000010001100011 p
b11000 2
b11000 e
b11000 f
b111100 /
b111100 W
b111100 d
b11000 1
b11000 8
b11000 \
b11000 c
b10100 3
b10100 9
b10100 V
b10100 Y
b10100 g
1!
#50
0!
#55
b10001 &
b10001 _
b10001 k
b10001 (
b10001 T
b10001 [
1'
b111100 5
b111100 <
b111100 R
b111100 Z
b0 ,
b0 X
b0 a
b0 q
14
b0 6
b0 >
b0 H
b0 M
b0 +
b0 E
b0 P
b0 o
b1 %
b1 C
b1 O
b1 ^
b0 G
b0 L
b0 Q
b111100 ;
b0 $
b0 =
b0 `
b111100 :
0F
b0 -
b0 S
b0 b
b0 l
b111100 .
b111100 ?
b111100 m
b0 A
b0 J
b10 @
b10 I
b11 B
b11 K
b11 N
b110 j
b0 i
b10 h
b10010001100000011 *
b10010001100000011 U
b10010001100000011 p
b11100 2
b11100 e
b11100 f
b11000 /
b11000 W
b11000 d
b11100 1
b11100 8
b11100 \
b11100 c
b11000 3
b11000 9
b11000 V
b11000 Y
b11000 g
1!
#60
0!
#65
b11 &
b11 _
b11 k
b11 (
b11 T
b11 [
b101000 5
b101000 <
b101000 R
b101000 Z
b101000 :
b101000 ;
b101000 .
b101000 ?
b101000 m
b111 j
b1 h
b1010001110000011 *
b1010001110000011 U
b1010001110000011 p
b100000 2
b100000 e
b100000 f
b11100 /
b11100 W
b11100 d
b100000 1
b100000 8
b100000 \
b100000 c
b11100 3
b11100 9
b11100 V
b11100 Y
b11100 g
1!
#70
0!
#75
0#
bx (
bx T
bx [
04
b1100001 &
b1100001 _
b1100001 k
b0 6
b0 >
b0 H
b0 M
b1100001 5
b1100001 <
b1100001 R
b1100001 Z
b10001 $
b10001 =
b10001 `
bx +
bx E
bx P
bx o
b0 %
b0 C
b0 O
b0 ^
b10 G
b10 L
b10 Q
b1100001 :
b0xx000x00000000x1x ,
b0xx000x00000000x1x X
b0xx000x00000000x1x a
b0xx000x00000000x1x q
b10001 -
b10001 S
b10001 b
b10001 l
b0 ;
b1010000 .
b1010000 ?
b1010000 m
b0 @
b0 I
b110011 B
b110011 K
b110011 N
b11 j
b110 i
b11 h
b11000011000000110110011 *
b11000011000000110110011 U
b11000011000000110110011 p
b100100 2
b100100 e
b100100 f
bx /
bx W
bx d
b100100 1
b100100 8
b100100 \
b100100 c
b100000 3
b100000 9
b100000 V
b100000 Y
b100000 g
1!
#80
0!
#85
0'
b100100 /
b100100 W
b100100 d
14
bx &
bx _
bx k
b1 +
b1 E
b1 P
b1 o
bx %
bx C
bx O
bx ^
b0 G
b0 L
b0 Q
b1100001 ;
b0 $
b0 =
b0 `
b1100001 5
b1100001 <
b1100001 R
b1100001 Z
b0 ,
b0 X
b0 a
b0 q
1)
b11 -
b11 S
b11 b
b11 l
b1100001 :
b10 @
b10 I
b100011 B
b100011 K
b100011 N
b0 j
b111 i
b1100001 .
b1100001 ?
b1100001 m
b11100011010000000100011 *
b11100011010000000100011 U
b11100011010000000100011 p
b101000 2
b101000 e
b101000 f
b101000 1
b101000 8
b101000 \
b101000 c
b100100 3
b100100 9
b100100 V
b100100 Y
b100100 g
1!
#90
0!
#95
b1010000 :
1'
0#
b1010000 5
b1010000 <
b1010000 R
b1010000 Z
b0 ;
b10001 $
b10001 =
b10001 `
04
b1010000 &
b1010000 _
b1010000 k
b1 6
b1 >
b1 H
b1 M
b0xx000x10000000x1x ,
b0xx000x10000000x1x X
b0xx000x10000000x1x a
b0xx000x10000000x1x q
bx +
bx E
bx P
bx o
b0 %
b0 C
b0 O
b0 ^
b10 G
b10 L
b10 Q
0)
b10001 -
b10001 S
b10001 b
b10001 l
b100000 A
b100000 J
b0 @
b0 I
b110011 B
b110011 K
b110011 N
b11 j
b110 i
b1000000011000011000000110110011 *
b1000000011000011000000110110011 U
b1000000011000011000000110110011 p
b101100 2
b101100 e
b101100 f
bx (
bx T
bx [
bx /
bx W
bx d
b101100 1
b101100 8
b101100 \
b101100 c
b101000 3
b101000 9
b101000 V
b101000 Y
b101000 g
1!
#100
0!
#105
0#
b0 6
b0 >
b0 H
b0 M
bx (
bx T
bx [
b1 &
b1 _
b1 k
b101101 /
b101101 W
b101101 d
b0 ;
b1 5
b1 <
b1 R
b1 Z
b0 +
b0 E
b0 P
b0 o
14
b1 $
b1 =
b1 `
b1 ,
b1 X
b1 a
b1 q
b101000 -
b101000 S
b101000 b
b101000 l
b1 :
b0 A
b0 J
b10011 B
b10011 K
b10011 N
b100 j
b1 i
b100 h
b0 .
b0 ?
b0 m
b100100000001000010011 *
b100100000001000010011 U
b100100000001000010011 p
b110000 2
b110000 e
b110000 f
b110000 1
b110000 8
b110000 \
b110000 c
b101100 3
b101100 9
b101100 V
b101100 Y
b101100 g
1!
#110
0!
#115
b111 (
b111 T
b111 [
b101001 &
b101001 _
b101001 k
b10100 ;
b101001 5
b101001 <
b101001 R
b101001 Z
b1 j
b1 h
b101001 :
b100001000000010010011 *
b100001000000010010011 U
b100001000000010010011 p
b110100 2
b110100 e
b110100 f
b101000 .
b101000 ?
b101000 m
b110001 /
b110001 W
b110001 d
b110100 1
b110100 8
b110100 \
b110100 c
b110000 3
b110000 9
b110000 V
b110000 Y
b110000 g
1!
#120
0!
#125
b1101 (
b1101 T
b1101 [
b111101 &
b111101 _
b111101 k
b111101 5
b111101 <
b111101 R
b111101 Z
b11110 ;
b111101 :
b10 j
b10 h
b111100 .
b111100 ?
b111100 m
b101001 -
b101001 S
b101001 b
b101001 l
b100010000000100010011 *
b100010000000100010011 U
b100010000000100010011 p
b111000 2
b111000 e
b111000 f
b110101 /
b110101 W
b110101 d
b111000 1
b111000 8
b111000 \
b111000 c
b110100 3
b110100 9
b110100 V
b110100 Y
b110100 g
1!
#130
0!
#135
10
1#
b1 6
b1 >
b1 H
b1 M
0'
b10 +
b10 E
b10 P
b10 o
04
bx %
bx C
bx O
bx ^
b1 G
b1 L
b1 Q
bx (
bx T
bx [
bx &
bx _
bx k
b11111111111111111111111111011100 ,
b11111111111111111111111111011100 X
b11111111111111111111111111011100 a
b11111111111111111111111111011100 q
1F
b1 -
b1 S
b1 b
b1 l
b0 ;
b0 5
b0 <
b0 R
b0 Z
b1111110 A
b1111110 J
b1100011 B
b1100011 K
b1100011 N
b11101 j
b100 i
b100 h
b0 :
b11111100010000100000111011100011 *
b11111100010000100000111011100011 U
b11111100010000100000111011100011 p
b10100 2
b10100 e
b10100 f
b1 .
b1 ?
b1 m
b10100 /
b10100 W
b10100 d
b111100 1
b111100 8
b111100 \
b111100 c
b111000 3
b111000 9
b111000 V
b111000 Y
b111000 g
1!
#140
0!
#145
00
0#
b11111111111111111111111111101101 5
b11111111111111111111111111101101 <
b11111111111111111111111111101101 R
b11111111111111111111111111101101 Z
b11111111111111111111111111101101 :
b101000 ,
b101000 X
b101000 a
b101000 q
b10100 $
b10100 =
b10100 `
b10100 -
b10100 S
b10100 b
b10100 l
b1 A
b1 J
b1000 j
b101 i
b11000 2
b11000 e
b11000 f
b10010100100000010001100011 *
b10010100100000010001100011 U
b10010100100000010001100011 p
b111100 /
b111100 W
b111100 d
b11000 1
b11000 8
b11000 \
b11000 c
b10100 3
b10100 9
b10100 V
b10100 Y
b10100 g
1!
#150
0!
#155
b1101 &
b1101 _
b1101 k
b1101 (
b1101 T
b1101 [
1'
b111101 5
b111101 <
b111101 R
b111101 Z
b0 ,
b0 X
b0 a
b0 q
14
b0 6
b0 >
b0 H
b0 M
b0 +
b0 E
b0 P
b0 o
b1 %
b1 C
b1 O
b1 ^
b0 G
b0 L
b0 Q
b111101 ;
b0 $
b0 =
b0 `
b111101 :
0F
b0 -
b0 S
b0 b
b0 l
b111101 .
b111101 ?
b111101 m
b0 A
b0 J
b10 @
b10 I
b11 B
b11 K
b11 N
b110 j
b0 i
b10 h
b10010001100000011 *
b10010001100000011 U
b10010001100000011 p
b11100 2
b11100 e
b11100 f
b11000 /
b11000 W
b11000 d
b11100 1
b11100 8
b11100 \
b11100 c
b11000 3
b11000 9
b11000 V
b11000 Y
b11000 g
1!
#160
0!
#165
b111 &
b111 _
b111 k
b111 (
b111 T
b111 [
b101001 5
b101001 <
b101001 R
b101001 Z
b101001 :
b101001 ;
b101001 .
b101001 ?
b101001 m
b111 j
b1 h
b1010001110000011 *
b1010001110000011 U
b1010001110000011 p
b100000 2
b100000 e
b100000 f
b11100 /
b11100 W
b11100 d
b100000 1
b100000 8
b100000 \
b100000 c
b11100 3
b11100 9
b11100 V
b11100 Y
b11100 g
1!
#170
0!
#175
0#
bx (
bx T
bx [
04
b1011101 &
b1011101 _
b1011101 k
b0 6
b0 >
b0 H
b0 M
b1011101 5
b1011101 <
b1011101 R
b1011101 Z
b1101 $
b1101 =
b1101 `
bx +
bx E
bx P
bx o
b0 %
b0 C
b0 O
b0 ^
b10 G
b10 L
b10 Q
b1011101 :
b0xx000x00000000x1x ,
b0xx000x00000000x1x X
b0xx000x00000000x1x a
b0xx000x00000000x1x q
b1101 -
b1101 S
b1101 b
b1101 l
b0 ;
b1010000 .
b1010000 ?
b1010000 m
b0 @
b0 I
b110011 B
b110011 K
b110011 N
b11 j
b110 i
b11 h
b11000011000000110110011 *
b11000011000000110110011 U
b11000011000000110110011 p
b100100 2
b100100 e
b100100 f
bx /
bx W
bx d
b100100 1
b100100 8
b100100 \
b100100 c
b100000 3
b100000 9
b100000 V
b100000 Y
b100000 g
1!
#180
0!
#185
0'
b1011101 ;
b100100 /
b100100 W
b100100 d
14
bx &
bx _
bx k
b1 +
b1 E
b1 P
b1 o
bx %
bx C
bx O
bx ^
b0 G
b0 L
b0 Q
b0 $
b0 =
b0 `
b1011101 5
b1011101 <
b1011101 R
b1011101 Z
b0 ,
b0 X
b0 a
b0 q
1)
b111 -
b111 S
b111 b
b111 l
b1011101 :
b10 @
b10 I
b100011 B
b100011 K
b100011 N
b0 j
b111 i
b1011101 .
b1011101 ?
b1011101 m
b11100011010000000100011 *
b11100011010000000100011 U
b11100011010000000100011 p
b101000 2
b101000 e
b101000 f
b101000 1
b101000 8
b101000 \
b101000 c
b100100 3
b100100 9
b100100 V
b100100 Y
b100100 g
1!
#190
0!
