2-2/Bilgisayar Organizasyonu/ödevler/2025/ödev 3/mert_guler/mux.v
module mux_2x1 (a, b, select, out); 
    input [31:0] a, b; 
    input select;
    output [31:0] out; 
    assign out = select ? a : b; 
endmodule

module mux_4x1 (a, b, c, d, select, out); 
    input [31:0] a, b, c, d; 
    input [1:0] select;
    output [31:0] out; 
    assign out = select[1] ? (select[0] ? a : b) : (select[0] ? c : d);
endmodule

2-2/Bilgisayar Organizasyonu/ödevler/2025/ödev 2/mert_guler/Q1/data_memory.v
module data_memory(WE, clk, A, WD, RD);
    input WE, clk;
    input [31:0] A, WD;
    output [31:0] RD;
    
    reg [31:0] memory[31:0];
    
    assign RD = memory[A[31:2]];
    
    always @(posedge clk) begin
        if (WE) 
           memory[A[31:2]] <= WD;
    end
      
endmodule

2-2/Bilgisayar Organizasyonu/ödevler/2025/ödev 2/mert_guler/Q1/alu.v
module alu(A, B, ALUControl, zero, out);
  input [31:0] A, B;
  input [2:0] ALUControl;
  output reg zero;
  output reg [31:0] out;

  always @(*) begin
  zero <= (A == B);
	case (ALUControl)
		  0:  out <= A + B; // ADD
		  1:  out <= A - B; // SUB
      2:  out <= A & B; // AND
      3:  out <= A | B; // OR
      5:  out <= $signed(A) < $signed(B); // SLT
		  default: out <= 32'bx;
		endcase
  end
endmodule

2-2/Bilgisayar Organizasyonu/ödevler/2025/ödev 2/mert_guler/Q1/extend.v
module extend(instr, ImmSrc, ImmExt);
    input [31:7] instr;
    input [1:0] ImmSrc;
    output reg [31:0] ImmExt;
    
    always@(*) begin
    case(ImmSrc)
        2'b00: ImmExt = {{20{instr[31]}}, instr[31:20]}; // I
        2'b01: ImmExt = {{20{instr[31]}}, instr[31:25], instr[11:7]}; // S
        2'b10: ImmExt = {{20{instr[31]}}, instr[7], instr[30:25], instr[11:8], 1'b0}; // B
        2'b11: ImmExt = {{12{instr[31]}}, instr[19:12], instr[20], instr[30:21], 1'b0}; // J
    endcase    
    end    
endmodule

2-2/Bilgisayar Organizasyonu/ödevler/2025/ödev 2/mert_guler/Q1/register.v
module register(WE3, clk, A1, A2, A3, WD3, RD1, RD2);
    input WE3, clk;
    input [4:0] A1, A2, A3;
    input [31:0] WD3;
    output reg [31:0] RD1, RD2;
    reg [31:0] registerFile[31:0];
    
    always@(posedge clk)
    if (WE3)
        registerFile[A3] <= WD3;
    
    always@(*) begin
        RD1 = (A1 != 0) ? registerFile[A1] : 0;
        RD2 = (A2 != 0) ? registerFile[A2] : 0;
    end

endmodule

2-2/Bilgisayar Organizasyonu/ödevler/2025/ödev 2/mert_guler/Q1/adder.v
module adder (A, B, PCTarget);
    input [31:0] A, B;
    output [31:0] PCTarget;
    assign PCTarget = A + B;
endmodule

module add4 (A, out);
    input [31:0] A;
    output [31:0] out;
    assign out = A + 4;
endmodule

2-2/Bilgisayar Organizasyonu/ödevler/2025/ödev 2/mert_guler/Q1/controller.v
module alu_decoder(op5, funct3, funct7, ALUOp, ALUControl);
    input op5;
    input [2:0] funct3;
    input funct7;
    input [1:0] ALUOp;
    output reg [2:0] ALUControl;

    always @(*) begin
        case (ALUOp)
            2'b00: ALUControl <= 3'b000;
            2'b01: ALUControl <= 3'b001;
            2'b10: begin
                case(funct3)
                    3'b000: begin
                        case({op5, funct7})
                            2'b11: ALUControl <= 3'b001; // SUB
                            default: ALUControl <= 3'b000; // ADD
                        endcase
                    end
                    3'b010: ALUControl <= 3'b101; // SLT
                    3'b110: ALUControl <= 3'b011; // OR
                    3'b111: ALUControl <= 3'b010; // AND
                endcase
            end
        endcase
    end
endmodule

module main_decoder(op, ResultSrc, MemWrite, Branch, Jump, ALUOp, ALUSrc, 
                    ImmSrc, RegWrite);
    input [6:0] op;
    output reg [1:0] ResultSrc, ALUOp, ImmSrc;
    output reg MemWrite, Branch, Jump, ALUSrc, RegWrite;

    always @(*) begin
    	case (op)
            7'b0000011: begin // lw
                RegWrite <= 1;
                MemWrite <= 0;
                Branch <= 0;
                ALUSrc <= 1;
                ALUOp <= 2'b00;
                ImmSrc <= 2'b00;
                ResultSrc <= 2'b01;
                Jump <= 0;
            end
			7'b0010011: begin // I-type
    			RegWrite <= 1;
                MemWrite <= 0;
                Branch <= 0; 
                ALUSrc <= 1; 
                ImmSrc <= 2'b00; 
                ResultSrc <= 2'b00; 
				ALUOp <= 2'b10;
                Jump <= 0;
			end
            	7'b0100011: begin // sw
    			RegWrite <= 0;
                MemWrite <= 1;
                Branch <= 0;
                ALUSrc <= 1;
                ALUOp <= 2'b00;
                ImmSrc <= 2'b01;
                ResultSrc <= 2'bx;
                Jump <= 0;
			end	
                7'b0110011: begin // R-type
    			RegWrite <= 1;
                MemWrite <= 0;
                Branch <= 0; 
                ALUSrc <= 0; 
                ImmSrc <= 2'bx; 
                ResultSrc <= 2'b00; 
                ALUOp <= 2'b10;
                Jump <= 0;
			end		
			7'b1100011: begin	// beq
    			RegWrite <= 0;
                MemWrite <= 0;
                Branch <= 1;
                ALUSrc <= 0;
                ALUOp <= 2'b01;
                ImmSrc <= 2'b10;
                ResultSrc <= 2'bxx;
                Jump <= 0;
			end			
			7'b1101111: begin	// jal
                RegWrite <= 1;
                MemWrite <= 0;
                Branch <= 0;
                ALUSrc <= 1'bx;
                ALUOp <= 2'bxx;
                ImmSrc <= 2'b11;
                ResultSrc <= 2'b10;
                Jump <= 1;
    		end
		endcase
	end
endmodule

module controller(op, funct3, funct7, Zero, PCSrc, ResultSrc, MemWrite, ALUControl,
                ALUSrc, ImmSrc, RegWrite);
    input [6:0] op;
    input [2:0] funct3;
    input funct7, Zero;
    output [2:0] ALUControl;
    output [1:0] ImmSrc, ResultSrc;
    output PCSrc, MemWrite, ALUSrc, RegWrite;

    wire Branch, Jump, temp;
    wire [1:0] ALUOp;

    main_decoder main_decoder(op, ResultSrc, MemWrite, Branch, Jump, ALUOp, ALUSrc, ImmSrc, RegWrite);
    alu_decoder alu_decoder(op[5], funct3, funct7, ALUOp, ALUControl);
    assign PCSrc = (Branch & Zero) | Jump;
endmodule

2-2/Bilgisayar Organizasyonu/ödevler/2025/ödev 2/mert_guler/Q1/instruction_memory.v
module instruction_memory(A, RD);
    input [31:0] A;
    output reg [31:0] RD;
    
    reg [31:0] memory[31:0];

    initial begin
        memory[0] = 32'h00100093; // addi x1, x0, 1
        memory[1] = 32'h00200113; // addi x2, x0, 2
        memory[2] = 32'h002081B3; // add x3, x1, x2 -> 3
        memory[3] = 32'h40218233; // sub x4, x3, x2 -> 1
        memory[4] = 32'h0041A2B3; // slt x5, x3, x4 -> 0
        memory[5] = 32'h0031e333; // or x6, x3, x3 -> 3
        memory[6] = 32'h0031f3b3; // and x7, x3, x3 -> 3
        memory[7] = 32'h00100413; // addi x8, x0, 1 -> 1
        memory[8] = 32'h00702023; // sw x7, 0(x0) -> mem(0) = 1
        memory[9] = 32'h00312493; // slti x9, x2, 3 -> 1
        memory[10] = 32'h00016513; // ori x10, x2, 0 -> 2
        memory[11] = 32'h00517593; // andi x11, x2, 5 -> 0
        memory[12] = 32'h00002603; // lw x12, 0(x0) -> 1
        memory[13] = 32'h004006ef; // jal x13, 4 -> 00000038
        memory[14] = 32'h02618063; // beq x3, x6, +32 -> 00000058
    end

    always @(*) begin
        RD = memory[A[31:2]];
    end
endmodule

2-2/Bilgisayar Organizasyonu/ödevler/2025/ödev 2/mert_guler/Q1/program_counter.v
module program_counter(reset, clk, pc_in, pc_out);
    input clk, reset;
    input [31:0] pc_in;
    output reg [31:0] pc_out;

    always@(posedge clk)
    if (reset)
        pc_out <= 32'b00000000;
    else
        pc_out <= pc_in;    

endmodule

2-2/Bilgisayar Organizasyonu/ödevler/2025/ödev 2/mert_guler/Q1/processor.v
`include "program_counter.v"
`include "adder.v"
`include "controller.v"
`include "extend.v"
`include "data_memory.v"
`include "instruction_memory.v"
`include "mux.v"
`include "register.v"
`include "alu.v"

module processor(
    input clk, reset,
    output Zero,
    output [31:0] PC,
    output [31:0] WriteData,
    output [31:0] ReadData,
    output [31:0] ALUResult
);

wire [31:0] PCNext, PCPlus4, ImmExt, PCTarget, Result, SrcA, SrcB;
wire [31:0] instruction;
wire PCSrc, ALUSrc, RegWrite, MemWrite;
wire [1:0] ResultSrc, ImmSrc;
wire [2:0] ALUControl;

program_counter pc(reset, clk, PCNext, PC);
instruction_memory im(PC, instruction);

controller controller(
    instruction[6:0], instruction[14:12], instruction[30], Zero,
    PCSrc, ResultSrc, MemWrite, ALUControl, ALUSrc, ImmSrc, RegWrite
    );

add4 add4(PC, PCPlus4);
adder adder(PC, ImmExt, PCTarget);
mux_2x1 mux1(PCTarget, PCPlus4, PCSrc, PCNext);

register register(RegWrite, clk, instruction[19:15], instruction[24:20], instruction[11:7], Result, SrcA, WriteData);
extend ext(instruction[31:7], ImmSrc, ImmExt);

mux_2x1 mux2(ImmExt, WriteData, ALUSrc, SrcB);
alu alu(SrcA, SrcB, ALUControl, Zero, ALUResult);
    
data_memory dm(MemWrite, clk, ALUResult, WriteData, ReadData);
    
mux_4x1 mux3(32'bx, PCPlus4, ReadData, ALUResult, ResultSrc, Result);

endmodule

2-2/Bilgisayar Organizasyonu/ödevler/2025/ödev 2/mert_guler/Q1/processor_tb.v
`timescale 1ns / 1ps
`include "processor.v"

// iverilog -o processor processor_tb.v
// vvp processor  
// gtkwave processor_tb.vcd 

module processor_tb;
  reg clk;
  reg reset;
  wire Zero;
  wire [31:0] PC;
  wire [31:0] WriteData;
  wire [31:0] ReadData;
  wire [31:0] ALUResult;

  processor processor (
    .clk(clk),
    .reset(reset),
    .Zero(Zero),
    .PC(PC),
    .WriteData(WriteData),
    .ReadData(ReadData),
    .ALUResult(ALUResult)
  );

  initial clk = 0;
  always #5 clk = ~clk;

  initial begin
    $dumpfile("processor_tb.vcd");
    $dumpvars(0, processor);

    reset = 1;
    #20;
    reset = 0;

    #500;

    $display("x1 = %d", processor.register.registerFile[1]); // Beklenen: 1
    $display("x2 = %d", processor.register.registerFile[2]); // Beklenen: 2
    $display("x3 = %d", processor.register.registerFile[3]); // Beklenen: 3
    $display("x4 = %d", processor.register.registerFile[4]); // Beklenen: 1
    $display("x5 = %d", processor.register.registerFile[5]); // Beklenen: 0
    $display("x6 = %d", processor.register.registerFile[6]); // Beklenen: 3
    $display("x7 = %d", processor.register.registerFile[7]); // Beklenen: 3
    $display("x8 = %d", processor.register.registerFile[8]); // Beklenen: 1
    $display("x9 = %d", processor.register.registerFile[9]); // Beklenen: 1
    $display("x10 = %d", processor.register.registerFile[10]); // Beklenen: 2
    $display("x11 = %d", processor.register.registerFile[11]); // Beklenen: 0
    $display("x12 = %d", processor.register.registerFile[12]); // Beklenen: 3
    $display("x13 = %h", processor.register.registerFile[13]); // Beklenen: 00000038
    $display("memory[0] = %d", processor.dm.memory[0]); // Beklenen: 3

    if (processor.register.registerFile[1] !== 1) $display("HATA: x1 beklenen 1 degil!");
    if (processor.register.registerFile[2] !== 2) $display("HATA: x3 beklenen 2 degil!");
    if (processor.register.registerFile[3] !== 3) $display("HATA: x3 beklenen 3 degil!");
    if (processor.register.registerFile[4] !== 1) $display("HATA: x4 beklenen 1 degil!");
    if (processor.register.registerFile[5] !== 0) $display("HATA: x5 beklenen 0 degil!");
    if (processor.register.registerFile[6] !== 3) $display("HATA: x3 beklenen 3 degil!");
    if (processor.register.registerFile[7] !== 3) $display("HATA: x7 beklenen 3 degil!");
    if (processor.register.registerFile[8] !== 1) $display("HATA: x8 beklenen 1 degil!");
    if (processor.register.registerFile[9] !== 1) $display("HATA: x9 beklenen 1 degil!");
    if (processor.register.registerFile[10] !== 2) $display("HATA: x10 beklenen 2 degil!");
    if (processor.register.registerFile[11] !== 0) $display("HATA: x11 beklenen 0 degil!");
    if (processor.register.registerFile[12] !== 3) $display("HATA: x12 beklenen 3 degil!");
    if (processor.register.registerFile[13] !== 32'h00000038) $display("HATA: x13 beklenen 0x00000038 degil!");
    if (processor.dm.memory[0] !== 3) $display("HATA: memory[0] beklenen 3 degil!");

    #100;
    $finish;
  end


endmodule

2-2/Bilgisayar Organizasyonu/ödevler/2025/ödev 2/mert_guler/Q1/processor_tb.vcd
$date
	Mon May  5 13:44:31 2025
$end
$version
	Icarus Verilog
$end
$timescale
	1ps
$end
$scope module processor_tb $end
$scope module processor $end
$var wire 1 ! clk $end
$var wire 1 " reset $end
$var wire 32 # instruction [31:0] $end
$var wire 1 $ Zero $end
$var wire 32 % WriteData [31:0] $end
$var wire 32 & SrcB [31:0] $end
$var wire 32 ' SrcA [31:0] $end
$var wire 2 ( ResultSrc [1:0] $end
$var wire 32 ) Result [31:0] $end
$var wire 1 * RegWrite $end
$var wire 32 + ReadData [31:0] $end
$var wire 32 , PCTarget [31:0] $end
$var wire 1 - PCSrc $end
$var wire 32 . PCPlus4 [31:0] $end
$var wire 32 / PCNext [31:0] $end
$var wire 32 0 PC [31:0] $end
$var wire 1 1 MemWrite $end
$var wire 2 2 ImmSrc [1:0] $end
$var wire 32 3 ImmExt [31:0] $end
$var wire 1 4 ALUSrc $end
$var wire 32 5 ALUResult [31:0] $end
$var wire 3 6 ALUControl [2:0] $end
$scope module add4 $end
$var wire 32 7 out [31:0] $end
$var wire 32 8 A [31:0] $end
$upscope $end
$scope module adder $end
$var wire 32 9 PCTarget [31:0] $end
$var wire 32 : B [31:0] $end
$var wire 32 ; A [31:0] $end
$upscope $end
$scope module alu $end
$var wire 32 < B [31:0] $end
$var wire 3 = ALUControl [2:0] $end
$var wire 32 > A [31:0] $end
$var reg 32 ? out [31:0] $end
$var reg 1 $ zero $end
$upscope $end
$scope module controller $end
$var wire 1 - PCSrc $end
$var wire 1 $ Zero $end
$var wire 3 @ funct3 [2:0] $end
$var wire 1 A funct7 $end
$var wire 7 B op [6:0] $end
$var wire 2 C ResultSrc [1:0] $end
$var wire 1 * RegWrite $end
$var wire 1 1 MemWrite $end
$var wire 1 D Jump $end
$var wire 2 E ImmSrc [1:0] $end
$var wire 1 F Branch $end
$var wire 1 4 ALUSrc $end
$var wire 2 G ALUOp [1:0] $end
$var wire 3 H ALUControl [2:0] $end
$scope module alu_decoder $end
$var wire 3 I funct3 [2:0] $end
$var wire 1 A funct7 $end
$var wire 1 J op5 $end
$var wire 2 K ALUOp [1:0] $end
$var reg 3 L ALUControl [2:0] $end
$upscope $end
$scope module main_decoder $end
$var wire 7 M op [6:0] $end
$var reg 2 N ALUOp [1:0] $end
$var reg 1 4 ALUSrc $end
$var reg 1 F Branch $end
$var reg 2 O ImmSrc [1:0] $end
$var reg 1 D Jump $end
$var reg 1 1 MemWrite $end
$var reg 1 * RegWrite $end
$var reg 2 P ResultSrc [1:0] $end
$upscope $end
$upscope $end
$scope module dm $end
$var wire 32 Q A [31:0] $end
$var wire 32 R RD [31:0] $end
$var wire 1 1 WE $end
$var wire 1 ! clk $end
$var wire 32 S WD [31:0] $end
$upscope $end
$scope module ext $end
$var wire 2 T ImmSrc [1:0] $end
$var wire 25 U instr [31:7] $end
$var reg 32 V ImmExt [31:0] $end
$upscope $end
$scope module im $end
$var wire 32 W A [31:0] $end
$var reg 32 X RD [31:0] $end
$upscope $end
$scope module mux1 $end
$var wire 32 Y a [31:0] $end
$var wire 32 Z b [31:0] $end
$var wire 1 - select $end
$var wire 32 [ out [31:0] $end
$upscope $end
$scope module mux2 $end
$var wire 32 \ a [31:0] $end
$var wire 1 4 select $end
$var wire 32 ] out [31:0] $end
$var wire 32 ^ b [31:0] $end
$upscope $end
$scope module mux3 $end
$var wire 32 _ a [31:0] $end
$var wire 32 ` b [31:0] $end
$var wire 32 a c [31:0] $end
$var wire 32 b d [31:0] $end
$var wire 2 c select [1:0] $end
$var wire 32 d out [31:0] $end
$upscope $end
$scope module pc $end
$var wire 1 ! clk $end
$var wire 32 e pc_in [31:0] $end
$var wire 1 " reset $end
$var reg 32 f pc_out [31:0] $end
$upscope $end
$scope module register $end
$var wire 5 g A1 [4:0] $end
$var wire 5 h A2 [4:0] $end
$var wire 5 i A3 [4:0] $end
$var wire 32 j WD3 [31:0] $end
$var wire 1 * WE3 $end
$var wire 1 ! clk $end
$var reg 32 k RD1 [31:0] $end
$var reg 32 l RD2 [31:0] $end
$upscope $end
$upscope $end
$upscope $end
$enddefinitions $end
$comment Show the parameter values. $end
$dumpall
$end
#0
$dumpvars
bx l
bx k
bx j
bx i
bx h
bx g
bx f
bx e
bx d
bx c
bx b
bx a
bx `
bx _
bx ^
bx ]
bx \
bx [
bx Z
bx Y
bx X
bx W
bx V
bx U
bx T
bx S
bx R
bx Q
bx P
bx O
bx N
bx M
bx L
bx K
xJ
bx I
bx H
bx G
xF
bx E
xD
bx C
bx B
xA
bx @
bx ?
bx >
bx =
bx <
bx ;
bx :
bx 9
bx 8
bx 7
bx 6
bx 5
x4
bx 3
bx 2
x1
bx 0
bx /
bx .
x-
bx ,
bx +
x*
bx )
bx (
bx '
bx &
bx %
x$
bx #
1"
0!
$end
#5000
b1 )
b1 d
b1 j
b1 5
b1 ?
b1 Q
b1 b
0$
b0 6
b0 =
b0 H
b0 L
b1 &
b1 <
b1 ]
b100 /
b100 [
b100 e
0-
b1 ,
b1 9
b1 Y
b1 3
b1 :
b1 V
b1 \
0D
b10 G
b10 K
b10 N
b0 (
b0 C
b0 P
b0 c
b0 2
b0 E
b0 O
b0 T
14
0F
01
1*
b0 '
b0 >
b0 k
0J
b10000000000001 U
b1 i
b1 h
b0 g
0A
b0 @
b0 I
b10011 B
b10011 M
b100000000000010010011 #
b100000000000010010011 X
b100 .
b100 7
b100 Z
b100 `
b0 0
b0 8
b0 ;
b0 W
b0 f
1!
#10000
0!
#15000
b1 %
b1 S
b1 ^
b1 l
1!
#20000
0!
0"
#25000
b10 )
b10 d
b10 j
b10 5
b10 ?
b10 Q
b10 b
b10 &
b10 <
b10 ]
b10 3
b10 :
b10 V
b10 \
bx %
bx S
bx ^
bx l
b100000000000010 U
b10 i
b10 h
b1000 /
b1000 [
b1000 e
b1000000000000100010011 #
b1000000000000100010011 X
b110 ,
b110 9
b110 Y
b1000 .
b1000 7
b1000 Z
b1000 `
b100 0
b100 8
b100 ;
b100 W
b100 f
1!
#30000
0!
#35000
b11 )
b11 d
b11 j
b11 5
b11 ?
b11 Q
b11 b
bx 2
bx E
bx O
bx T
04
b1 '
b1 >
b1 k
1J
b100000100000011 U
b11 i
b1 g
b110011 B
b110011 M
b10 %
b10 S
b10 ^
b10 l
b1100 /
b1100 [
b1100 e
b1000001000000110110011 #
b1000001000000110110011 X
b1010 ,
b1010 9
b1010 Y
b1100 .
b1100 7
b1100 Z
b1100 `
b1000 0
b1000 8
b1000 ;
b1000 W
b1000 f
1!
#40000
0!
#45000
b1 )
b1 d
b1 j
b1 5
b1 ?
b1 Q
b1 b
b1 6
b1 =
b1 H
b1 L
b11 '
b11 >
b11 k
b100000000100001100000100 U
b100 i
b11 g
1A
b10000 /
b10000 [
b10000 e
b1000000001000011000001000110011 #
b1000000001000011000001000110011 X
b1110 ,
b1110 9
b1110 Y
b10000 .
b10000 7
b10000 Z
b10000 `
b1100 0
b1100 8
b1100 ;
b1100 W
b1100 f
1!
#50000
0!
#55000
b0 )
b0 d
b0 j
b0 5
b0 ?
b0 Q
b0 b
b101 6
b101 =
b101 H
b101 L
b1 &
b1 <
b1 ]
b1 %
b1 S
b1 ^
b1 l
b1000001101000101 U
b101 i
b100 h
0A
b10 @
b10 I
b10100 /
b10100 [
b10100 e
b10000011010001010110011 #
b10000011010001010110011 X
b10010 ,
b10010 9
b10010 Y
b10100 .
b10100 7
b10100 Z
b10100 `
b10000 0
b10000 8
b10000 ;
b10000 W
b10000 f
1!
#60000
0!
#65000
b11 )
b11 d
b11 j
b11 5
b11 ?
b11 Q
b11 b
1$
b11 6
b11 =
b11 H
b11 L
b11 &
b11 <
b11 ]
b11 %
b11 S
b11 ^
b11 l
b110001111000110 U
b110 i
b11 h
b110 @
b110 I
b11000 /
b11000 [
b11000 e
b1100011110001100110011 #
b1100011110001100110011 X
b10110 ,
b10110 9
b10110 Y
b11000 .
b11000 7
b11000 Z
b11000 `
b10100 0
b10100 8
b10100 ;
b10100 W
b10100 f
1!
#70000
0!
#75000
b10 6
b10 =
b10 H
b10 L
b110001111100111 U
b111 i
b111 @
b111 I
b11100 /
b11100 [
b11100 e
b1100011111001110110011 #
b1100011111001110110011 X
b11010 ,
b11010 9
b11010 Y
b11100 .
b11100 7
b11100 Z
b11100 `
b11000 0
b11000 8
b11000 ;
b11000 W
b11000 f
1!
#80000
0!
#85000
b1 )
b1 d
b1 j
b1 3
b1 :
b1 V
b1 \
b1 5
b1 ?
b1 Q
b1 b
0$
b0 6
b0 =
b0 H
b0 L
b0 2
b0 E
b0 O
b0 T
14
b1 &
b1 <
b1 ]
b1 %
b1 S
b1 ^
b1 l
b0 '
b0 >
b0 k
0J
b10000000001000 U
b1000 i
b1 h
b0 g
b0 @
b0 I
b10011 B
b10011 M
b100000 /
b100000 [
b100000 e
b100000000010000010011 #
b100000000010000010011 X
b11101 ,
b11101 9
b11101 Y
b100000 .
b100000 7
b100000 Z
b100000 `
b11100 0
b11100 8
b11100 ;
b11100 W
b11100 f
1!
#90000
0!
#95000
1$
bx )
bx d
bx j
b0 5
b0 ?
b0 Q
b0 b
b0 6
b0 =
b0 H
b0 L
bx (
bx C
bx P
bx c
b1 2
b1 E
b1 O
b1 T
b0 G
b0 K
b0 N
11
0*
b0 &
b0 <
b0 ]
b0 3
b0 :
b0 V
b0 \
b11 %
b11 S
b11 ^
b11 l
1J
b1110000001000000 U
b0 i
b111 h
b10 @
b10 I
b100011 B
b100011 M
b100100 /
b100100 [
b100100 e
b11100000010000000100011 #
b11100000010000000100011 X
b100000 ,
b100000 9
b100000 Y
b100100 .
b100100 7
b100100 Z
b100100 `
b100000 0
b100000 8
b100000 ;
b100000 W
b100000 f
1!
#100000
0!
#105000
b101 6
b101 =
b101 H
b101 L
b1 )
b1 d
b1 j
b1 5
b1 ?
b1 Q
b1 b
0$
b10 G
b10 K
b10 N
b0 (
b0 C
b0 P
b0 c
b0 2
b0 E
b0 O
b0 T
01
1*
b11 &
b11 <
b11 ]
b11 3
b11 :
b11 V
b11 \
b10 '
b10 >
b10 k
0J
b110001001001001 U
b1001 i
b11 h
b10 g
b10011 B
b10011 M
b101000 /
b101000 [
b101000 e
b1100010010010010010011 #
b1100010010010010010011 X
b100111 ,
b100111 9
b100111 Y
b101000 .
b101000 7
b101000 Z
b101000 `
b100100 0
b100100 8
b100100 ;
b100100 W
b100100 f
b11 +
b11 R
b11 a
1!
#110000
0!
#115000
b10 )
b10 d
b10 j
b10 5
b10 ?
b10 Q
b10 b
b11 6
b11 =
b11 H
b11 L
b0 &
b0 <
b0 ]
b0 3
b0 :
b0 V
b0 \
b0 %
b0 S
b0 ^
b0 l
b1011001010 U
b1010 i
b0 h
b110 @
b110 I
b101100 /
b101100 [
b101100 e
b10110010100010011 #
b10110010100010011 X
b101000 ,
b101000 9
b101000 Y
b101100 .
b101100 7
b101100 Z
b101100 `
b101000 0
b101000 8
b101000 ;
b101000 W
b101000 f
1!
#120000
0!
#125000
b0 )
b0 d
b0 j
b11 +
b11 R
b11 a
b0 5
b0 ?
b0 Q
b0 b
b10 6
b10 =
b10 H
b10 L
b101 &
b101 <
b101 ]
b101 3
b101 :
b101 V
b101 \
b1010001011101011 U
b1011 i
b101 h
b111 @
b111 I
b110000 /
b110000 [
b110000 e
b10100010111010110010011 #
b10100010111010110010011 X
b110001 ,
b110001 9
b110001 Y
b110000 .
b110000 7
b110000 Z
b110000 `
b101100 0
b101100 8
b101100 ;
b101100 W
b101100 f
1!
#130000
0!
#135000
b11 )
b11 d
b11 j
1$
b0 6
b0 =
b0 H
b0 L
b1 (
b1 C
b1 P
b1 c
b0 G
b0 K
b0 N
b0 &
b0 <
b0 ]
b0 3
b0 :
b0 V
b0 \
b0 '
b0 >
b0 k
b1001100 U
b1100 i
b0 h
b0 g
b10 @
b10 I
b11 B
b11 M
b110100 /
b110100 [
b110100 e
b10011000000011 #
b10011000000011 X
b110000 ,
b110000 9
b110000 Y
b110100 .
b110100 7
b110100 Z
b110100 `
b110000 0
b110000 8
b110000 ;
b110000 W
b110000 f
1!
#140000
0!
#145000
b111000 )
b111000 d
b111000 j
bx +
bx R
bx a
1-
bx 5
bx ?
bx Q
bx b
x$
1D
b10 (
b10 C
b10 P
b10 c
b11 2
b11 E
b11 O
b11 T
bx G
bx K
bx N
x4
b0x0x &
b0x0x <
b0x0x ]
b100 3
b100 :
b100 V
b100 \
b1 %
b1 S
b1 ^
b1 l
1J
b1000000000001101 U
b1101 i
b100 h
b0 @
b0 I
b1101111 B
b1101111 M
b111000 /
b111000 [
b111000 e
b10000000000011011101111 #
b10000000000011011101111 X
b111000 ,
b111000 9
b111000 Y
b111000 .
b111000 7
b111000 Z
b111000 `
b110100 0
b110100 8
b110100 ;
b110100 W
b110100 f
1!
#150000
0!
#155000
b11 +
b11 R
b11 a
b0 5
b0 ?
b0 Q
b0 b
b1 6
b1 =
b1 H
b1 L
1-
1$
0D
bx (
bx C
bx P
bx c
b10 2
b10 E
b10 O
b10 T
b1 G
b1 K
b1 N
04
1F
0*
b11 &
b11 <
b11 ]
b100000 3
b100000 :
b100000 V
b100000 \
b11 %
b11 S
b11 ^
b11 l
b11 '
b11 >
b11 k
bx )
bx d
bx j
b1001100001100000000 U
b0 i
b110 h
b11 g
b1100011 B
b1100011 M
b1011000 /
b1011000 [
b1011000 e
b10011000011000000001100011 #
b10011000011000000001100011 X
b1011000 ,
b1011000 9
b1011000 Y
b111100 .
b111100 7
b111100 Z
b111100 `
b111000 0
b111000 8
b111000 ;
b111000 W
b111000 f
1!
#160000
0!
#165000
x-
bx +
bx R
bx a
bx 5
bx ?
bx Q
bx b
x$
bx &
bx <
bx ]
bx0 3
bx0 :
bx0 V
bx0 \
bx %
bx S
bx ^
bx l
bx '
bx >
bx k
xJ
bx U
bx i
bx h
bx g
xA
bx @
bx I
bx B
bx M
bx /
bx [
bx e
bx #
bx X
bx ,
bx 9
bx Y
b1011100 .
b1011100 7
b1011100 Z
b1011100 `
b1011000 0
b1011000 8
b1011000 ;
b1011000 W
b1011000 f
1!
#170000
0!
#175000
bx .
bx 7
bx Z
bx `
bx 0
bx 8
bx ;
bx W
bx f
1!
