2-2/Bilgisayar Organizasyonu/ödevler/2025/ödev 2/batuhan_odcikin/S1/data_memory.v
`timescale 1ns/1ps
module DataMemory (
    input         clk,
    input         we,
    input  [31:0] addr,
    input  [31:0] wd,
    output [31:0] rd
);
    reg [31:0] mem[0:1023];
    always @(posedge clk)
        if (we)
            mem[addr[11:2]] <= wd;
    assign rd = mem[addr[11:2]];
endmodule

2-2/Bilgisayar Organizasyonu/ödevler/2025/ödev 3/batuhan_odcikin/S1/alu.v
// ALU: Aritmetik ve mantık işlemlerini yapan modül
module ALU (
    input  [31:0] srcA,
    input  [31:0] srcB,
    input  [2:0]  ALUControl,
    output reg [31:0] ALUResult,
    output        Zero
);
    always @(*) begin
        case (ALUControl)
            3'b000: ALUResult = srcA + srcB;               // ADD, ADDI
            3'b001: ALUResult = srcA - srcB;               // SUB, BEQ
            3'b010: ALUResult = srcA & srcB;               // AND, ANDI
            3'b011: ALUResult = srcA | srcB;               // OR, ORI
            3'b101: ALUResult = (srcA < srcB) ? 32'd1 : 32'd0; // SLT, SLTI
            3'b110: ALUResult = srcA << srcB[4:0];        // SLL added
            default: ALUResult = 32'd0;
        endcase
    end

    assign Zero = (ALUResult == 32'd0);
endmodule

2-2/Bilgisayar Organizasyonu/ödevler/2025/ödev 2/batuhan_odcikin/S2/alu_control.v
`timescale 1ns/1ps
module ALUControl (
    input  [1:0] aluOp,
    input  [2:0] funct3,
    input        funct7_5,
    output reg [2:0] ALUControl
);
    always @(*) begin
        case(aluOp)
        2'b00: ALUControl=3'b000; // ADD
        2'b01: ALUControl=3'b001; // SUB
        2'b10: begin              // R-type / I-type
            case(funct3)
            3'b000: ALUControl = funct7_5 ? 3'b001 : 3'b000; // SUB/ADD
            3'b001: ALUControl = 3'b110;                    // SLL added
            3'b010: ALUControl = 3'b101;                    // SLT
            3'b110: ALUControl = 3'b011;                    // OR
            3'b111: ALUControl = 3'b010;                    // AND
            default: ALUControl = 3'b000;
            endcase
        end
        default: ALUControl=3'b000;
        endcase
    end
endmodule

2-2/Bilgisayar Organizasyonu/ödevler/2025/ödev 2/batuhan_odcikin/S1/reg_file.v
// RegFile.v
module RegFile (
    input         clk,
    input         we3,        // write enable
    input  [4:0]  ra1, ra2, ra3,  // read addresses
    input  [4:0]  wa3,       // write address
    input  [31:0] wd3,       // write data
    output [31:0] rd1, rd2   // read data
);
    
    reg [31:0] regs [0:31];
    integer i;
   
    initial begin
        for (i = 0; i < 32; i = i + 1)
            regs[i] = 32'd0;
    end
   
    always @(posedge clk) begin
        if (we3 && wa3 != 5'd0)
            regs[wa3] <= wd3;
    end

    assign rd1 = (ra1 != 5'd0) ? regs[ra1] : 32'd0;
    assign rd2 = (ra2 != 5'd0) ? regs[ra2] : 32'd0;
endmodule

2-2/Bilgisayar Organizasyonu/ödevler/2025/ödev 3/batuhan_odcikin/S1/imm_gen.v
module ImmGen (
    input  [31:0] instr,
    input  [2:0]  ImmSrc,   // artık 3 bit
    output reg [31:0] immExt
);
    always @(*) begin
        case (ImmSrc) // 2 bit yeterli olmadığından 3 bite yükseltildi
          3'b000: // I-type 
            immExt = {{20{instr[31]}}, instr[31:20]};
          3'b001: // S-type
            immExt = {{20{instr[31]}}, instr[31:25], instr[11:7]};
          3'b010: // B-type
            immExt = {{19{instr[31]}}, instr[31], instr[7],
                      instr[30:25], instr[11:8], 1'b0};
          3'b011: // J-type (JAL)
            immExt = {{11{instr[31]}}, instr[31], instr[19:12],
                      instr[20], instr[30:21], 1'b0};
          3'b100: // U-type (LUI)
            immExt = {instr[31:12], 12'b0};
          default:
            immExt = 32'd0;
        endcase
    end
endmodule

2-2/Bilgisayar Organizasyonu/ödevler/2025/ödev 3/batuhan_odcikin/S1/control_unit.v
// ======================= ControlUnit.v =======================
module ControlUnit (
    input  [6:0] opcode,
    input        zero,
    output reg   regWrite,
    output reg   memWrite,
    output reg   aluSrc,
    output reg [2:0] immSrc, // 3 biye yükseltildi
    output reg [1:0] resultSrc,
    output reg [1:0] pcSrc,
    output reg [1:0] aluOp
);
    reg branch;
    always @(*) begin
        // Default değerler
        regWrite  = 1'b0;
        memWrite  = 1'b0;
        aluSrc    = 1'b0;
        immSrc    = 3'b000;
        resultSrc = 2'b00;
        pcSrc     = 2'b00;
        aluOp     = 2'b00;
        branch    = 1'b0;

        case (opcode)
            7'b0000011: begin // LW
                regWrite  = 1; memWrite = 0; aluSrc = 1;
                immSrc    = 3'b000; resultSrc = 2'b01; aluOp = 2'b00;
            end
            7'b0100011: begin // SW
                regWrite  = 0; memWrite = 1; aluSrc = 1;
                immSrc    = 3'b001; aluOp = 2'b00;
            end
            7'b1100011: begin // BEQ
                regWrite  = 0; memWrite = 0; aluSrc = 0; branch = 1;
                immSrc    = 3'b010; aluOp = 2'b01;
            end
            7'b1101111: begin // JAL
                regWrite  = 1; memWrite = 0; aluSrc = 0;
                immSrc    = 3'b011; resultSrc = 2'b10; pcSrc = 2'b10;
            end
            7'b0010011: begin // I-type ALU (ADDI, SLTI, ANDI, ORI)
                regWrite  = 1; memWrite = 0; aluSrc = 1;
                immSrc    = 3'b000; resultSrc = 2'b00; aluOp = 2'b10;
            end
            7'b0110111: begin // LUI
                regWrite = 1; memWrite = 0; aluSrc = 0;
                immSrc = 3'b100; resultSrc = 2'b11;
                pcSrc = 2'b00; aluOp = 2'b00;
            end
            default: begin
                regWrite  = 0;
                memWrite  = 0;
                aluSrc    = 0;
                immSrc    = 3'b000;
                resultSrc = 2'b00;
                pcSrc     = 2'b00;
                aluOp     = 2'b00;
                branch    = 0;
            end
        endcase

        // Branch doğru ve Zero=1 ise PCSrc=01
        if (branch & zero)
            pcSrc = 2'b01;
    end
endmodule

2-2/Bilgisayar Organizasyonu/ödevler/2025/ödev 3/batuhan_odcikin/S1/cpu_top.v
`timescale 1ns/1ps

`include "control_unit.v"
`include "imm_gen.v"
`include "reg_file.v"
`include "alu_control.v"
`include "alu.v"
`include "data_memory.v"

module cpu_top (
    input         clk,
    input         rst,
    output [31:0] pc,
    output [31:0] instr,
    output [31:0] aluOut,
    output [31:0] memReadData
);
    
    reg  [31:0] PC;
    wire [31:0] PCPlus4, PCBranch, PCNext;

    always @(posedge clk or posedge rst) begin
        if (rst) 
            PC <= 0; 
        else 
            PC <= PCNext;
    end
    assign pc       = PC;
    assign PCPlus4  = PC + 4;

    reg [31:0] imem [0:255];
    
    assign instr = imem[PC[9:2]];

    // Main Control
    wire        regWrite, memWrite, aluSrc;
    wire [2:0]  immSrc;
    wire [1:0]  resultSrc, pcSrc, aluOp;
    wire        zero;
    ControlUnit control_unit(
        .opcode(instr[6:0]),
        .zero(zero),
        .regWrite(regWrite),
        .memWrite(memWrite),
        .aluSrc(aluSrc),
        .immSrc(immSrc),
        .resultSrc(resultSrc),
        .pcSrc(pcSrc),
        .aluOp(aluOp)
    );

    // Immediate Generator
    wire [31:0] immExt;
    ImmGen imm_gen(
        .instr(instr),
        .ImmSrc(immSrc),
        .immExt(immExt)
    );

    // Register File
    wire [31:0] rd1, rd2;
    wire [31:0] wd3 = (resultSrc==2'b01) ? memReadData :
                      (resultSrc==2'b10) ? PCPlus4 :
                                            aluOut;
    RegFile reg_file(
        .clk(clk),
        .we3(regWrite),
        .ra1(instr[19:15]),
        .ra2(instr[24:20]),
        .wa3(instr[11:7]),
        .wd3(wd3),
        .rd1(rd1),
        .rd2(rd2)
    );

    // ALU Control + ALU
    wire [2:0] aluControl;
    ALUControl alu_control(
        .aluOp(aluOp),
        .funct3(instr[14:12]),
        .funct7_5(instr[30]),
        .ALUControl(aluControl)
    );
    wire [31:0] aluInB = aluSrc ? immExt : rd2;
    ALU alu(
        .srcA(rd1),
        .srcB(aluInB),
        .ALUControl(aluControl),
        .ALUResult(aluOut),
        .Zero(zero)
    );

    // Data Memory
    DataMemory data_memory(
        .clk(clk),
        .we(memWrite),
        .addr(aluOut),
        .wd(rd2),
        .rd(memReadData)
    );

    // PC Next Mux
    assign PCBranch = PCPlus4 + immExt;
    assign PCNext   = (pcSrc==2'b10) ? (PCPlus4 + immExt) :  // JAL
                      (pcSrc==2'b01) ? PCBranch :            // BEQ
                                         PCPlus4;           
endmodule

2-2/Bilgisayar Organizasyonu/ödevler/2025/ödev 3/batuhan_odcikin/S1/tb_cpu_top.v

`timescale 1ns/1ps

module tb_cpu_top;
    // Clock & reset
    reg clk;
    reg rst;

    // CPU outputs
    wire [31:0] pc;
    wire [31:0] instr;
    wire [31:0] aluOut;
    wire [31:0] memReadData;

    // Instantiate DUT
    cpu_top UUT (
        .clk(clk),
        .rst(rst),
        .pc(pc),
        .instr(instr),
        .aluOut(aluOut),
        .memReadData(memReadData)
    );

    // Clock generation: 10 ns period
    initial clk = 0;
    always #5 clk = ~clk;

    // Load instruction memory
    initial begin
        // Hex dosyası, imem[0]…imem[N] adreslerine yüklenecek
        $readmemh("instr_mem_2.hex", UUT.imem);
    end
    // Reset sequencing
    initial begin
        rst = 1;
        #10;       // 2 clock cycle boyunca reset aktif
        rst = 0;
    end

    // Optional: monitor bazı sinyalleri
    initial begin
        $dumpfile("tb_cpu_top.vcd");
        $dumpvars(0, tb_cpu_top);
        $display("time\tpc\tinstr\taluOut\tmemRd");
        $monitor("time=%0t, pc=%h, instr=%h, x10=%h, x11=%h, x12=%h, x13=%h, x14=%h", $time, pc, instr, UUT.reg_file.regs[10], UUT.reg_file.regs[11], UUT.reg_file.regs[12], UUT.reg_file.regs[13], UUT.reg_file.regs[14]);
        end

    // Simulation stop
    initial begin
        #10000;     // 1000 ns sonra simülasyonu bitir
        $display("Final x9 = 0x%h", UUT.reg_file.regs[9]);
        $display("Final x10 = 0x%h", UUT.reg_file.regs[10]);
        $display("Final x11 = 0x%h", UUT.reg_file.regs[11]);
        $display("Final x12 = 0x%h", UUT.reg_file.regs[12]);
        $display("Final x13 = 0x%h", UUT.reg_file.regs[13]);
        $finish;
    end

endmodule

2-2/Bilgisayar Organizasyonu/ödevler/2025/ödev 3/batuhan_odcikin/S1/tb_cpu_top.vcd
$date
	Wed May 28 08:20:53 2025
$end
$version
	Icarus Verilog
$end
$timescale
	1ps
$end
$scope module tb_cpu_top $end
$var wire 32 ! pc [31:0] $end
$var wire 32 " memReadData [31:0] $end
$var wire 32 # instr [31:0] $end
$var wire 32 $ aluOut [31:0] $end
$var reg 1 % clk $end
$var reg 1 & rst $end
$scope module UUT $end
$var wire 1 % clk $end
$var wire 32 ' instr [31:0] $end
$var wire 32 ( pc [31:0] $end
$var wire 1 & rst $end
$var wire 1 ) zero $end
$var wire 32 * wd3 [31:0] $end
$var wire 2 + resultSrc [1:0] $end
$var wire 1 , regWrite $end
$var wire 32 - rd2 [31:0] $end
$var wire 32 . rd1 [31:0] $end
$var wire 2 / pcSrc [1:0] $end
$var wire 1 0 memWrite $end
$var wire 32 1 memReadData [31:0] $end
$var wire 3 2 immSrc [2:0] $end
$var wire 32 3 immExt [31:0] $end
$var wire 1 4 aluSrc $end
$var wire 32 5 aluOut [31:0] $end
$var wire 2 6 aluOp [1:0] $end
$var wire 32 7 aluInB [31:0] $end
$var wire 3 8 aluControl [2:0] $end
$var wire 32 9 PCPlus4 [31:0] $end
$var wire 32 : PCNext [31:0] $end
$var wire 32 ; PCBranch [31:0] $end
$var reg 32 < PC [31:0] $end
$scope module alu $end
$var wire 32 = srcB [31:0] $end
$var wire 32 > srcA [31:0] $end
$var wire 1 ) Zero $end
$var wire 3 ? ALUControl [2:0] $end
$var reg 32 @ ALUResult [31:0] $end
$upscope $end
$scope module alu_control $end
$var wire 3 A funct3 [2:0] $end
$var wire 1 B funct7_5 $end
$var wire 2 C aluOp [1:0] $end
$var reg 3 D ALUControl [2:0] $end
$upscope $end
$scope module control_unit $end
$var wire 7 E opcode [6:0] $end
$var wire 1 ) zero $end
$var reg 2 F aluOp [1:0] $end
$var reg 1 4 aluSrc $end
$var reg 1 G branch $end
$var reg 3 H immSrc [2:0] $end
$var reg 1 0 memWrite $end
$var reg 2 I pcSrc [1:0] $end
$var reg 1 , regWrite $end
$var reg 2 J resultSrc [1:0] $end
$upscope $end
$scope module data_memory $end
$var wire 32 K addr [31:0] $end
$var wire 1 % clk $end
$var wire 32 L rd [31:0] $end
$var wire 1 0 we $end
$var wire 32 M wd [31:0] $end
$upscope $end
$scope module imm_gen $end
$var wire 3 N ImmSrc [2:0] $end
$var wire 32 O instr [31:0] $end
$var reg 32 P immExt [31:0] $end
$upscope $end
$scope module reg_file $end
$var wire 1 % clk $end
$var wire 5 Q ra1 [4:0] $end
$var wire 5 R ra2 [4:0] $end
$var wire 5 S ra3 [4:0] $end
$var wire 5 T wa3 [4:0] $end
$var wire 32 U wd3 [31:0] $end
$var wire 1 , we3 $end
$var wire 32 V rd2 [31:0] $end
$var wire 32 W rd1 [31:0] $end
$var integer 32 X i [31:0] $end
$upscope $end
$upscope $end
$upscope $end
$enddefinitions $end
$comment Show the parameter values. $end
$dumpall
$end
#0
$dumpvars
b100000 X
b0 W
b0 V
b0 U
b1010 T
bz S
b11011 R
b1010 Q
b11000111101101010010000000000000 P
b11000111101101010010010100110111 O
b100 N
b0 M
bx L
b0 K
b11 J
b0 I
b100 H
0G
b0 F
b110111 E
b0 D
b0 C
1B
b10 A
b0 @
b0 ?
b0 >
b0 =
b0 <
b11000111101101010010000000000100 ;
b100 :
b100 9
b0 8
b0 7
b0 6
b0 5
04
b11000111101101010010000000000000 3
b100 2
bx 1
00
b0 /
b0 .
b0 -
1,
b11 +
b0 *
1)
b0 (
b11000111101101010010010100110111 '
1&
0%
b0 $
b11000111101101010010010100110111 #
bx "
b0 !
$end
#5000
1%
#10000
0%
0&
#15000
b101101001 *
b101101001 U
0)
b101101001 $
b101101001 5
b101101001 @
b101101001 K
b101101001 7
b101101001 =
b10 6
b10 C
b10 F
14
b0 +
b0 J
b0 2
b0 H
b0 N
1,
b1000 :
b10011 E
b1001 R
b0 A
0B
b101101001 3
b101101001 P
b10110100101010000010100010011 #
b10110100101010000010100010011 '
b10110100101010000010100010011 O
b101110001 ;
b1000 9
b100 !
b100 (
b100 <
1%
#20000
0%
#25000
b1 *
b1 U
b1 7
b1 =
b1 $
b1 5
b1 @
b1 K
b1100 :
b0 Q
b1 R
b1011 T
b1 3
b1 P
b0 .
b0 >
b0 W
b100000000010110010011 #
b100000000010110010011 '
b100000000010110010011 O
b1101 ;
b1100 9
b1000 !
b1000 (
b1000 <
1%
#30000
0%
#35000
b0 *
b0 U
b10 6
b10 C
b10 F
14
1,
1)
b0 $
b0 5
b0 @
b0 K
b0 7
b0 =
b10000 :
b0 R
b1100 T
b0 3
b0 P
b11000010011 #
b11000010011 '
b11000010011 O
b10000 ;
b10000 9
b1100 !
b1100 (
b1100 <
1%
#40000
0%
#45000
b10100 :
b1101 T
b11010010011 #
b11010010011 '
b11010010011 O
b10100 ;
b10100 9
b10000 !
b10000 (
b10000 <
1%
#50000
0%
#55000
b1000 *
b1000 U
b10 6
b10 C
b10 F
14
1,
0)
b1000 $
b1000 5
b1000 @
b1000 K
b1000 7
b1000 =
b11000 :
b1000 R
b1110 T
b1000 3
b1000 P
b100000000000011100010011 #
b100000000000011100010011 '
b100000000000011100010011 O
b100000 ;
b11000 9
b10100 !
b10100 (
b10100 <
1%
#60000
0%
#65000
b100000 *
b100000 U
b100000 $
b100000 5
b100000 @
b100000 K
b1000 .
b1000 >
b1000 W
b110 8
b110 ?
b110 D
b10 7
b10 =
b11100 :
b1110 Q
b10 R
b1 A
b10 3
b10 P
b1001110001011100010011 #
b1001110001011100010011 '
b1001110001011100010011 O
b11110 ;
b11100 9
b11000 !
b11000 (
b11000 <
1%
#70000
0%
#75000
b11111111111111111111111111100000 *
b11111111111111111111111111100000 U
b10 2
b10 H
b10 N
1G
b1 6
b1 C
b1 F
04
0,
b100000 -
b100000 M
b100000 V
b1 8
b1 ?
b1 D
b100000 7
b100000 =
b11111111111111111111111111100000 $
b11111111111111111111111111100000 5
b11111111111111111111111111100000 @
b11111111111111111111111111100000 K
b100000 :
b1100011 E
b1101 Q
b1110 R
b11100 T
b0 A
b11100 3
b11100 P
b0 .
b0 >
b0 W
b111001101000111001100011 #
b111001101000111001100011 '
b111001101000111001100011 O
b111100 ;
b100000 9
b11100 !
b11100 (
b11100 <
1%
#80000
0%
#85000
b101101010 *
b101101010 U
b0 8
b0 ?
b0 D
b101101010 $
b101101010 5
b101101010 @
b101101010 K
b1 7
b1 =
0G
b0 6
b0 C
b0 F
b0 2
b0 H
b0 N
b101101001 .
b101101001 >
b101101001 W
b1 -
b1 M
b1 V
b100100 :
b110011 E
b1010 Q
b1011 R
b1111 T
b111 A
b1011 3
b1011 P
b101101010111011110110011 #
b101101010111011110110011 '
b101101010111011110110011 O
b101111 ;
b100100 9
b100000 !
b100000 (
b100000 <
1%
#90000
0%
#95000
b11111111111111111111111111111111 *
b11111111111111111111111111111111 U
b1 8
b1 ?
b1 D
b1000 3
b1000 P
b11111111111111111111111111111111 $
b11111111111111111111111111111111 5
b11111111111111111111111111111111 @
b11111111111111111111111111111111 K
b1 6
b1 C
b1 F
b10 2
b10 H
b10 N
1G
b0 .
b0 >
b0 W
b101000 :
b1100011 E
b1111 Q
b1000 T
b1 A
b101101111001010001100011 #
b101101111001010001100011 '
b101101111001010001100011 O
b110000 ;
b101000 9
b100100 !
b100100 (
b100100 <
1%
#100000
0%
#105000
b1 *
b1 U
b1 $
b1 5
b1 @
b1 K
b0 8
b0 ?
b0 D
b1 7
b1 =
14
1,
0G
b10 6
b10 C
b10 F
b0 2
b0 H
b0 N
b0 -
b0 M
b0 V
b101100 :
b10011 E
b1100 Q
b1 R
b1100 T
b0 A
b1 3
b1 P
b101100000011000010011 #
b101100000011000010011 '
b101100000011000010011 O
b101101 ;
b101100 9
b101000 !
b101000 (
b101000 <
1%
#110000
0%
#115000
b10 *
b10 U
b110 8
b110 ?
b110 D
b10 $
b10 5
b10 @
b10 K
b110000 :
b1011 Q
b1011 T
b1 A
b1 .
b1 >
b1 W
b101011001010110010011 #
b101011001010110010011 '
b101011001010110010011 O
b110001 ;
b110000 9
b101100 !
b101100 (
b101100 <
1%
#120000
0%
#125000
b1 *
b1 U
b0 8
b0 ?
b0 D
b1 $
b1 5
b1 @
b1 K
b110100 :
b1101 Q
b1101 T
b0 A
b0 .
b0 >
b0 W
b101101000011010010011 #
b101101000011010010011 '
b101101000011010010011 O
b110101 ;
b110100 9
b110000 !
b110000 (
b110000 <
1%
#130000
0%
#135000
b1 /
b1 I
1)
b0 *
b0 U
b10 2
b10 H
b10 N
1G
b1 6
b1 C
b1 F
04
0,
b1 8
b1 ?
b1 D
b0 7
b0 =
b0 $
b0 5
b0 @
b0 K
b100000 :
b1100011 E
b0 Q
b0 R
b1001 T
1B
b11111111111111111111111111101000 3
b11111111111111111111111111101000 P
b0 .
b0 >
b0 W
b11111110000000000000010011100011 #
b11111110000000000000010011100011 '
b11111110000000000000010011100011 O
b100000 ;
b111000 9
b110100 !
b110100 (
b110100 <
1%
#140000
0%
#145000
b101101011 *
b101101011 U
b0 8
b0 ?
b0 D
0)
b101101011 $
b101101011 5
b101101011 @
b101101011 K
b10 7
b10 =
0G
b0 6
b0 C
b0 F
b0 /
b0 I
b0 2
b0 H
b0 N
b101101001 .
b101101001 >
b101101001 W
b10 -
b10 M
b10 V
b100100 :
b110011 E
b1010 Q
b1011 R
b1111 T
b111 A
0B
b1011 3
b1011 P
b101101010111011110110011 #
b101101010111011110110011 '
b101101010111011110110011 O
b101111 ;
b100100 9
b100000 !
b100000 (
b100000 <
1%
#150000
0%
#155000
b11111111111111111111111111111110 *
b11111111111111111111111111111110 U
b1 8
b1 ?
b1 D
b1000 3
b1000 P
b11111111111111111111111111111110 $
b11111111111111111111111111111110 5
b11111111111111111111111111111110 @
b11111111111111111111111111111110 K
b1 6
b1 C
b1 F
b10 2
b10 H
b10 N
1G
b0 .
b0 >
b0 W
b101000 :
b1100011 E
b1111 Q
b1000 T
b1 A
b101101111001010001100011 #
b101101111001010001100011 '
b101101111001010001100011 O
b110000 ;
b101000 9
b100100 !
b100100 (
b100100 <
1%
#160000
0%
#165000
b10 *
b10 U
b0 8
b0 ?
b0 D
b10 $
b10 5
b10 @
b10 K
b1 7
b1 =
14
1,
0G
b10 6
b10 C
b10 F
b0 2
b0 H
b0 N
b1 .
b1 >
b1 W
b0 -
b0 M
b0 V
b101100 :
b10011 E
b1100 Q
b1 R
b1100 T
b0 A
b1 3
b1 P
b101100000011000010011 #
b101100000011000010011 '
b101100000011000010011 O
b101101 ;
b101100 9
b101000 !
b101000 (
b101000 <
1%
#170000
0%
#175000
b100 *
b100 U
b110 8
b110 ?
b110 D
b100 $
b100 5
b100 @
b100 K
b110000 :
b1011 Q
b1011 T
b1 A
b10 .
b10 >
b10 W
b101011001010110010011 #
b101011001010110010011 '
b101011001010110010011 O
b110001 ;
b110000 9
b101100 !
b101100 (
b101100 <
1%
#180000
0%
#185000
b10 *
b10 U
b0 8
b0 ?
b0 D
b10 $
b10 5
b10 @
b10 K
b110100 :
b1101 Q
b1101 T
b0 A
b1 .
b1 >
b1 W
b101101000011010010011 #
b101101000011010010011 '
b101101000011010010011 O
b110101 ;
b110100 9
b110000 !
b110000 (
b110000 <
1%
#190000
0%
#195000
b1 /
b1 I
1)
b0 *
b0 U
b10 2
b10 H
b10 N
1G
b1 6
b1 C
b1 F
04
0,
b1 8
b1 ?
b1 D
b0 7
b0 =
b0 $
b0 5
b0 @
b0 K
b100000 :
b1100011 E
b0 Q
b0 R
b1001 T
1B
b11111111111111111111111111101000 3
b11111111111111111111111111101000 P
b0 .
b0 >
b0 W
b11111110000000000000010011100011 #
b11111110000000000000010011100011 '
b11111110000000000000010011100011 O
b100000 ;
b111000 9
b110100 !
b110100 (
b110100 <
1%
#200000
0%
#205000
b101101101 *
b101101101 U
b0 8
b0 ?
b0 D
0)
b101101101 $
b101101101 5
b101101101 @
b101101101 K
b100 7
b100 =
0G
b0 6
b0 C
b0 F
b0 /
b0 I
b0 2
b0 H
b0 N
b101101001 .
b101101001 >
b101101001 W
b100 -
b100 M
b100 V
b100100 :
b110011 E
b1010 Q
b1011 R
b1111 T
b111 A
0B
b1011 3
b1011 P
b101101010111011110110011 #
b101101010111011110110011 '
b101101010111011110110011 O
b101111 ;
b100100 9
b100000 !
b100000 (
b100000 <
1%
#210000
0%
#215000
b11111111111111111111111111111100 *
b11111111111111111111111111111100 U
b1 8
b1 ?
b1 D
b1000 3
b1000 P
b11111111111111111111111111111100 $
b11111111111111111111111111111100 5
b11111111111111111111111111111100 @
b11111111111111111111111111111100 K
b1 6
b1 C
b1 F
b10 2
b10 H
b10 N
1G
b0 .
b0 >
b0 W
b101000 :
b1100011 E
b1111 Q
b1000 T
b1 A
b101101111001010001100011 #
b101101111001010001100011 '
b101101111001010001100011 O
b110000 ;
b101000 9
b100100 !
b100100 (
b100100 <
1%
#220000
0%
#225000
b11 *
b11 U
b0 8
b0 ?
b0 D
b11 $
b11 5
b11 @
b11 K
b1 7
b1 =
14
1,
0G
b10 6
b10 C
b10 F
b0 2
b0 H
b0 N
b10 .
b10 >
b10 W
b0 -
b0 M
b0 V
b101100 :
b10011 E
b1100 Q
b1 R
b1100 T
b0 A
b1 3
b1 P
b101100000011000010011 #
b101100000011000010011 '
b101100000011000010011 O
b101101 ;
b101100 9
b101000 !
b101000 (
b101000 <
1%
#230000
0%
#235000
b1000 *
b1000 U
b110 8
b110 ?
b110 D
b1000 $
b1000 5
b1000 @
b1000 K
b110000 :
b1011 Q
b1011 T
b1 A
b100 .
b100 >
b100 W
b101011001010110010011 #
b101011001010110010011 '
b101011001010110010011 O
b110001 ;
b110000 9
b101100 !
b101100 (
b101100 <
1%
#240000
0%
#245000
b11 *
b11 U
b0 8
b0 ?
b0 D
b11 $
b11 5
b11 @
b11 K
b110100 :
b1101 Q
b1101 T
b0 A
b10 .
b10 >
b10 W
b101101000011010010011 #
b101101000011010010011 '
b101101000011010010011 O
b110101 ;
b110100 9
b110000 !
b110000 (
b110000 <
1%
#250000
0%
#255000
b1 /
b1 I
1)
b0 *
b0 U
b10 2
b10 H
b10 N
1G
b1 6
b1 C
b1 F
04
0,
b1 8
b1 ?
b1 D
b0 7
b0 =
b0 $
b0 5
b0 @
b0 K
b100000 :
b1100011 E
b0 Q
b0 R
b1001 T
1B
b11111111111111111111111111101000 3
b11111111111111111111111111101000 P
b0 .
b0 >
b0 W
b11111110000000000000010011100011 #
b11111110000000000000010011100011 '
b11111110000000000000010011100011 O
b100000 ;
b111000 9
b110100 !
b110100 (
b110100 <
1%
#260000
0%
#265000
b101110001 *
b101110001 U
b0 8
b0 ?
b0 D
0)
b101110001 $
b101110001 5
b101110001 @
b101110001 K
b1000 7
b1000 =
0G
b0 6
b0 C
b0 F
b0 /
b0 I
b0 2
b0 H
b0 N
b101101001 .
b101101001 >
b101101001 W
b1000 -
b1000 M
b1000 V
b100100 :
b110011 E
b1010 Q
b1011 R
b1111 T
b111 A
0B
b1011 3
b1011 P
b101101010111011110110011 #
b101101010111011110110011 '
b101101010111011110110011 O
b101111 ;
b100100 9
b100000 !
b100000 (
b100000 <
1%
#270000
0%
#275000
b11111111111111111111111111111000 *
b11111111111111111111111111111000 U
b1 8
b1 ?
b1 D
b1000 3
b1000 P
b11111111111111111111111111111000 $
b11111111111111111111111111111000 5
b11111111111111111111111111111000 @
b11111111111111111111111111111000 K
b1 6
b1 C
b1 F
b10 2
b10 H
b10 N
1G
b0 .
b0 >
b0 W
b101000 :
b1100011 E
b1111 Q
b1000 T
b1 A
b101101111001010001100011 #
b101101111001010001100011 '
b101101111001010001100011 O
b110000 ;
b101000 9
b100100 !
b100100 (
b100100 <
1%
#280000
0%
#285000
b100 *
b100 U
b0 8
b0 ?
b0 D
b100 $
b100 5
b100 @
b100 K
b1 7
b1 =
14
1,
0G
b10 6
b10 C
b10 F
b0 2
b0 H
b0 N
b11 .
b11 >
b11 W
b0 -
b0 M
b0 V
b101100 :
b10011 E
b1100 Q
b1 R
b1100 T
b0 A
b1 3
b1 P
b101100000011000010011 #
b101100000011000010011 '
b101100000011000010011 O
b101101 ;
b101100 9
b101000 !
b101000 (
b101000 <
1%
#290000
0%
#295000
b10000 *
b10000 U
b110 8
b110 ?
b110 D
b10000 $
b10000 5
b10000 @
b10000 K
b110000 :
b1011 Q
b1011 T
b1 A
b1000 .
b1000 >
b1000 W
b101011001010110010011 #
b101011001010110010011 '
b101011001010110010011 O
b110001 ;
b110000 9
b101100 !
b101100 (
b101100 <
1%
#300000
0%
#305000
b100 *
b100 U
b0 8
b0 ?
b0 D
b100 $
b100 5
b100 @
b100 K
b110100 :
b1101 Q
b1101 T
b0 A
b11 .
b11 >
b11 W
b101101000011010010011 #
b101101000011010010011 '
b101101000011010010011 O
b110101 ;
b110100 9
b110000 !
b110000 (
b110000 <
1%
#310000
0%
#315000
b1 /
b1 I
1)
b0 *
b0 U
b10 2
b10 H
b10 N
1G
b1 6
b1 C
b1 F
04
0,
b1 8
b1 ?
b1 D
b0 7
b0 =
b0 $
b0 5
b0 @
b0 K
b100000 :
b1100011 E
b0 Q
b0 R
b1001 T
1B
b11111111111111111111111111101000 3
b11111111111111111111111111101000 P
b0 .
b0 >
b0 W
b11111110000000000000010011100011 #
b11111110000000000000010011100011 '
b11111110000000000000010011100011 O
b100000 ;
b111000 9
b110100 !
b110100 (
b110100 <
1%
#320000
0%
#325000
b101111001 *
b101111001 U
b0 8
b0 ?
b0 D
0)
b101111001 $
b101111001 5
b101111001 @
b101111001 K
b10000 7
b10000 =
0G
b0 6
b0 C
b0 F
b0 /
b0 I
b0 2
b0 H
b0 N
b101101001 .
b101101001 >
b101101001 W
b10000 -
b10000 M
b10000 V
b100100 :
b110011 E
b1010 Q
b1011 R
b1111 T
b111 A
0B
b1011 3
b1011 P
b101101010111011110110011 #
b101101010111011110110011 '
b101101010111011110110011 O
b101111 ;
b100100 9
b100000 !
b100000 (
b100000 <
1%
#330000
0%
#335000
b11111111111111111111111111110000 *
b11111111111111111111111111110000 U
b1 8
b1 ?
b1 D
b1000 3
b1000 P
b11111111111111111111111111110000 $
b11111111111111111111111111110000 5
b11111111111111111111111111110000 @
b11111111111111111111111111110000 K
b1 6
b1 C
b1 F
b10 2
b10 H
b10 N
1G
b0 .
b0 >
b0 W
b101000 :
b1100011 E
b1111 Q
b1000 T
b1 A
b101101111001010001100011 #
b101101111001010001100011 '
b101101111001010001100011 O
b110000 ;
b101000 9
b100100 !
b100100 (
b100100 <
1%
#340000
0%
#345000
b101 *
b101 U
b0 8
b0 ?
b0 D
b101 $
b101 5
b101 @
b101 K
b1 7
b1 =
14
1,
0G
b10 6
b10 C
b10 F
b0 2
b0 H
b0 N
b100 .
b100 >
b100 W
b0 -
b0 M
b0 V
b101100 :
b10011 E
b1100 Q
b1 R
b1100 T
b0 A
b1 3
b1 P
b101100000011000010011 #
b101100000011000010011 '
b101100000011000010011 O
b101101 ;
b101100 9
b101000 !
b101000 (
b101000 <
1%
#350000
0%
#355000
b100000 *
b100000 U
b110 8
b110 ?
b110 D
b100000 $
b100000 5
b100000 @
b100000 K
b110000 :
b1011 Q
b1011 T
b1 A
b10000 .
b10000 >
b10000 W
b101011001010110010011 #
b101011001010110010011 '
b101011001010110010011 O
b110001 ;
b110000 9
b101100 !
b101100 (
b101100 <
1%
#360000
0%
#365000
b101 *
b101 U
b0 8
b0 ?
b0 D
b101 $
b101 5
b101 @
b101 K
b110100 :
b1101 Q
b1101 T
b0 A
b100 .
b100 >
b100 W
b101101000011010010011 #
b101101000011010010011 '
b101101000011010010011 O
b110101 ;
b110100 9
b110000 !
b110000 (
b110000 <
1%
#370000
0%
