2-2/Bilgisayar Organizasyonu/ödevler/2025/ödev 2/batuhan_odcikin/S1/data_memory.v
`timescale 1ns/1ps
module DataMemory (
    input         clk,
    input         we,
    input  [31:0] addr,
    input  [31:0] wd,
    output [31:0] rd
);
    reg [31:0] mem[0:1023];
    always @(posedge clk)
        if (we)
            mem[addr[11:2]] <= wd;
    assign rd = mem[addr[11:2]];
endmodule

2-2/Bilgisayar Organizasyonu/ödevler/2025/ödev 2/batuhan_odcikin/S1/alu.v
// ALU: Aritmetik ve mantık işlemlerini yapan modül
module ALU (
    input  [31:0] srcA,
    input  [31:0] srcB,
    input  [2:0]  ALUControl,
    output reg [31:0] ALUResult,
    output        Zero
);
    always @(*) begin
        case (ALUControl)
            3'b000: ALUResult = srcA + srcB;               // ADD, ADDI
            3'b001: ALUResult = srcA - srcB;               // SUB, BEQ
            3'b010: ALUResult = srcA & srcB;               // AND, ANDI
            3'b011: ALUResult = srcA | srcB;               // OR, ORI
            3'b101: ALUResult = (srcA < srcB) ? 32'd1 : 32'd0; // SLT, SLTI
            default: ALUResult = 32'd0;
        endcase
    end

    assign Zero = (ALUResult == 32'd0);
endmodule

2-2/Bilgisayar Organizasyonu/ödevler/2025/ödev 2/batuhan_odcikin/S1/alu_control.v
`timescale 1ns/1ps
module ALUControl (
    input  [1:0] aluOp,
    input  [2:0] funct3,
    input        funct7_5,
    output reg [2:0] ALUControl
);
    always @(*) begin
        case(aluOp)
        2'b00: ALUControl=3'b000; // ADD
        2'b01: ALUControl=3'b001; // SUB
        2'b10: begin              // R-type / I-type
            case(funct3)
            3'b000: ALUControl = funct7_5 ? 3'b001 : 3'b000; // SUB/ADD
            3'b010: ALUControl = 3'b101;                    // SLT
            3'b110: ALUControl = 3'b011;                    // OR
            3'b111: ALUControl = 3'b010;                    // AND
            default: ALUControl = 3'b000;
            endcase
        end
        default: ALUControl=3'b000;
        endcase
    end
endmodule

2-2/Bilgisayar Organizasyonu/ödevler/2025/ödev 2/batuhan_odcikin/S1/reg_file.v
// RegFile.v
module RegFile (
    input         clk,
    input         we3,        // write enable
    input  [4:0]  ra1, ra2, ra3,  // read addresses
    input  [4:0]  wa3,       // write address
    input  [31:0] wd3,       // write data
    output [31:0] rd1, rd2   // read data
);
    
    reg [31:0] regs [0:31];
    integer i;
   
    initial begin
        for (i = 0; i < 32; i = i + 1)
            regs[i] = 32'd0;
    end
   
    always @(posedge clk) begin
        if (we3 && wa3 != 5'd0)
            regs[wa3] <= wd3;
    end

    assign rd1 = (ra1 != 5'd0) ? regs[ra1] : 32'd0;
    assign rd2 = (ra2 != 5'd0) ? regs[ra2] : 32'd0;
endmodule

2-2/Bilgisayar Organizasyonu/ödevler/2025/ödev 2/batuhan_odcikin/S2/imm_gen.v
// ======================= ImmGen.v =======================
module ImmGen (
    input  [31:0] instr,
    input  [1:0]  ImmSrc,   // 00=I, 01=S, 10=B, 11=J
    output reg [31:0] immExt
);
    always @(*) begin
        case (ImmSrc)
            2'b00: // I-type
                immExt = {{20{instr[31]}}, instr[31:20]};
            2'b01: // S-type
                immExt = {{20{instr[31]}}, instr[31:25], instr[11:7]};
            2'b10: // B-type (<<1)
                immExt = {{19{instr[31]}}, instr[31], instr[7],
                          instr[30:25], instr[11:8], 1'b0};
            2'b11: // J-type (<<1)
                immExt = {{11{instr[31]}}, instr[31], instr[19:12],
                          instr[20], instr[30:21], 1'b0};
            default:
                immExt = 32'd0;
        endcase
    end
endmodule

2-2/Bilgisayar Organizasyonu/ödevler/2025/ödev 2/batuhan_odcikin/S2/control_unit.v
// ======================= ControlUnit.v =======================
module ControlUnit (
    input  [6:0] opcode,
    input        zero,
    output reg   regWrite,
    output reg   memWrite,
    output reg   aluSrc,
    output reg [1:0] immSrc,
    output reg [1:0] resultSrc,
    output reg [1:0] pcSrc,
    output reg [1:0] aluOp
);
    reg branch;
    always @(*) begin
        // Default değerler
        regWrite  = 1'b0;
        memWrite  = 1'b0;
        aluSrc    = 1'b0;
        immSrc    = 2'b00;
        resultSrc = 2'b00;
        pcSrc     = 2'b00;
        aluOp     = 2'b00;
        branch    = 1'b0;

        case (opcode)
            7'b0000011: begin // LW
                regWrite  = 1; memWrite = 0; aluSrc = 1;
                immSrc    = 2'b00; resultSrc = 2'b01; aluOp = 2'b00;
            end
            7'b0100011: begin // SW
                regWrite  = 0; memWrite = 1; aluSrc = 1;
                immSrc    = 2'b01; aluOp = 2'b00;
            end
            7'b1100011: begin // BEQ
                regWrite  = 0; memWrite = 0; aluSrc = 0; branch = 1;
                immSrc    = 2'b10; aluOp = 2'b01;
            end
            7'b1101111: begin // JAL
                regWrite  = 1; memWrite = 0; aluSrc = 0;
                immSrc    = 2'b11; resultSrc = 2'b10; pcSrc = 2'b10;
            end
            7'b0010011: begin // I-type ALU (ADDI, SLTI, ANDI, ORI)
                regWrite  = 1; memWrite = 0; aluSrc = 1;
                immSrc    = 2'b00; resultSrc = 2'b00; aluOp = 2'b10;
            end
            7'b0110011: begin // R-type ALU (ADD, SUB, SLT, AND, OR)
                regWrite  = 1; memWrite = 0; aluSrc = 0;
                immSrc    = 2'b00; resultSrc = 2'b00; aluOp = 2'b10;
            end
            default: ;
        endcase

        // Branch doğru ve Zero=1 ise PCSrc=01
        if (branch & zero)
            pcSrc = 2'b01;
    end
endmodule

2-2/Bilgisayar Organizasyonu/ödevler/2025/ödev 2/batuhan_odcikin/S1/cpu_top.v
`timescale 1ns/1ps

`include "control_unit.v"
`include "imm_gen.v"
`include "reg_file.v"
`include "alu_control.v"
`include "alu.v"
`include "data_memory.v"

module cpu_top (
    input         clk,
    input         rst,
    output [31:0] pc,
    output [31:0] instr,
    output [31:0] aluOut,
    output [31:0] memReadData
);
   
    reg  [31:0] PC;
    wire [31:0] PCPlus4, PCBranch, PCNext;

    always @(posedge clk or posedge rst) begin
        if (rst) 
            PC <= 0; 
        else 
            PC <= PCNext;
    end
    assign pc       = PC;
    assign PCPlus4  = PC + 4;

    
    reg [31:0] imem [0:255];
    assign instr = imem[PC[9:2]];

    // Main Control
    wire        regWrite, memWrite, aluSrc;
    wire [1:0]  immSrc, resultSrc, pcSrc, aluOp;
    wire        zero;
    ControlUnit control_unit(
        .opcode(instr[6:0]),
        .zero(zero),
        .regWrite(regWrite),
        .memWrite(memWrite),
        .aluSrc(aluSrc),
        .immSrc(immSrc),
        .resultSrc(resultSrc),
        .pcSrc(pcSrc),
        .aluOp(aluOp)
    );

    // Immediate Generator
    wire [31:0] immExt;
    ImmGen imm_gen(
        .instr(instr),
        .ImmSrc(immSrc),
        .immExt(immExt)
    );

    // Register File
    wire [31:0] rd1, rd2;
    wire [31:0] wd3 = (resultSrc==2'b01) ? memReadData :
                      (resultSrc==2'b10) ? PCPlus4 :
                                            aluOut;
    RegFile reg_file(
        .clk(clk),
        .we3(regWrite),
        .ra1(instr[19:15]),
        .ra2(instr[24:20]),
        .wa3(instr[11:7]),
        .wd3(wd3),
        .rd1(rd1),
        .rd2(rd2)
    );

    // ALU Control + ALU
    wire [2:0] aluControl;
    ALUControl alu_control(
        .aluOp(aluOp),
        .funct3(instr[14:12]),
        .funct7_5(instr[30]),
        .ALUControl(aluControl)
    );
    wire [31:0] aluInB = aluSrc ? immExt : rd2;
    ALU alu(
        .srcA(rd1),
        .srcB(aluInB),
        .ALUControl(aluControl),
        .ALUResult(aluOut),
        .Zero(zero)
    );

    // Data Memory
    DataMemory data_memory(
        .clk(clk),
        .we(memWrite),
        .addr(aluOut),
        .wd(rd2),
        .rd(memReadData)
    );

    // PC Next Mux
    assign PCBranch = PCPlus4 + immExt;
    assign PCNext   = (pcSrc==2'b10) ? (PCPlus4 + immExt) :  // JAL
                      (pcSrc==2'b01) ? PCBranch :            // BEQ
                                         PCPlus4;           
endmodule

2-2/Bilgisayar Organizasyonu/ödevler/2025/ödev 2/batuhan_odcikin/S1/cpu_testbench.v
`timescale 1ns/1ps
`include "cpu_top.v"

module tb_cpu_top;
  // Clock & reset
  reg           clk = 0;
  reg           rst = 1;
  // Program memory için sayaç
  integer       i;

  // CPU top-level sinyalleri
  wire [31:0]   pc, instr, aluOut, memReadData;

  // cpu instantiate
  cpu_top cpu (
    .clk(clk), .rst(rst),
    .pc(pc), .instr(instr),
    .aluOut(aluOut), .memReadData(memReadData)
  );

  // 100 MHz clock
  always #5 clk = ~clk;

  initial begin
    // Dalga kaydı
    $dumpfile("tb_cpu_top.vcd");
    $dumpvars(0, tb_cpu_top);

    // --------- PROGRAM YÜKLEME -------------
    cpu.imem[0]  = 32'h00a00093;   // addi x1, x0, 10
    cpu.imem[1]  = 32'h00300113;   // addi x2, x0, 3
    cpu.imem[2]  = 32'h002081b3;   // add x3, x1, x2
    cpu.imem[3]  = 32'h40208233;   // sub x4, x1, x2
    cpu.imem[4]  = 32'h001122b3;   // slt x5, x2, x1
    cpu.imem[5]  = 32'h0020f333;   // and x6, x1, x2
    cpu.imem[6]  = 32'h0020e3b3;   // or  x7, x1, x2
    cpu.imem[7]  = 32'h00f0f413;   // andi x8, x1, 15
    cpu.imem[8]  = 32'h00816493;   // ori  x9, x2, 8
    cpu.imem[9]  = 32'h00302023;   // sw  x3, 0(x0)
    cpu.imem[10] = 32'h00002503;   // lw  x10,0(x0)
    cpu.imem[11] = 32'h00350463;   // beq x10,x3, +8
    cpu.imem[12] = 32'h00100593;   // addi x11,x0,1
    cpu.imem[13] = 32'h0080066f;   // jal x12, +8
    cpu.imem[14] = 32'h00200693;   // addi x13,x0,2
    // Geri kalanları NOP (0) yap
    for (i = 15; i < 70; i = i + 1) begin
      cpu.imem[i] = 32'h00000013;
    end
    // ---------------------------------------

    // Reset’i kaldır
    #20 rst = 0;

    // Bir süre çalışsın
    repeat (70) @(posedge clk);

    $finish;
  end
endmodule

2-2/Bilgisayar Organizasyonu/ödevler/2025/ödev 2/batuhan_odcikin/S1/tb_cpu_top.vcd
$date
	Wed May 07 03:24:24 2025
$end
$version
	Icarus Verilog
$end
$timescale
	1ps
$end
$scope module tb_cpu_top $end
$var wire 32 ! pc [31:0] $end
$var wire 32 " memReadData [31:0] $end
$var wire 32 # instr [31:0] $end
$var wire 32 $ aluOut [31:0] $end
$var reg 1 % clk $end
$var reg 1 & rst $end
$var integer 32 ' i [31:0] $end
$scope module cpu $end
$var wire 1 % clk $end
$var wire 32 ( instr [31:0] $end
$var wire 32 ) pc [31:0] $end
$var wire 1 & rst $end
$var wire 1 * zero $end
$var wire 32 + wd3 [31:0] $end
$var wire 2 , resultSrc [1:0] $end
$var wire 1 - regWrite $end
$var wire 32 . rd2 [31:0] $end
$var wire 32 / rd1 [31:0] $end
$var wire 2 0 pcSrc [1:0] $end
$var wire 1 1 memWrite $end
$var wire 32 2 memReadData [31:0] $end
$var wire 2 3 immSrc [1:0] $end
$var wire 32 4 immExt [31:0] $end
$var wire 1 5 aluSrc $end
$var wire 32 6 aluOut [31:0] $end
$var wire 2 7 aluOp [1:0] $end
$var wire 32 8 aluInB [31:0] $end
$var wire 3 9 aluControl [2:0] $end
$var wire 32 : PCPlus4 [31:0] $end
$var wire 32 ; PCNext [31:0] $end
$var wire 32 < PCBranch [31:0] $end
$var reg 32 = PC [31:0] $end
$scope module alu $end
$var wire 32 > srcB [31:0] $end
$var wire 32 ? srcA [31:0] $end
$var wire 1 * Zero $end
$var wire 3 @ ALUControl [2:0] $end
$var reg 32 A ALUResult [31:0] $end
$upscope $end
$scope module alu_control $end
$var wire 3 B funct3 [2:0] $end
$var wire 1 C funct7_5 $end
$var wire 2 D aluOp [1:0] $end
$var reg 3 E ALUControl [2:0] $end
$upscope $end
$scope module control_unit $end
$var wire 7 F opcode [6:0] $end
$var wire 1 * zero $end
$var reg 2 G aluOp [1:0] $end
$var reg 1 5 aluSrc $end
$var reg 1 H branch $end
$var reg 2 I immSrc [1:0] $end
$var reg 1 1 memWrite $end
$var reg 2 J pcSrc [1:0] $end
$var reg 1 - regWrite $end
$var reg 2 K resultSrc [1:0] $end
$upscope $end
$scope module data_memory $end
$var wire 32 L addr [31:0] $end
$var wire 1 % clk $end
$var wire 32 M rd [31:0] $end
$var wire 1 1 we $end
$var wire 32 N wd [31:0] $end
$upscope $end
$scope module imm_gen $end
$var wire 2 O ImmSrc [1:0] $end
$var wire 32 P instr [31:0] $end
$var reg 32 Q immExt [31:0] $end
$upscope $end
$scope module reg_file $end
$var wire 1 % clk $end
$var wire 5 R ra1 [4:0] $end
$var wire 5 S ra2 [4:0] $end
$var wire 5 T ra3 [4:0] $end
$var wire 5 U wa3 [4:0] $end
$var wire 32 V wd3 [31:0] $end
$var wire 1 - we3 $end
$var wire 32 W rd2 [31:0] $end
$var wire 32 X rd1 [31:0] $end
$var integer 32 Y i [31:0] $end
$upscope $end
$upscope $end
$upscope $end
$enddefinitions $end
$comment Show the parameter values. $end
$dumpall
$end
#0
$dumpvars
b100000 Y
b0 X
b0 W
b1010 V
b1 U
bz T
b1010 S
b0 R
b1010 Q
b101000000000000010010011 P
b0 O
b0 N
bx M
b1010 L
b0 K
b0 J
b0 I
0H
b10 G
b10011 F
b0 E
b10 D
0C
b0 B
b1010 A
b0 @
b0 ?
b1010 >
b0 =
b1110 <
b100 ;
b100 :
b0 9
b1010 8
b10 7
b1010 6
15
b1010 4
b0 3
bx 2
01
b0 0
b0 /
b0 .
1-
b0 ,
b1010 +
0*
b0 )
b101000000000000010010011 (
b1000110 '
1&
0%
b1010 $
b101000000000000010010011 #
bx "
b0 !
$end
#5000
1%
#10000
0%
#15000
1%
#20000
0%
0&
#25000
b11 +
b11 V
b11 $
b11 6
b11 A
b11 L
b11 8
b11 >
b1000 ;
b11 S
b10 U
b11 4
b11 Q
b1100000000000100010011 #
b1100000000000100010011 (
b1100000000000100010011 P
b1011 <
b1000 :
b100 !
b100 )
b100 =
1%
#30000
0%
#35000
b1101 +
b1101 V
b1101 $
b1101 6
b1101 A
b1101 L
b10 7
b10 D
b10 G
05
1-
b1010 /
b1010 ?
b1010 X
b11 .
b11 N
b11 W
b11 8
b11 >
b1100 ;
b110011 F
b1 R
b10 S
b11 U
b10 4
b10 Q
b1000001000000110110011 #
b1000001000000110110011 (
b1000001000000110110011 P
b1110 <
b1100 :
b1000 !
b1000 )
b1000 =
1%
#40000
0%
#45000
b111 +
b111 V
b111 $
b111 6
b111 A
b111 L
b1 9
b1 @
b1 E
b10000 ;
b100 U
1C
b10000000010 4
b10000000010 Q
b1000000001000001000001000110011 #
b1000000001000001000001000110011 (
b1000000001000001000001000110011 P
b10000010010 <
b10000 :
b1100 !
b1100 )
b1100 =
1%
#50000
0%
#55000
b1 +
b1 V
b10 7
b10 D
b10 G
1-
b1010 8
b1010 >
0*
b1 $
b1 6
b1 A
b1 L
b11 /
b11 ?
b11 X
b1010 .
b1010 N
b1010 W
b101 9
b101 @
b101 E
b10100 ;
b10 R
b1 S
b101 U
b10 B
0C
b1 4
b1 Q
b100010010001010110011 #
b100010010001010110011 (
b100010010001010110011 P
b10101 <
b10100 :
b10000 !
b10000 )
b10000 =
1%
#60000
0%
#65000
b10 +
b10 V
b11 8
b11 >
b10 $
b10 6
b10 A
b10 L
b1010 /
b1010 ?
b1010 X
b11 .
b11 N
b11 W
b10 9
b10 @
b10 E
b11000 ;
b1 R
b10 S
b110 U
b111 B
b10 4
b10 Q
b1000001111001100110011 #
b1000001111001100110011 (
b1000001111001100110011 P
b11010 <
b11000 :
b10100 !
b10100 )
b10100 =
1%
#70000
0%
#75000
b1011 +
b1011 V
b1011 $
b1011 6
b1011 A
b1011 L
b11 9
b11 @
b11 E
b11100 ;
b111 U
b110 B
b1000001110001110110011 #
b1000001110001110110011 (
b1000001110001110110011 P
b11110 <
b11100 :
b11000 !
b11000 )
b11000 =
1%
#80000
0%
#85000
b1010 +
b1010 V
b1111 8
b1111 >
b1010 $
b1010 6
b1010 A
b1010 L
15
b10 7
b10 D
b10 G
1-
b0 .
b0 N
b0 W
b10 9
b10 @
b10 E
b100000 ;
b10011 F
b1111 S
b1000 U
b111 B
b1111 4
b1111 Q
b111100001111010000010011 #
b111100001111010000010011 (
b111100001111010000010011 P
b101111 <
b100000 :
b11100 !
b11100 )
b11100 =
1%
#90000
0%
#95000
b1011 +
b1011 V
b1011 $
b1011 6
b1011 A
b1011 L
b11 /
b11 ?
b11 X
b1010 .
b1010 N
b1010 W
b11 9
b11 @
b11 E
b1000 8
b1000 >
b100100 ;
b10 R
b1000 S
b1001 U
b110 B
b1000 4
b1000 Q
b100000010110010010010011 #
b100000010110010010010011 (
b100000010110010010010011 P
b101100 <
b100100 :
b100000 !
b100000 )
b100000 =
1%
#100000
0%
#105000
1*
b0 +
b0 V
b0 $
b0 6
b0 A
b0 L
b1 3
b1 I
b1 O
11
b0 7
b0 D
b0 G
15
0-
b0 /
b0 ?
b0 X
b1101 .
b1101 N
b1101 W
b0 9
b0 @
b0 E
b0 8
b0 >
b101000 ;
b100011 F
b0 R
b11 S
b0 U
b10 B
b0 4
b0 Q
b1100000010000000100011 #
b1100000010000000100011 (
b1100000010000000100011 P
b101000 <
b101000 :
b100100 !
b100100 )
b100100 =
1%
#110000
0%
#115000
b1101 +
b1101 V
1*
b0 $
b0 6
b0 A
b0 L
b1 ,
b1 K
1-
b0 3
b0 I
b0 O
15
01
b0 .
b0 N
b0 W
b0 8
b0 >
b101100 ;
b11 F
b0 S
b1010 U
b0 4
b0 Q
b10010100000011 #
b10010100000011 (
b10010100000011 P
b1101 "
b1101 2
b1101 M
b101100 <
b101100 :
b101000 !
b101000 )
b101000 =
1%
#120000
0%
#125000
b1101 "
b1101 2
b1101 M
b1 9
b1 @
b1 E
b0 +
b0 V
1*
b0 $
b0 6
b0 A
b0 L
b1 0
b1 J
b1 7
b1 D
b1 G
b10 3
b10 I
b10 O
1H
b0 ,
b0 K
05
0-
b1101 /
b1101 ?
b1101 X
b1101 .
b1101 N
b1101 W
b1101 8
b1101 >
b111000 ;
b1100011 F
b1010 R
b11 S
b1000 U
b0 B
b1000 4
b1000 Q
b1101010000010001100011 #
b1101010000010001100011 (
b1101010000010001100011 P
b111000 <
b110000 :
b101100 !
b101100 )
b101100 =
1%
#130000
0%
#135000
b10 +
b10 V
b1101 "
b1101 2
b1101 M
b0 9
b0 @
b0 E
0*
b10 $
b10 6
b10 A
b10 L
b10 8
b10 >
15
1-
0H
b10 7
b10 D
b10 G
b0 0
b0 J
b0 3
b0 I
b0 O
b0 /
b0 ?
b0 X
b11 .
b11 N
b11 W
b111100 ;
b10011 F
b0 R
b10 S
b1101 U
b10 4
b10 Q
b1000000000011010010011 #
b1000000000011010010011 (
b1000000000011010010011 P
b111110 <
b111100 :
b111000 !
b111000 )
b111000 =
1%
#140000
0%
#145000
b0 +
b0 V
b10 7
b10 D
b10 G
15
1-
1*
b0 $
b0 6
b0 A
b0 L
b0 .
b0 N
b0 W
b0 8
b0 >
b1000000 ;
b0 S
b0 U
b0 4
b0 Q
b10011 #
b10011 (
b10011 P
b1000000 <
b1000000 :
b111100 !
b111100 )
b111100 =
1%
#150000
0%
#155000
b1000100 ;
b1000100 <
b1000100 :
b1000000 !
b1000000 )
b1000000 =
1%
#160000
0%
#165000
b1001000 ;
b1001000 <
b1001000 :
b1000100 !
b1000100 )
b1000100 =
1%
#170000
0%
#175000
b1001100 ;
b1001100 <
b1001100 :
b1001000 !
b1001000 )
b1001000 =
1%
#180000
0%
#185000
b1010000 ;
b1010000 <
b1010000 :
b1001100 !
b1001100 )
b1001100 =
1%
#190000
0%
#195000
b1010100 ;
b1010100 <
b1010100 :
b1010000 !
b1010000 )
b1010000 =
1%
#200000
0%
#205000
b1011000 ;
b1011000 <
b1011000 :
b1010100 !
b1010100 )
b1010100 =
1%
#210000
0%
#215000
b1011100 ;
b1011100 <
b1011100 :
b1011000 !
b1011000 )
b1011000 =
1%
#220000
0%
#225000
b1100000 ;
b1100000 <
b1100000 :
b1011100 !
b1011100 )
b1011100 =
1%
#230000
0%
#235000
b1100100 ;
b1100100 <
b1100100 :
b1100000 !
b1100000 )
b1100000 =
1%
#240000
0%
#245000
b1101000 ;
b1101000 <
b1101000 :
b1100100 !
b1100100 )
b1100100 =
1%
#250000
0%
#255000
b1101100 ;
b1101100 <
b1101100 :
b1101000 !
b1101000 )
b1101000 =
1%
#260000
0%
#265000
b1110000 ;
b1110000 <
b1110000 :
b1101100 !
b1101100 )
b1101100 =
1%
#270000
0%
#275000
b1110100 ;
b1110100 <
b1110100 :
b1110000 !
b1110000 )
b1110000 =
1%
#280000
0%
#285000
b1111000 ;
b1111000 <
b1111000 :
b1110100 !
b1110100 )
b1110100 =
1%
#290000
0%
#295000
b1111100 ;
b1111100 <
b1111100 :
b1111000 !
b1111000 )
b1111000 =
1%
#300000
0%
#305000
b10000000 ;
b10000000 <
b10000000 :
b1111100 !
b1111100 )
b1111100 =
1%
#310000
0%
#315000
b10000100 ;
b10000100 <
b10000100 :
b10000000 !
b10000000 )
b10000000 =
1%
#320000
0%
#325000
b10001000 ;
b10001000 <
b10001000 :
b10000100 !
b10000100 )
b10000100 =
1%
#330000
0%
#335000
b10001100 ;
b10001100 <
b10001100 :
b10001000 !
b10001000 )
b10001000 =
1%
#340000
0%
#345000
b10010000 ;
b10010000 <
b10010000 :
b10001100 !
b10001100 )
b10001100 =
1%
#350000
0%
#355000
b10010100 ;
b10010100 <
b10010100 :
b10010000 !
b10010000 )
b10010000 =
1%
#360000
0%
#365000
b10011000 ;
b10011000 <
b10011000 :
b10010100 !
b10010100 )
b10010100 =
1%
#370000
0%
#375000
b10011100 ;
b10011100 <
b10011100 :
b10011000 !
b10011000 )
b10011000 =
1%
#380000
0%
#385000
b10100000 ;
b10100000 <
b10100000 :
b10011100 !
b10011100 )
b10011100 =
1%
#390000
0%
#395000
b10100100 ;
b10100100 <
b10100100 :
b10100000 !
b10100000 )
b10100000 =
1%
#400000
0%
#405000
b10101000 ;
b10101000 <
b10101000 :
b10100100 !
b10100100 )
b10100100 =
1%
#410000
0%
#415000
b10101100 ;
b10101100 <
b10101100 :
b10101000 !
b10101000 )
b10101000 =
1%
#420000
0%
#425000
b10110000 ;
b10110000 <
b10110000 :
b10101100 !
b10101100 )
b10101100 =
1%
#430000
0%
#435000
b10110100 ;
b10110100 <
b10110100 :
b10110000 !
b10110000 )
b10110000 =
1%
#440000
0%
#445000
b10111000 ;
b10111000 <
b10111000 :
b10110100 !
b10110100 )
b10110100 =
1%
#450000
0%
#455000
b10111100 ;
b10111100 <
b10111100 :
b10111000 !
b10111000 )
b10111000 =
1%
#460000
0%
#465000
b11000000 ;
b11000000 <
b11000000 :
b10111100 !
b10111100 )
b10111100 =
1%
#470000
0%
#475000
b11000100 ;
b11000100 <
b11000100 :
b11000000 !
b11000000 )
b11000000 =
1%
#480000
0%
#485000
b11001000 ;
b11001000 <
b11001000 :
b11000100 !
b11000100 )
b11000100 =
1%
#490000
0%
#495000
b11001100 ;
b11001100 <
b11001100 :
b11001000 !
b11001000 )
b11001000 =
1%
#500000
0%
#505000
b11010000 ;
b11010000 <
b11010000 :
b11001100 !
b11001100 )
b11001100 =
1%
#510000
0%
#515000
b11010100 ;
b11010100 <
b11010100 :
b11010000 !
b11010000 )
b11010000 =
1%
#520000
0%
#525000
b11011000 ;
b11011000 <
b11011000 :
b11010100 !
b11010100 )
b11010100 =
1%
#530000
0%
#535000
b11011100 ;
b11011100 <
b11011100 :
b11011000 !
b11011000 )
b11011000 =
1%
#540000
0%
#545000
b11100000 ;
b11100000 <
b11100000 :
b11011100 !
b11011100 )
b11011100 =
1%
#550000
0%
#555000
b11100100 ;
b11100100 <
b11100100 :
b11100000 !
b11100000 )
b11100000 =
1%
#560000
0%
#565000
b11101000 ;
b11101000 <
b11101000 :
b11100100 !
b11100100 )
b11100100 =
1%
#570000
0%
#575000
b11101100 ;
b11101100 <
b11101100 :
b11101000 !
b11101000 )
b11101000 =
1%
#580000
0%
#585000
b11110000 ;
b11110000 <
b11110000 :
b11101100 !
b11101100 )
b11101100 =
1%
#590000
0%
#595000
b11110100 ;
b11110100 <
b11110100 :
b11110000 !
b11110000 )
b11110000 =
1%
#600000
0%
#605000
b11111000 ;
b11111000 <
b11111000 :
b11110100 !
b11110100 )
b11110100 =
1%
#610000
0%
#615000
b11111100 ;
b11111100 <
b11111100 :
b11111000 !
b11111000 )
b11111000 =
1%
#620000
0%
#625000
b100000000 ;
b100000000 <
b100000000 :
b11111100 !
b11111100 )
b11111100 =
1%
#630000
0%
#635000
b100000100 ;
b100000100 <
b100000100 :
b100000000 !
b100000000 )
b100000000 =
1%
#640000
0%
#645000
b100001000 ;
b100001000 <
b100001000 :
b100000100 !
b100000100 )
b100000100 =
1%
#650000
0%
#655000
b100001100 ;
b100001100 <
b100001100 :
b100001000 !
b100001000 )
b100001000 =
1%
#660000
0%
#665000
b100010000 ;
b100010000 <
b100010000 :
b100001100 !
b100001100 )
b100001100 =
1%
#670000
0%
#675000
b100010100 ;
b100010100 <
b100010100 :
b100010000 !
b100010000 )
b100010000 =
1%
#680000
0%
#685000
b100011000 ;
b100011000 <
b100011000 :
b100010100 !
b100010100 )
b100010100 =
1%
#690000
0%
#695000
bx +
bx V
bx "
bx 2
bx M
x*
bx $
bx 6
bx A
bx L
b0 7
b0 D
b0 G
05
0-
bx /
bx ?
bx X
bx .
bx N
bx W
bx 8
bx >
b100011100 ;
bx F
bx R
bx S
bx U
bx B
xC
bx 4
bx Q
bx #
bx (
bx P
bx <
b100011100 :
b100011000 !
b100011000 )
b100011000 =
1%
#700000
0%
#705000
b100100000 ;
b100100000 :
b100011100 !
b100011100 )
b100011100 =
1%
#710000
0%
#715000
b100100100 ;
b100100100 :
b100100000 !
b100100000 )
b100100000 =
1%
