2-2/Bilgisayar Organizasyonu/ödevler/2024/tarık_taşkın/bilgisayar_organizasyonu/ödev_2/q_2/SCPwithSra.v
module singleCycleProcessorWithSra(clk, rst);
    input clk, rst;

    wire PCSrc, regWrite, zero, memWrite, ALUSrc;
    wire [1:0] immSrc, resultSrc;
    wire [2:0] ALUControl;
    wire [31:0] PCNext, PCPlus4, PCTarget;
    wire [31:0] RD1, RD2, immExt, PC, instruction, result;
    wire [31:0] srcB, ALUResult, readData;
    
    PC pc(PC, PCNext, clk, rst);
    adder PCAdder(PCPlus4, PC, 32'd4);
    mux nextPC(PCNext, PCPlus4, PCTarget, PCSrc);
    adder jumpAdder(PCTarget, PC, immExt);

    instructionMemory instrMem(instruction, PC, rst);
    regFile regF(RD1, RD2, instruction[19:15], instruction[24:20], instruction[11:7], result, regWrite, clk, rst);
    signExtender signExt(immExt, instruction, immSrc);   
    mux muxRegtoALU(srcB, RD2, immExt, ALUSrc);
    ALU alu(ALUResult, zero, RD1, srcB, ALUControl);
    controlUnit control(PCSrc, resultSrc, memWrite, ALUControl, ALUSrc, immSrc, regWrite, instruction[6:0], instruction[14:12], instruction[31:25], zero);
    dataMemory dataMem(readData, ALUResult, RD2, memWrite, clk, rst);
    mux4 muxDatatoReg1(result, ALUResult, readData, PCPlus4, {32{1'bx}}, resultSrc);
endmodule

module ALU(result, zero, A, B, ALUControl);
    input [31:0] A, B;
    input [2:0] ALUControl;

    output [31:0] result;
    output zero;
    
    wire [31:0] sum, sra;
    wire msb;
    
    assign sum = ALUControl[0] ? (A + (~B + 1)) : (A + B);
    assign sra = $signed(A) >>> B; // sağa kaydırma işlemi A'nın MSB'i dikkate alınarak gerçekleştirilir.
    
    assign result = (ALUControl == 3'b000) ? sum :
                    (ALUControl == 3'b001) ? sum :
                    (ALUControl == 3'b010) ? A & B :
                    (ALUControl == 3'b011) ? A | B :
                    (ALUControl == 3'b100) ? sra : // sra işlemi 100 seçim bitiyle sonuç olarak çıkar.
                    (ALUControl == 3'b101) ? {{31{1'b0}}, sum[31]} :
                    {32{1'bx}};

    assign zero = (result == 32'b0);
endmodule

module adder(result, A, B);
    input [31:0] A, B;
    output [31:0] result;

    assign result = A + B;
endmodule

module PC(PC, PCNext, clk, rst);
    input [31:0] PCNext;
    input clk, rst;
    output reg [31:0] PC;

    always@(posedge clk)
        if(~rst) PC <= PCNext;
        else PC <= {32{1'b0}};
endmodule

module signExtender(immExt, instruction, immSrc);
    input [31:0] instruction;
    input [1:0] immSrc;
    output [31:0] immExt;

    assign immExt = (immSrc == 2'b00) ? {{20{instruction[31]}}, instruction[31:20]} : // I-Type
                    (immSrc == 2'b01) ? {{20{instruction[31]}}, instruction[31:25], instruction[11:7]} : // S-Type
                    (immSrc == 2'b10) ? {{19{instruction[31]}}, instruction[31], instruction[7], instruction[30:25], instruction[11:8], 1'b0} : // B-Type
                    {{12{instruction[31]}}, instruction[19:12], instruction[20], instruction[30:21], 1'b0} ; // J-Type
endmodule

module mux(result, A, B, select);
    input [31:0] A, B;
    input select;    
    output [31:0] result;

    assign result = select ? B : A;
endmodule

module mux4(result, A, B, C, D, select);
    input [31:0] A, B, C, D;
    input [1:0] select;    
    output [31:0] result;

    assign result = (select == 2'b00) ? A :
                    (select == 2'b01) ? B :
                    (select == 2'b10) ? C : D;
endmodule

module regFile(RD1, RD2, A1, A2, A3, WD3, WE3, clk, rst);
    input [4:0] A1, A2, A3;
    input clk, rst, WE3;
    input [31:0] WD3;
    output [31:0] RD1, RD2;

    reg [31:0] register[31:0];

    integer i;
    initial begin
        for (i=0; i<32; i=i+1) begin
            register[i] = 0;
        end
    end

    always@(posedge clk)
        if(WE3) register[A3] <= WD3;
    
    //aşağıda bi terslik var
    assign RD1 = (~rst) ? register[A1] : {32{1'b0}};
    assign RD2 = (~rst) ? register[A2] : {32{1'b0}};    
endmodule

module instructionMemory(RD, A, rst);
    input [31:0] A;
    input rst;
    output [31:0] RD;

    reg [31:0] memory[31:0];

    initial
        begin
            $readmemh("instructionMemory.dat", memory);
            /*
                addi x5, x5, 146    // x5 = 146
                addi x6, x6, 4      // x6 = 4
                sra  x5, x5, x6     // x5 = 146 / 2^4 = 9
                addi x7, zero, -146 // x7 = -146 (FFFFFF6E)
                sra  x7, x7, x6     // x7 = -146/ 2^4 = -10 (FFFFFFF6)
            */
        end

    assign RD = (rst) ? {32{1'b0}} : memory[A/4]; //sadece 4'ün katlarındaki verileri okumaması için

endmodule

module dataMemory(RD, A, WD, WE, clk, rst);
    input [31:0] A, WD;
    input WE, clk, rst;
    output [31:0] RD;

    reg [31:0] memory[63:0];

    always@(posedge clk)
        if(WE) memory[A] <= WD;

    assign RD = (rst) ? {32{1'b0}} : memory[A];
endmodule

module ALUDecoder(ALUControl, funct3, funct7, op, ALUOp);
    input [2:0] funct3;
    input [6:0] funct7, op;
    input [1:0] ALUOp;
    output [2:0] ALUControl;

    assign ALUControl = (ALUOp == 2'b00) ? 3'b000 : // lw, sw (add)
                        (ALUOp == 2'b01) ? 3'b001 : // beq (sub)
                        ((ALUOp == 2'b10) & (funct3 == 3'b000) & ({op[5], funct7[5]} == 2'b11)) ? 3'b001 : // sub
                        ((ALUOp == 2'b10) & (funct3 == 3'b000) & ({op[5], funct7[5]} != 2'b11)) ? 3'b000 : // add
                        ((ALUOp == 2'b10) & (funct3 == 3'b010)) ? 3'b101 : // slt
                        ((ALUOp == 2'b10) & (funct3 == 3'b101) & ({op[5], funct7[5]} == 2'b11)) ? 3'b100 : //sra
                        ((ALUOp == 2'b10) & (funct3 == 3'b110)) ? 3'b011 : // or
                        ((ALUOp == 2'b10) & (funct3 == 3'b111)) ? 3'b010 : // and
                                                                  3'bxxx ;
endmodule

module mainDecoder(regWrite, immSrc, ALUSrc, memWrite, resultSrc, branch, ALUOp, jump, op);
    input [6:0] op;
    output regWrite, ALUSrc, memWrite, branch, jump;
    output [1:0] ALUOp, immSrc, resultSrc;

    assign regWrite = (op == 7'b0000011 | op == 7'b0110011 | op == 7'b0010011 | op == 7'b1101111) ? 1'b1 : 1'b0;
    assign immSrc = (op == 7'b0000011 | op == 7'b0010011) ? 2'b00 :
                    (op == 7'b0100011) ? 2'b01 :
                    (op == 7'b1100011) ? 2'b10 :
                    (op == 7'b1101111) ? 2'b11 : 
                    2'bxx;
    assign ALUSrc = (op == 7'b0000011 | op == 7'b0100011 | op == 7'b0010011) ? 1'b1 :
                    (op == 7'b0110011 | op == 7'b1100011) ? 1'b0 :
                    1'bx;
    assign memWrite = (op == 7'b0100011) ? 1'b1 : 1'b0;
    assign resultSrc = (op == 7'b0110011 | op == 7'b0010011) ? 2'b00 :
                       (op == 7'b0000011) ? 2'b01 : 
                       (op == 7'b1101111) ? 2'b10 :
                       2'bxx;
    assign branch = (op == 7'b1100011) ? 1'b1 : 1'b0;
    assign ALUOp = (op == 7'b0000011 | op == 7'b0100011) ? 2'b00 :
                   (op == 7'b1100011) ? 2'b01 : 
                   (op == 7'b0110011 | op == 7'b0010011) ? 2'b10 :
                   2'bxx;
    assign jump = (op == 7'b1101111) ? 1'b1 : 1'b0;
endmodule

module controlUnit(PCSrc, resultSrc, memWrite, ALUControl, ALUSrc, immSrc, regWrite, op, funct3, funct7, zero);
    input [6:0] op, funct7;
    input [2:0] funct3;
    input zero;

    output PCSrc, memWrite, ALUSrc, regWrite;
    output [1:0] resultSrc, immSrc;
    output [2:0] ALUControl;

    wire [1:0] ALUOp;
    wire branch, jump;

    mainDecoder mainDecoder(regWrite, immSrc, ALUSrc, memWrite, resultSrc, branch, ALUOp, jump, op);
    ALUDecoder ALUDecoder(ALUControl, funct3, funct7, op, ALUOp);

    assign PCSrc = (zero & branch) | jump;
endmodule

2-2/Bilgisayar Organizasyonu/ödevler/2024/tarık_taşkın/bilgisayar_organizasyonu/ödev_2/q_2/SCPwithSra_tb.v
`include "SCPwithSra.v"

module SCPwithSra_tb();
    reg clk = 1'b1;
    reg rst = 1'b1;

    singleCycleProcessorWithSra scp(clk, rst);

    initial begin
        $dumpfile("SCPwithSra_tb.vcd");
        $dumpvars(0, SCPwithSra_tb);
    end

    always begin
        clk = ~clk; #5;
    end

    initial begin
        rst <= 1'b0; #175;
        rst <= 1'b1; #5;
        $finish;
    end
endmodule

//iverilog -o SCPwithSra_tb.vvp SCPwithSra_tb.v
//vvp SCPwithSra_tb.vvp

2-2/Bilgisayar Organizasyonu/ödevler/2024/tarık_taşkın/bilgisayar_organizasyonu/ödev_2/q_2/scpwithsra_tb.vcd
$date
	Wed May 08 23:08:50 2024
$end
$version
	Icarus Verilog
$end
$timescale
	1s
$end
$scope module SCPwithSra_tb $end
$var reg 1 ! clk $end
$var reg 1 " rst $end
$scope module scp $end
$var wire 1 ! clk $end
$var wire 1 " rst $end
$var wire 1 # zero $end
$var wire 32 $ srcB [31:0] $end
$var wire 2 % resultSrc [1:0] $end
$var wire 32 & result [31:0] $end
$var wire 1 ' regWrite $end
$var wire 32 ( readData [31:0] $end
$var wire 1 ) memWrite $end
$var wire 32 * instruction [31:0] $end
$var wire 2 + immSrc [1:0] $end
$var wire 32 , immExt [31:0] $end
$var wire 32 - RD2 [31:0] $end
$var wire 32 . RD1 [31:0] $end
$var wire 32 / PCTarget [31:0] $end
$var wire 1 0 PCSrc $end
$var wire 32 1 PCPlus4 [31:0] $end
$var wire 32 2 PCNext [31:0] $end
$var wire 32 3 PC [31:0] $end
$var wire 1 4 ALUSrc $end
$var wire 32 5 ALUResult [31:0] $end
$var wire 3 6 ALUControl [2:0] $end
$scope module PCAdder $end
$var wire 32 7 B [31:0] $end
$var wire 32 8 result [31:0] $end
$var wire 32 9 A [31:0] $end
$upscope $end
$scope module alu $end
$var wire 1 # zero $end
$var wire 32 : sum [31:0] $end
$var wire 32 ; sra [31:0] $end
$var wire 32 < result [31:0] $end
$var wire 32 = B [31:0] $end
$var wire 3 > ALUControl [2:0] $end
$var wire 32 ? A [31:0] $end
$upscope $end
$scope module control $end
$var wire 1 0 PCSrc $end
$var wire 3 @ funct3 [2:0] $end
$var wire 7 A funct7 [6:0] $end
$var wire 7 B op [6:0] $end
$var wire 1 # zero $end
$var wire 2 C resultSrc [1:0] $end
$var wire 1 ' regWrite $end
$var wire 1 ) memWrite $end
$var wire 1 D jump $end
$var wire 2 E immSrc [1:0] $end
$var wire 1 F branch $end
$var wire 1 4 ALUSrc $end
$var wire 2 G ALUOp [1:0] $end
$var wire 3 H ALUControl [2:0] $end
$scope module ALUDecoder $end
$var wire 3 I funct3 [2:0] $end
$var wire 7 J funct7 [6:0] $end
$var wire 7 K op [6:0] $end
$var wire 2 L ALUOp [1:0] $end
$var wire 3 M ALUControl [2:0] $end
$upscope $end
$scope module mainDecoder $end
$var wire 7 N op [6:0] $end
$var wire 2 O resultSrc [1:0] $end
$var wire 1 ' regWrite $end
$var wire 1 ) memWrite $end
$var wire 1 D jump $end
$var wire 2 P immSrc [1:0] $end
$var wire 1 F branch $end
$var wire 1 4 ALUSrc $end
$var wire 2 Q ALUOp [1:0] $end
$upscope $end
$upscope $end
$scope module dataMem $end
$var wire 32 R A [31:0] $end
$var wire 1 ) WE $end
$var wire 1 ! clk $end
$var wire 1 " rst $end
$var wire 32 S WD [31:0] $end
$var wire 32 T RD [31:0] $end
$upscope $end
$scope module instrMem $end
$var wire 1 " rst $end
$var wire 32 U RD [31:0] $end
$var wire 32 V A [31:0] $end
$upscope $end
$scope module jumpAdder $end
$var wire 32 W result [31:0] $end
$var wire 32 X B [31:0] $end
$var wire 32 Y A [31:0] $end
$upscope $end
$scope module muxDatatoReg1 $end
$var wire 32 Z A [31:0] $end
$var wire 32 [ B [31:0] $end
$var wire 32 \ C [31:0] $end
$var wire 32 ] D [31:0] $end
$var wire 2 ^ select [1:0] $end
$var wire 32 _ result [31:0] $end
$upscope $end
$scope module muxRegtoALU $end
$var wire 1 4 select $end
$var wire 32 ` result [31:0] $end
$var wire 32 a B [31:0] $end
$var wire 32 b A [31:0] $end
$upscope $end
$scope module nextPC $end
$var wire 32 c A [31:0] $end
$var wire 32 d B [31:0] $end
$var wire 1 0 select $end
$var wire 32 e result [31:0] $end
$upscope $end
$scope module pc $end
$var wire 32 f PCNext [31:0] $end
$var wire 1 ! clk $end
$var wire 1 " rst $end
$var reg 32 g PC [31:0] $end
$upscope $end
$scope module regF $end
$var wire 5 h A1 [4:0] $end
$var wire 5 i A2 [4:0] $end
$var wire 5 j A3 [4:0] $end
$var wire 32 k WD3 [31:0] $end
$var wire 1 ' WE3 $end
$var wire 1 ! clk $end
$var wire 1 " rst $end
$var wire 32 l RD2 [31:0] $end
$var wire 32 m RD1 [31:0] $end
$var integer 32 n i [31:0] $end
$upscope $end
$scope module signExt $end
$var wire 2 o immSrc [1:0] $end
$var wire 32 p instruction [31:0] $end
$var wire 32 q immExt [31:0] $end
$upscope $end
$upscope $end
$upscope $end
$enddefinitions $end
$comment Show the parameter values. $end
$dumpall
$end
#0
$dumpvars
b10010010 q
b1001001000101000001010010011 p
b0 o
b100000 n
b0 m
b0 l
b10010010 k
b101 j
b10010 i
b101 h
b0 g
b100 f
b100 e
b10010010 d
b100 c
b0 b
b10010010 a
b10010010 `
b10010010 _
b0 ^
bx ]
b100 \
bx [
b10010010 Z
b0 Y
b10010010 X
b10010010 W
b0 V
b1001001000101000001010010011 U
bx T
b0 S
b10010010 R
b10 Q
b0 P
b0 O
b10011 N
b0 M
b10 L
b10011 K
b100 J
b0 I
b0 H
b10 G
0F
b0 E
0D
b0 C
b10011 B
b100 A
b0 @
b0 ?
b0 >
b10010010 =
b10010010 <
b0 ;
b10010010 :
b0 9
b100 8
b100 7
b0 6
b10010010 5
14
b0 3
b100 2
b100 1
00
b10010010 /
b0 .
b0 -
b10010010 ,
b0 +
b1001001000101000001010010011 *
0)
bx (
1'
b10010010 &
b0 %
b10010010 $
0#
0"
0!
$end
#5
b100 &
b100 _
b100 k
b100 $
b100 =
b100 `
b100 5
b100 <
b100 R
b100 Z
b100 ,
b100 X
b100 a
b100 q
b100 :
b0 A
b0 J
b110 j
b100 i
b110 h
b0 .
b0 ?
b0 m
b10000110000001100010011 *
b10000110000001100010011 U
b10000110000001100010011 p
b1000 2
b1000 e
b1000 f
b1000 /
b1000 W
b1000 d
b1000 1
b1000 8
b1000 \
b1000 c
b100 3
b100 9
b100 V
b100 Y
b100 g
1!
#10
0!
#15
0#
b100 6
b100 >
b100 H
b100 M
1'
bx +
bx E
bx P
bx o
04
b1001 &
b1001 _
b1001 k
b0x0xx0xx100000001xx ,
b0x0xx0xx100000001xx X
b0x0xx0xx100000001xx a
b0x0xx0xx100000001xx q
b100 -
b100 S
b100 b
b100 l
b1001 ;
b1001 5
b1001 <
b1001 R
b1001 Z
b100000 A
b100000 J
b101 @
b101 I
b110011 B
b110011 K
b110011 N
b101 j
b110 i
b101 h
b10010110 :
b1000000011000101101001010110011 *
b1000000011000101101001010110011 U
b1000000011000101101001010110011 p
b1100 2
b1100 e
b1100 f
b10010010 .
b10010010 ?
b10010010 m
bx /
bx W
bx d
b1100 1
b1100 8
b1100 \
b1100 c
b1000 3
b1000 9
b1000 V
b1000 Y
b1000 g
1!
#20
0!
#25
b0 6
b0 >
b0 H
b0 M
b11111111111111111111111101101110 &
b11111111111111111111111101101110 _
b11111111111111111111111101101110 k
0#
b11111111111111111111111101101110 5
b11111111111111111111111101101110 <
b11111111111111111111111101101110 R
b11111111111111111111111101101110 Z
b11111111111111111111111101111010 /
b11111111111111111111111101111010 W
b11111111111111111111111101111010 d
b0 +
b0 E
b0 P
b0 o
14
b11111111111111111111111101101110 $
b11111111111111111111111101101110 =
b11111111111111111111111101101110 `
b11111111111111111111111101101110 ,
b11111111111111111111111101101110 X
b11111111111111111111111101101110 a
b11111111111111111111111101101110 q
b0 -
b0 S
b0 b
b0 l
b11111111111111111111111101101110 :
b1111011 A
b1111011 J
b0 @
b0 I
b10011 B
b10011 K
b10011 N
b111 j
b1110 i
b0 h
b0 ;
b0 .
b0 ?
b0 m
b11110110111000000000001110010011 *
b11110110111000000000001110010011 U
b11110110111000000000001110010011 p
b10000 2
b10000 e
b10000 f
b10000 1
b10000 8
b10000 \
b10000 c
b1100 3
b1100 9
b1100 V
b1100 Y
b1100 g
1!
#30
0!
#35
0#
b100 6
b100 >
b100 H
b100 M
b11111111111111111111111111110110 &
b11111111111111111111111111110110 _
b11111111111111111111111111110110 k
1'
b11111111111111111111111111110110 5
b11111111111111111111111111110110 <
b11111111111111111111111111110110 R
b11111111111111111111111111110110 Z
b100 $
b100 =
b100 `
bx +
bx E
bx P
bx o
04
b11111111111111111111111101110010 :
b0xxxx0xx1000000011x ,
b0xxxx0xx1000000011x X
b0xxxx0xx1000000011x a
b0xxxx0xx1000000011x q
b100 -
b100 S
b100 b
b100 l
b11111111111111111111111111110110 ;
b11111111111111111111111101101110 .
b11111111111111111111111101101110 ?
b11111111111111111111111101101110 m
b100000 A
b100000 J
b101 @
b101 I
b110011 B
b110011 K
b110011 N
b110 i
b111 h
b1000000011000111101001110110011 *
b1000000011000111101001110110011 U
b1000000011000111101001110110011 p
b10100 2
b10100 e
b10100 f
bx /
bx W
bx d
b10100 1
b10100 8
b10100 \
b10100 c
b10000 3
b10000 9
b10000 V
b10000 Y
b10000 g
1!
#40
0!
#45
x'
x#
bx 5
bx <
bx R
bx Z
bx &
bx _
bx k
bx 6
bx >
bx H
bx M
x4
bx %
bx C
bx O
bx ^
bx G
bx L
bx Q
x0
bx $
bx =
bx `
bx ,
bx X
bx a
bx q
x)
xF
xD
bx -
bx S
bx b
bx l
bx :
bx A
bx J
bx @
bx I
bx B
bx K
bx N
bx j
bx i
bx h
bx ;
bx .
bx ?
bx m
bx *
bx U
bx p
bx 2
bx e
bx f
b11000 1
b11000 8
b11000 \
b11000 c
b10100 3
b10100 9
b10100 V
b10100 Y
b10100 g
1!
#50
0!
#55
bx 1
bx 8
bx \
bx c
bx 3
bx 9
bx V
bx Y
bx g
1!
#60
0!
#65
1!
#70
0!
#75
1!
#80
0!
#85
1!
#90
0!
#95
1!
#100
0!
#105
1!
#110
0!
#115
1!
#120
0!
#125
1!
#130
0!
#135
1!
#140
0!
#145
1!
#150
0!
#155
1!
#160
0!
#165
1!
#170
0!
#175
0'
b0 :
00
b0 ;
b0 $
b0 =
b0 `
b0 ,
b0 X
b0 a
b0 q
0)
0F
0D
b0 A
b0 J
b0 @
b0 I
b0 B
b0 K
b0 N
b0 j
b0 i
b0 h
b0 .
b0 ?
b0 m
b0 -
b0 S
b0 b
b0 l
b0 (
b0 T
b0 [
b0 *
b0 U
b0 p
1"
1!
