2-2/Bilgisayar Organizasyonu/ödevler/2025/ödev 1/mert_guler/Q1/mux_2x1_32bit.v
module mux_2x1_32bit (a, b, select, out); 
    input [31:0] a, b; 
    input select; 
    output [31:0] out; 
    assign out = select ? b : a;
endmodule

2-2/Bilgisayar Organizasyonu/ödevler/2025/ödev 1/mert_guler/Q1/mux_8x1_32bit.v
`include "../01/mux_2x1_32bit.v"

module mux_8x1_32bit(a, b, c, d, e, f, g, h, select, result);
    input [31:0] a, b, c, d, e, f, g, h;
    input [2:0] select;
    output [31:0] result;

    wire [31:0] out1, out2, out3, out4, out5, out6;

    mux_2x1_32bit mux1(.a(a), .b(b), .select(select[0]), .out(out1));
    mux_2x1_32bit mux2(.a(c), .b(d), .select(select[0]), .out(out2));
    mux_2x1_32bit mux3(.a(e), .b(f), .select(select[0]), .out(out3));
    mux_2x1_32bit mux4(.a(g), .b(h), .select(select[0]), .out(out4));

    mux_2x1_32bit mux5(.a(out1), .b(out2), .select(select[1]), .out(out5));
    mux_2x1_32bit mux6(.a(out3), .b(out4), .select(select[1]), .out(out6));

    mux_2x1_32bit mux7(.a(out5), .b(out6), .select(select[2]), .out(result));
endmodule

2-2/Bilgisayar Organizasyonu/ödevler/2025/ödev 1/mert_guler/Q1/mux_8x1_32bit_tb.v
`include "mux_8x1_32bit.v"

module mux_8x1_32bit_tb;
    reg [31:0] a, b, c, d, e, f, g, h;
    reg [2:0] select;
    wire [31:0] result;

    mux_8x1_32bit mux(a, b, c, d, e, f, g, h, select, result);

    initial
    begin
        $dumpfile("mux_8x1_32bit.vcd");
        $dumpvars(0, mux_8x1_32bit_tb);

        a = 32'd1; b = 32'd2; c = 32'd3; d = 32'd4; e = 32'd5; f = 32'd6; g = 32'd7; h = 32'd8;
        select = 3'b000;
        #10

        a = 32'd1; b = 32'd2; c = 32'd3; d = 32'd4; e = 32'd5; f = 32'd6; g = 32'd7; h = 32'd8;
        select = 3'b001;
        #10

        a = 32'd1; b = 32'd2; c = 32'd3; d = 32'd4; e = 32'd5; f = 32'd6; g = 32'd7; h = 32'd8;
        select = 3'b010;
        #10

        a = 32'd1; b = 32'd2; c = 32'd3; d = 32'd4; e = 32'd5; f = 32'd6; g = 32'd7; h = 32'd8;
        select = 3'b011;
        #10

        a = 32'd1; b = 32'd2; c = 32'd3; d = 32'd4; e = 32'd5; f = 32'd6; g = 32'd7; h = 32'd8;
        select = 3'b100;
        #10

        a = 32'd1; b = 32'd2; c = 32'd3; d = 32'd4; e = 32'd5; f = 32'd6; g = 32'd7; h = 32'd8;
        select = 3'b101;
        #10

        a = 32'd1; b = 32'd2; c = 32'd3; d = 32'd4; e = 32'd5; f = 32'd6; g = 32'd7; h = 32'd8;
        select = 3'b110;
        #10

        a = 32'd1; b = 32'd2; c = 32'd3; d = 32'd4; e = 32'd5; f = 32'd6; g = 32'd7; h = 32'd8;
        select = 3'b111;
        #10

        $finish;
    end
endmodule

2-2/Bilgisayar Organizasyonu/ödevler/2025/ödev 1/mert_guler/Q1/mux_8x1_32bit.vcd
$date
	Wed Apr 16 15:37:56 2025
$end
$version
	Icarus Verilog
$end
$timescale
	1s
$end
$scope module mux_8x1_32bit_tb $end
$var wire 32 ! result [31:0] $end
$var reg 32 " a [31:0] $end
$var reg 32 # b [31:0] $end
$var reg 32 $ c [31:0] $end
$var reg 32 % d [31:0] $end
$var reg 32 & e [31:0] $end
$var reg 32 ' f [31:0] $end
$var reg 32 ( g [31:0] $end
$var reg 32 ) h [31:0] $end
$var reg 3 * select [2:0] $end
$scope module mux $end
$var wire 32 + a [31:0] $end
$var wire 32 , b [31:0] $end
$var wire 32 - c [31:0] $end
$var wire 32 . d [31:0] $end
$var wire 32 / e [31:0] $end
$var wire 32 0 f [31:0] $end
$var wire 32 1 g [31:0] $end
$var wire 32 2 h [31:0] $end
$var wire 3 3 select [2:0] $end
$var wire 32 4 result [31:0] $end
$var wire 32 5 out6 [31:0] $end
$var wire 32 6 out5 [31:0] $end
$var wire 32 7 out4 [31:0] $end
$var wire 32 8 out3 [31:0] $end
$var wire 32 9 out2 [31:0] $end
$var wire 32 : out1 [31:0] $end
$scope module mux1 $end
$var wire 32 ; a [31:0] $end
$var wire 32 < b [31:0] $end
$var wire 1 = select $end
$var wire 32 > out [31:0] $end
$upscope $end
$scope module mux2 $end
$var wire 32 ? a [31:0] $end
$var wire 32 @ b [31:0] $end
$var wire 1 A select $end
$var wire 32 B out [31:0] $end
$upscope $end
$scope module mux3 $end
$var wire 32 C a [31:0] $end
$var wire 32 D b [31:0] $end
$var wire 1 E select $end
$var wire 32 F out [31:0] $end
$upscope $end
$scope module mux4 $end
$var wire 32 G a [31:0] $end
$var wire 32 H b [31:0] $end
$var wire 1 I select $end
$var wire 32 J out [31:0] $end
$upscope $end
$scope module mux5 $end
$var wire 32 K a [31:0] $end
$var wire 32 L b [31:0] $end
$var wire 1 M select $end
$var wire 32 N out [31:0] $end
$upscope $end
$scope module mux6 $end
$var wire 32 O a [31:0] $end
$var wire 32 P b [31:0] $end
$var wire 1 Q select $end
$var wire 32 R out [31:0] $end
$upscope $end
$scope module mux7 $end
$var wire 32 S a [31:0] $end
$var wire 32 T b [31:0] $end
$var wire 1 U select $end
$var wire 32 V out [31:0] $end
$upscope $end
$upscope $end
$upscope $end
$enddefinitions $end
$comment Show the parameter values. $end
$dumpall
$end
#0
$dumpvars
b1 V
0U
b101 T
b1 S
b101 R
0Q
b111 P
b101 O
b1 N
0M
b11 L
b1 K
b111 J
0I
b1000 H
b111 G
b101 F
0E
b110 D
b101 C
b11 B
0A
b100 @
b11 ?
b1 >
0=
b10 <
b1 ;
b1 :
b11 9
b101 8
b111 7
b1 6
b101 5
b1 4
b0 3
b1000 2
b111 1
b110 0
b101 /
b100 .
b11 -
b10 ,
b1 +
b0 *
b1000 )
b111 (
b110 '
b101 &
b100 %
b11 $
b10 #
b1 "
b1 !
$end
#10
b10 !
b10 4
b10 V
b10 6
b10 N
b10 S
b110 5
b110 R
b110 T
b10 :
b10 >
b10 K
b100 9
b100 B
b100 L
b110 8
b110 F
b110 O
b1000 7
b1000 J
b1000 P
1=
1A
1E
1I
b1 *
b1 3
#20
b11 !
b11 4
b11 V
b1 :
b1 >
b1 K
b11 9
b11 B
b11 L
b101 8
b101 F
b101 O
b111 7
b111 J
b111 P
b11 6
b11 N
b11 S
b111 5
b111 R
b111 T
0=
0A
0E
0I
1M
1Q
b10 *
b10 3
#30
b100 !
b100 4
b100 V
b100 6
b100 N
b100 S
b1000 5
b1000 R
b1000 T
b10 :
b10 >
b10 K
b100 9
b100 B
b100 L
b110 8
b110 F
b110 O
b1000 7
b1000 J
b1000 P
1=
1A
1E
1I
b11 *
b11 3
#40
b1 :
b1 >
b1 K
b11 9
b11 B
b11 L
b101 8
b101 F
b101 O
b111 7
b111 J
b111 P
b1 6
b1 N
b1 S
b101 5
b101 R
b101 T
b101 !
b101 4
b101 V
0=
0A
0E
0I
0M
0Q
1U
b100 *
b100 3
#50
b110 !
b110 4
b110 V
b10 6
b10 N
b10 S
b110 5
b110 R
b110 T
b10 :
b10 >
b10 K
b100 9
b100 B
b100 L
b110 8
b110 F
b110 O
b1000 7
b1000 J
b1000 P
1=
1A
1E
1I
b101 *
b101 3
#60
b111 !
b111 4
b111 V
b1 :
b1 >
b1 K
b11 9
b11 B
b11 L
b101 8
b101 F
b101 O
b111 7
b111 J
b111 P
b11 6
b11 N
b11 S
b111 5
b111 R
b111 T
0=
0A
0E
0I
1M
1Q
b110 *
b110 3
#70
b1000 !
b1000 4
b1000 V
b100 6
b100 N
b100 S
b1000 5
b1000 R
b1000 T
b10 :
b10 >
b10 K
b100 9
b100 B
b100 L
b110 8
b110 F
b110 O
b1000 7
b1000 J
b1000 P
1=
1A
1E
1I
b111 *
b111 3
